Workbook

Sheet Forside
B2: =Tekstnøgler!C33 -> Resultat
B5: =Hovedresultater!C5 -> Resultat for 0 (År) - Tiltagscase
B6: =Hovedresultater!C6 -> 10.230,61 ton CO₂e
B8: =Tekstnøgler!C3 -> Download af resultater
B10: =Tekstnøgler!C4 -> I dette Excel regneark, kan du finde alle resultater som du kunne se på Klimakompasset for den beregning du har valgt (se navn på beregning ovenfor). Herunder kan du se en liste af de resultater og data, du har adgang til. Da navne på individuelle ark i bunden af Excel-arket ikke ændres, når du vælger mellem dansk og engelsk sprog, er det skrevet ind, hvilke ark de danske titler referer til.
B12: =Tekstnøgler!C5 -> Vælg af sprog | D12: Dansk | E12: =Tekstnøgler!C6 -> <-- klik på cellen
B15: =Tekstnøgler!C7 -> Indholdsfortegnelse
B17: =Tekstnøgler!C8 -> Generelle oplysninger om beregningen | F17: =Tekstnøgler!C587 -> Henviser til ark:
B18: 1. | C18: =Tekstnøgler!C9 -> Forside | F18: =Tekstnøgler!E9 -> Forside
B19: 2. | C19: =Tekstnøgler!C10 -> Stamdata | F19: =Tekstnøgler!E10 -> Stamdata
B20: 3. | C20: =Tekstnøgler!C11 -> Kontaktoplysninger | F20: =Tekstnøgler!E11 -> Kontaktoplysninger
B22: =Tekstnøgler!C12 -> Resultater
B23: 4. | C23: =Tekstnøgler!C13 -> Hovedresultater | F23: =Tekstnøgler!E13 -> Hovedresultater
B24: 5. | C24: =Tekstnøgler!C14 -> Delresultater | F24: =Tekstnøgler!E14 -> Delresultater
B25: 6. | C25: =Tekstnøgler!C15 -> Hovedresultater (GHG) | F25: =Tekstnøgler!E15 -> Hovedresultater (GHG)
B26: 7. | C26: =Tekstnøgler!C16 -> Delresultater (GHG) | F26: =Tekstnøgler!E16 -> Delresultater (GHG)
B27: 8. | C27: =Tekstnøgler!C17 -> E-nøgletal (ESG) | F27: =Tekstnøgler!E17 -> E-nøgletal (ESG)
B28: 9. | C28: =Tekstnøgler!C18 -> Scope 3 kategorier | F28: =Tekstnøgler!E18 -> Scope 3 kategorier
B29: 10. | C29: =Tekstnøgler!C19 -> Største udledningsposter | F29: =Tekstnøgler!E19 -> Største udledningsposter
B31: =Tekstnøgler!C20 -> Fremskrivning & Reduktionsmålsætninger
B32: 11. | C32: =Tekstnøgler!C21 -> Fremskrivning - Hovedresultater | F32: =Tekstnøgler!E21 -> Fremskrivning - Hovedresultater
B33: 12. | C33: =Tekstnøgler!C22 -> Fremskrivning - Delresultater | F33: =Tekstnøgler!E22 -> Fremskrivning - Delresultater
B34: 13. | C34: =Tekstnøgler!C23 -> Reduktionsmålsætninger | F34: =Tekstnøgler!E23 -> Reduktionsmålsætninger
B36: =Tekstnøgler!C24 -> Data
B37: a. | C37: =Tekstnøgler!C25 -> Emissionsfaktorer | F37: =Tekstnøgler!E25 -> Emissionsfaktorer
B38: b. | C38: =Tekstnøgler!C26 -> Egne emissionsfaktorer | F38: =Tekstnøgler!E26 -> Egne emissionsfaktorer
B39: c. | C39: =Tekstnøgler!C27 -> Fremskrevne emissionsfaktorer | F39: =Tekstnøgler!E27 -> Fremskrevne emissionsfaktorer
B40: d. | C40: =Tekstnøgler!C28 -> Data (alle poster) | F40: =Tekstnøgler!E28 -> Data (alle poster)
B41: e. | C41: =Tekstnøgler!C29 -> Data (E-nøgletal) | F41: =Tekstnøgler!E29 -> Data (E-nøgletal)
B43: =Tekstnøgler!C30 -> Til udviklerne | E43: Skjult række
B44: 19. | C44: =Tekstnøgler!C31 -> Til udviklerne | E44: Skjult række
B45: 20. | C45: =Tekstnøgler!C32 -> Tekstnøgler | E45: Skjult række

Sheet Stamdata
B2: =Tekstnøgler!C37 -> Stamdata | I2: =Tekstnøgler!C2 -> <-- Gå til forsiden
B5: =Tekstnøgler!C38 -> Om beregningen
B7: =Tekstnøgler!C39 -> Navn på beregning
B8: 0 (År) - Tiltagscase
B10: =Tekstnøgler!C40 -> Formål med beregningen
B11: =Tekstnøgler!C44 -> 4. Beregn klimaaftrykket for din virksomhed (ingen krav om CVR nr.).
B13: =Tekstnøgler!C45 -> Start dato - Klimaopgørelser laves typisk for et kalenderår
B14: =DATE(2021,1,1) -> 44197 | C14: =IF(OR(ISBLANK(B14),ISTEXT(B14)),Tekstnøgler!C533,"")
B16: =Tekstnøgler!C46 -> Slut dato
B17: =DATE(2021,12,31) -> 44561 | C17: =IF(YEAR(B17)-YEAR(B14)>2,Tekstnøgler!C592,"")
B19: =Tekstnøgler!C47 -> Kommentarer til beregningen
B24: =Tekstnøgler!C48 -> Din virksomhed
B26: =Tekstnøgler!C49 -> CVR
B29: =Tekstnøgler!C50 -> Virksomhedens navn
B30: Testvirksomhed
B34: =Tekstnøgler!C51 -> Virksomhed som beregningen vedrører
B36: =Tekstnøgler!C52 -> Land
B37: Danmark
B39: =Tekstnøgler!C49 -> CVR
B42: =Tekstnøgler!C48 -> Din virksomhed
B43: Tiltagscase - 0
B45: =Tekstnøgler!C53 -> P-nummer
B48: Branche [kommer senere]
B53: =Tekstnøgler!C60 -> Nøgletal
B55: =Tekstnøgler!C61 -> Antal fuldtidsansatte
B56: 50
B58: =Tekstnøgler!C62 -> Nettoomsætning, mio. kr.
B59: 23
B61: =Tekstnøgler!C63 -> Antal m2 bygningsareal
B62: 5000

Sheet Kontaktoplysninger
B2: =Tekstnøgler!C64 -> Kontaktoplysninger | I2: =Tekstnøgler!C2 -> <-- Gå til forsiden
B5: =Tekstnøgler!C65 -> Virksomhedsoplysninger
B7: =Tekstnøgler!C66 -> Virksomhedens e-mailadresse
B11: =Tekstnøgler!C67 -> Kontaktperson
B13: =Tekstnøgler!C68 -> Fornavn
B14: Victor
B16: =Tekstnøgler!C69 -> Efternavn
B17: Skovmand
B19: =Tekstnøgler!C70 -> E-mail
B20: VicSko@erst.dk

Sheet Hovedresultater
C2: =Tekstnøgler!C33 -> Resultat | H2: =Tekstnøgler!C2 -> <-- Gå til forsiden
C5: =Tekstnøgler!C34&" "&Stamdata!B8 -> Resultat for 0 (År) - Tiltagscase
C6: =TEXT(D29, "#.##0,00") & " " & Tekstnøgler!C582 -> 10.230,61 ton CO₂e
C8: =Tekstnøgler!C71 -> Metodevalg | D8: xxxx
C10: =Tekstnøgler!C72 -> Resultaterne baserer sig på en række metodiske valg, der er foretaget i forbindelse med beregningerne. I nedenstående tabel kan du se, hvorvidt Radiative Forcing Index (RFI) er medregnet i forbindelse med udledninger fra flytransport. At medregne (eller korrigere for) RFI betyder, at der er taget højde for, at CO₂e udledt højere oppe i atmosfæren har en større drivhuseffekt end CO₂e udledt ved landjorden. Tabellen viser også, om emissionsfaktoren for el baserer sig på det årlige gennemsnit for sammensætningen af produktionen af el (miljødeklaration), eller om der i emissionsfaktoren korrigeres for virksomheders køb af grønne certifikater, såkaldte oprindelsesgarantier (eldeklaration).
C12: =Tekstnøgler!C73 -> Emissionsfaktor | E12: =Tekstnøgler!C74 -> Metodevalg
C13: =Tekstnøgler!C75 -> Valg af emissionsfaktor for elektricitet | E13: =Tekstnøgler!C79 -> Eldeklaration
C14: =Tekstnøgler!C76 -> Emissionsfaktor for flytransport | E14: =Tekstnøgler!C78 -> Inkluder RFI
C17: =Tekstnøgler!C81 -> Hovedresultater
C19: =Tekstnøgler!C82 -> Virksomhedens samlede CO₂e-udledning er angivet i tabel 1. CO₂e-udledningen er angivet i ton CO₂-ækvivalenter, og tabellen viser udledningen fordelt på de forskellige hovedkategorier. Bemærk, at udenfor scopes ikke medregnes i klimaaftrykket ifølge GHG-protokollen, men kan oplyses særskilt.
C21: =Tekstnøgler!C83 -> Tabel 1: Oversigt over virksomhedens CO₂e-udledninger
C22: =Tekstnøgler!C84 -> Hovedkategori | D22: =Tekstnøgler!C85 -> Udledning i ton CO₂e (scope 1+2+3) | E22: =Tekstnøgler!C86 -> Andel af udledning (scope 1+2+3) | F22: =Tekstnøgler!C110 -> Udledning i ton CO₂e (udenfor scopes)
C24: =Tekstnøgler!C90 -> Energi og processer | D24: =Delresultater!D24 -> 2699.8361 | E24: =IF($D$29 = 0,"",$D24/$D$29) -> 0.2638979 | F24: =Delresultater!F24 -> 137.48754
C25: =Tekstnøgler!C91 -> Indkøb | D25: =Delresultater!D36 -> 6765.5856 | E25: =IF($D$29 = 0,"",$D25/$D$29) -> 0.66130823 | F25: =Delresultater!F36 -> 0
C26: =Tekstnøgler!C92 -> Transport | D26: =Delresultater!D65 -> 765.18681 | E26: =IF($D$29 = 0,"",$D26/$D$29) -> 0.07479387 | F26: =Delresultater!F65 -> 41.952344
C27: =Tekstnøgler!C93 -> Affald og genbrug | D27: =Delresultater!D84 -> 0 | E27: =IF($D$29 = 0,"",$D27/$D$29) -> 0 | F27: =Delresultater!F84 -> -128.21782
C28: =Tekstnøgler!C94 -> Solgte produkter | D28: =Delresultater!D89 -> 0 | E28: =IF($D$29 = 0,"",$D28/$D$29) -> 0 | F28: =Delresultater!F89 -> -111.89732
C29: =Tekstnøgler!C95 -> Total | D29: =SUM(D24:D28) -> 10230.609 | E29: =SUM(E24:E28) -> 1 | F29: =SUM(F24:F28) -> -60.675259
C32: =Tekstnøgler!C96 -> Opsummering af virksomhedens beregnede CO₂e-udledning
C34: =Tekstnøgler!C97 -> Nedenstående figurer opsummerer virksomhedens beregnede CO₂e-udledning. Figur 1 angiver virksomhedens absolutte CO₂e-udledning i ton CO₂e-ækvivalenter fordelt på hovedkategorier. Figur 2 viser den procentuelle fordeling af CO₂e-udledningen fordelt på hovedkategorier.
C36: =Tekstnøgler!C98 -> Figur 1: CO₂e-udledning i ton (scope 1+2+3) fordelt på hovedkategorier | G36: =Tekstnøgler!C99 -> Figur 2: Procentfordeling af CO₂e-udledning (scope 1+2+3) fordelt på hovedkategorier
C57: =Tekstnøgler!C100 -> Figur 3: CO₂e-udledning i ton (udenfor scopes) fordelt på hovedkategorier
C78: =Tekstnøgler!C102 -> Nøgletal
C80: =Tekstnøgler!C103 -> Denne tabel viser beregninger af nøgletal i tilfælde af, at der under Stamdata er indtastet data for hhv. antal fuldtidsansatte i virksomheden, nettoomsætning og areal.
C81: =Tekstnøgler!C104 -> Nøgletalsberegninger | E81: =Tekstnøgler!C105 -> Ton CO₂e
C82: =Tekstnøgler!C106 -> CO₂e pr. ansat | E82: =IF(ISBLANK(Stamdata!B56),"",D29/Stamdata!B56) -> 204.61217
C83: =Tekstnøgler!C107 -> CO₂e pr. mio. kr. nettoomsætning | E83: =IF(ISBLANK(Stamdata!B59),"",D29/Stamdata!B59) -> 444.80907
C84: =Tekstnøgler!C108 -> CO₂e pr. m2 | E84: =IF(ISBLANK(Stamdata!B62),"",D29/Stamdata!B62) -> 2.0461217
C87: =Tekstnøgler!C109 -> Egne bemærkninger

Sheet Delresultater
C2: =Tekstnøgler!C33 -> Resultat | F2: =Tekstnøgler!C2 -> <-- Gå til forsiden
C5: =Hovedresultater!C5 -> Resultat for 0 (År) - Tiltagscase
C6: =Hovedresultater!C6 -> 10.230,61 ton CO₂e
C8: =Tekstnøgler!C71 -> Metodevalg
C10: =Tekstnøgler!C72 -> Resultaterne baserer sig på en række metodiske valg, der er foretaget i forbindelse med beregningerne. I nedenstående tabel kan du se, hvorvidt Radiative Forcing Index (RFI) er medregnet i forbindelse med udledninger fra flytransport. At medregne (eller korrigere for) RFI betyder, at der er taget højde for, at CO₂e udledt højere oppe i atmosfæren har en større drivhuseffekt end CO₂e udledt ved landjorden. Tabellen viser også, om emissionsfaktoren for el baserer sig på det årlige gennemsnit for sammensætningen af produktionen af el (miljødeklaration), eller om der i emissionsfaktoren korrigeres for virksomheders køb af grønne certifikater, såkaldte oprindelsesgarantier (eldeklaration).
C12: =Tekstnøgler!C73 -> Emissionsfaktor | D12: =Tekstnøgler!C74 -> Metodevalg
C13: =Tekstnøgler!C75 -> Valg af emissionsfaktor for elektricitet | D13: =IF(ISBLANK(Hovedresultater!$E13),"",Hovedresultater!$E13) -> Eldeklaration
C14: =Tekstnøgler!C76 -> Emissionsfaktor for flytransport | D14: =IF(ISBLANK(Hovedresultater!$E14),"",Hovedresultater!$E14) -> Inkluder RFI
C17: =Tekstnøgler!C112 -> Delresultater
C19: =Tekstnøgler!C113 -> Her ses en mere detaljeret resultatvisning. Tabellen viser alle underkategorierne, der kan angives data for, den tilhørende udledning i ton CO₂e og underkategoriens samlede andel af de totale udledninger.
C21: =Tekstnøgler!C114 -> Oversigt over CO₂e-udledningen fordelt på hoved- og underkategorier
C22: =Tekstnøgler!C115 -> Hovedkategori | D22: =Tekstnøgler!C85 -> Udledning i ton CO₂e (scope 1+2+3) | E22: =Tekstnøgler!C86 -> Andel af udledning (scope 1+2+3) | F22: =Tekstnøgler!C87 -> Udledning i ton CO₂e (udenfor scopes)
C24: =Tekstnøgler!C90 -> Energi og processer | D24: =D25+D28+D32+D35 -> 2699.8361 | E24: =E25+E28+E32+E35 -> 0.2638979 | F24: =F25+F28+F32+F35 -> 137.48754
C25: =Tekstnøgler!C121 -> Elektricitet | D25: =SUM(D26:D27) -> 2182.8961 | E25: =SUM(E26:E27) -> 0.21336914 | F25: =SUM(F26:F27) -> 129.88681
C26: =Tekstnøgler!C122 -> Forbrug af elektricitet | D26: =SUM('Delresultater (GHG)'!D26:F26) -> 2182.8961 | E26: =IF($D$98 = 0,0,$D26/$D$98) -> 0.21336914 | F26: ='Delresultater (GHG)'!D110 -> 129.88681
C27: =Tekstnøgler!C123 -> Forbrug af elektricitet med egne emissionsfaktorer | D27: =SUM('Delresultater (GHG)'!D27:F27) -> 0 | E27: =IF($D$98 = 0,0,$D27/$D$98) -> 0 | F27: ='Delresultater (GHG)'!D111 -> 0
C28: =Tekstnøgler!C124 -> Varme og procesenergi | D28: =SUM(D29:D31) -> 516.93997 | E28: =SUM(E29:E31) -> 0.05052876 | F28: =SUM(F29:F31) -> 7.6007239
C29: =Tekstnøgler!C125 -> Fjernvarme | D29: =SUM('Delresultater (GHG)'!D29:F29) -> 0 | E29: =IF($D$98 = 0,0,$D29/$D$98) -> 0 | F29: ='Delresultater (GHG)'!D113 -> 0
C30: =Tekstnøgler!C126 -> Brændsler | D30: =SUM('Delresultater (GHG)'!D30:F30) -> 516.93997 | E30: =IF($D$98 = 0,0,$D30/$D$98) -> 0.05052876 | F30: ='Delresultater (GHG)'!D114 -> 7.6007239
C31: =Tekstnøgler!C127 -> Varme og procesenergi med egne emissionsfaktorer | D31: =SUM('Delresultater (GHG)'!D31:F31) -> 0 | E31: =IF($D$98 = 0,0,$D31/$D$98) -> 0 | F31: ='Delresultater (GHG)'!D115 -> 0
C32: =Tekstnøgler!C128 -> Procesudledning | D32: =SUM(D33:D34) -> 0 | E32: =SUM(E33:E34) -> 0 | F32: =SUM(F33:F34) -> 0
C33: =Tekstnøgler!C129 -> Procesudledning | D33: =SUM('Delresultater (GHG)'!D33:F33) -> 0 | E33: =IF($D$98 = 0,0,$D33/$D$98) -> 0 | F33: ='Delresultater (GHG)'!D117 -> 0
C34: =Tekstnøgler!C130 -> Procesudledning med egne emissionsfaktorer | D34: =SUM('Delresultater (GHG)'!D34:F34) -> 0 | E34: =IF($D$98 = 0,0,$D34/$D$98) -> 0 | F34: ='Delresultater (GHG)'!D118 -> 0
C35: =Tekstnøgler!C131 -> Andet udledning ved energi og processer | D35: =SUM('Delresultater (GHG)'!D35:F35) -> 0 | E35: =IF($D$98 = 0,0,$D35/$D$98) -> 0 | F35: ='Delresultater (GHG)'!D119 -> 0
C36: =Tekstnøgler!C91 -> Indkøb | D36: =D37+D51 -> 6765.5856 | E36: =E37+E51 -> 0.66130823 | F36: =F37+F51 -> 0
C37: =Tekstnøgler!C133 -> Primære indkøb af råvarer til produktion | D37: =D38+D43+D48 -> 6765.5856 | E37: =E38+E43+E48 -> 0.66130823 | F37: =F38+F43+F48 -> 0
C38: =Tekstnøgler!C134 -> Materialer (primære indkøb) | D38: =SUM(D39:D42) -> 6760.9302 | E38: =SUM(E39:E42) -> 0.66085318 | F38: =SUM(F39:F42) -> 0
C39: =Tekstnøgler!C135 -> Indkøb af materialer i fysiske enheder | D39: =SUM('Delresultater (GHG)'!D39:F39) -> 6760.9302 | E39: =IF($D$98 = 0,0,$D39/$D$98) -> 0.66085318 | F39: ='Delresultater (GHG)'!D123 -> 0
C40: =Tekstnøgler!C136 -> Indkøb af materialer i monetære enheder (beløb i DKK) | D40: =SUM('Delresultater (GHG)'!D40:F40) -> 0 | E40: =IF($D$98 = 0,0,$D40/$D$98) -> 0 | F40: ='Delresultater (GHG)'!D124 -> 0
C41: =Tekstnøgler!C137 -> Fysiske enheder med egne emissionsfaktorer | D41: =SUM('Delresultater (GHG)'!D41:F41) -> 0 | E41: =IF($D$98 = 0,0,$D41/$D$98) -> 0 | F41: ='Delresultater (GHG)'!D125 -> 0
C42: =Tekstnøgler!C138 -> Monetære enheder (beløb i DKK) med egne emissionsfaktorer | D42: =SUM('Delresultater (GHG)'!D42:F42) -> 0 | E42: =IF($D$98 = 0,0,$D42/$D$98) -> 0 | F42: ='Delresultater (GHG)'!D126 -> 0
C43: =Tekstnøgler!C139 -> Produkter og services (primære indkøb) | D43: =SUM(D44:D47) -> 4.6554366 | E43: =SUM(E44:E47) -> 0.00045504982 | F43: =SUM(F44:F47) -> 0
C44: =Tekstnøgler!C140 -> Indkøb af produkter i fysiske enheder | D44: =SUM('Delresultater (GHG)'!D44:F44) -> 4.6554366 | E44: =IF($D$98 = 0,0,$D44/$D$98) -> 0.00045504982 | F44: ='Delresultater (GHG)'!D128 -> 0
C45: =Tekstnøgler!C141 -> Indkøb af produkter i monetære enheder (beløb i DKK) | D45: =SUM('Delresultater (GHG)'!D45:F45) -> 0 | E45: =IF($D$98 = 0,0,$D45/$D$98) -> 0 | F45: ='Delresultater (GHG)'!D129 -> 0
C46: =Tekstnøgler!C142 -> Fysiske enheder med egne emissionsfaktorer | D46: =SUM('Delresultater (GHG)'!D46:F46) -> 0 | E46: =IF($D$98 = 0,0,$D46/$D$98) -> 0 | F46: ='Delresultater (GHG)'!D130 -> 0
C47: =Tekstnøgler!C143 -> Monetære enheder (beløb i DKK) med egne emissionsfaktorer | D47: =SUM('Delresultater (GHG)'!D47:F47) -> 0 | E47: =IF($D$98 = 0,0,$D47/$D$98) -> 0 | F47: ='Delresultater (GHG)'!D131 -> 0
C48: =Tekstnøgler!C144 -> Andet udledning ved primære indkøb | D48: =SUM(D49:D50) -> 0 | E48: =SUM(E49:E50) -> 0 | F48: =SUM(F49:F50) -> 0
C49: =Tekstnøgler!C145 -> Fysiske enheder med egne emissionsfaktorer | D49: =SUM('Delresultater (GHG)'!D49:F49) -> 0 | E49: =IF($D$98 = 0,0,$D49/$D$98) -> 0 | F49: ='Delresultater (GHG)'!D133 -> 0
C50: =Tekstnøgler!C146 -> Monetære enheder (beløb i DKK) med egne emissionsfaktorer | D50: =SUM('Delresultater (GHG)'!D50:F50) -> 0 | E50: =IF($D$98 = 0,0,$D50/$D$98) -> 0 | F50: ='Delresultater (GHG)'!D134 -> 0
C51: =Tekstnøgler!C147 -> Sekundære indkøb af hjælpematerialer og serviceydelser | D51: =D52+D57+D62 -> 0 | E51: =E52+E57+E62 -> 0 | F51: =F52+F57+F62 -> 0
C52: =Tekstnøgler!C148 -> Materialer (sekundære indkøb) | D52: =SUM(D53:D56) -> 0 | E52: =SUM(E53:E56) -> 0 | F52: =SUM(F53:F56) -> 0
C53: =Tekstnøgler!C149 -> Indkøb af materialer i fysiske enheder | D53: =SUM('Delresultater (GHG)'!D53:F53) -> 0 | E53: =IF($D$98 = 0,0,$D53/$D$98) -> 0 | F53: ='Delresultater (GHG)'!D137 -> 0
C54: =Tekstnøgler!C150 -> Indkøb af materialer i monetære enheder (beløb i DKK) | D54: =SUM('Delresultater (GHG)'!D54:F54) -> 0 | E54: =IF($D$98 = 0,0,$D54/$D$98) -> 0 | F54: ='Delresultater (GHG)'!D138 -> 0
C55: =Tekstnøgler!C151 -> Fysiske enheder med egne emissionsfaktorer | D55: =SUM('Delresultater (GHG)'!D55:F55) -> 0 | E55: =IF($D$98 = 0,0,$D55/$D$98) -> 0 | F55: ='Delresultater (GHG)'!D139 -> 0
C56: =Tekstnøgler!C152 -> Monetære enheder (beløb i DKK) med egne emissionsfaktorer | D56: =SUM('Delresultater (GHG)'!D56:F56) -> 0 | E56: =IF($D$98 = 0,0,$D56/$D$98) -> 0 | F56: ='Delresultater (GHG)'!D140 -> 0
C57: =Tekstnøgler!C153 -> Produkter og services (sekundære indkøb) | D57: =SUM(D58:D61) -> 0 | E57: =SUM(E58:E61) -> 0 | F57: =SUM(F58:F61) -> 0
C58: =Tekstnøgler!C154 -> Indkøb af produkter i fysiske enheder | D58: =SUM('Delresultater (GHG)'!D58:F58) -> 0 | E58: =IF($D$98 = 0,0,$D58/$D$98) -> 0 | F58: ='Delresultater (GHG)'!D142 -> 0
C59: =Tekstnøgler!C155 -> Indkøb af produkter i monetære enheder (beløb i DKK) | D59: =SUM('Delresultater (GHG)'!D59:F59) -> 0 | E59: =IF($D$98 = 0,0,$D59/$D$98) -> 0 | F59: ='Delresultater (GHG)'!D143 -> 0
C60: =Tekstnøgler!C156 -> Fysiske enheder med egne emissionsfaktorer | D60: =SUM('Delresultater (GHG)'!D60:F60) -> 0 | E60: =IF($D$98 = 0,0,$D60/$D$98) -> 0 | F60: ='Delresultater (GHG)'!D144 -> 0
C61: =Tekstnøgler!C157 -> Monetære enheder (beløb i DKK) med egne emissionsfaktorer | D61: =SUM('Delresultater (GHG)'!D61:F61) -> 0 | E61: =IF($D$98 = 0,0,$D61/$D$98) -> 0 | F61: ='Delresultater (GHG)'!D145 -> 0
C62: =Tekstnøgler!C158 -> Andet udledning ved sekundære indkøb | D62: =SUM(D63:D64) -> 0 | E62: =SUM(E63:E64) -> 0 | F62: =SUM(F63:F64) -> 0
C63: =Tekstnøgler!C159 -> Fysiske enheder med egne emissionsfaktorer | D63: =SUM('Delresultater (GHG)'!D63:F63) -> 0 | E63: =IF($D$98 = 0,0,$D63/$D$98) -> 0 | F63: ='Delresultater (GHG)'!D147 -> 0
C64: =Tekstnøgler!C160 -> Monetære enheder (beløb i DKK) med egne emissionsfaktorer | D64: =SUM('Delresultater (GHG)'!D64:F64) -> 0 | E64: =IF($D$98 = 0,0,$D64/$D$98) -> 0 | F64: ='Delresultater (GHG)'!D148 -> 0
C65: =Tekstnøgler!C92 -> Transport | D65: =D66+D70+D75+D79+D83 -> 765.18681 | E65: =E66+E70+E75+E79+E83 -> 0.07479387 | F65: =F66+F70+F75+F79+F83 -> 41.952344
C66: =Tekstnøgler!C162 -> Egne og leasede transportmidler | D66: =SUM(D67:D69) -> 10.049122 | E66: =SUM(E67:E69) -> 0.00098226042 | F66: =SUM(F67:F69) -> 0.5543102
C67: =Tekstnøgler!C163 -> Egne og leasede transportmidler | D67: =SUM('Delresultater (GHG)'!D67:F67) -> 10.049122 | E67: =IF($D$98 = 0,0,$D67/$D$98) -> 0.00098226042 | F67: ='Delresultater (GHG)'!D151 -> 0.5543102
C68: =Tekstnøgler!C164 -> Fly og Skibe | D68: =SUM('Delresultater (GHG)'!D68:F68) -> 0 | E68: =IF($D$98 = 0,0,$D68/$D$98) -> 0 | F68: ='Delresultater (GHG)'!D152 -> 0
C69: =Tekstnøgler!C165 -> Egne og leasede transportmidler med egne emissionsfaktorer | D69: =SUM('Delresultater (GHG)'!D69:F69) -> 0 | E69: =IF($D$98 = 0,0,$D69/$D$98) -> 0 | F69: ='Delresultater (GHG)'!D153 -> 0
C70: =Tekstnøgler!C166 -> Medarbejdertransport | D70: =SUM(D71:D74) -> 3.6176839 | E70: =SUM(E71:E74) -> 0.00035361375 | F70: =SUM(F71:F74) -> 0.19955167
C71: =Tekstnøgler!C167 -> Pendling | D71: =SUM('Delresultater (GHG)'!D71:F71) -> 3.6176839 | E71: =IF($D$98 = 0,0,$D71/$D$98) -> 0.00035361375 | F71: ='Delresultater (GHG)'!D155 -> 0.19955167
C72: =Tekstnøgler!C168 -> Rejser i forbindelse med arbejder - Fysiske enheder | D72: =SUM('Delresultater (GHG)'!D72:F72) -> 0 | E72: =IF($D$98 = 0,0,$D72/$D$98) -> 0 | F72: ='Delresultater (GHG)'!D156 -> 0
C73: =Tekstnøgler!C169 -> Rejser i forbindelse med arbejder - Monetære enheder (beløb i DKK) | D73: =SUM('Delresultater (GHG)'!D73:F73) -> 0 | E73: =IF($D$98 = 0,0,$D73/$D$98) -> 0 | F73: ='Delresultater (GHG)'!D157 -> 0
C74: =Tekstnøgler!C170 -> Medarbejdertransport med egne emissionsfaktorer | D74: =SUM('Delresultater (GHG)'!D74:F74) -> 0 | E74: =IF($D$98 = 0,0,$D74/$D$98) -> 0 | F74: ='Delresultater (GHG)'!D158 -> 0
C75: =Tekstnøgler!C171 -> Varetransport til virksomhed | D75: =SUM(D76:D78) -> 204.96 | E75: =SUM(E76:E78) -> 0.020033999 | F75: =SUM(F76:F78) -> 11.23595
C76: =Tekstnøgler!C172 -> Varetransport i fysiske enheder | D76: =SUM('Delresultater (GHG)'!D76:F76) -> 204.96 | E76: =IF($D$98 = 0,0,$D76/$D$98) -> 0.020033999 | F76: ='Delresultater (GHG)'!D160 -> 11.23595
C77: =Tekstnøgler!C173 -> Varetransport i monetære enheder (beløb i DKK) | D77: =SUM('Delresultater (GHG)'!D77:F77) -> 0 | E77: =IF($D$98 = 0,0,$D77/$D$98) -> 0 | F77: ='Delresultater (GHG)'!D161 -> 0
C78: =Tekstnøgler!C174 -> Varetransport til virksomhed med egne emissionsfaktorer | D78: =SUM('Delresultater (GHG)'!D78:F78) -> 0 | E78: =IF($D$98 = 0,0,$D78/$D$98) -> 0 | F78: ='Delresultater (GHG)'!D162 -> 0
C79: =Tekstnøgler!C175 -> Varetransport fra virksomhed til kunde | D79: =SUM(D80:D82) -> 546.56 | E79: =SUM(E80:E82) -> 0.053423997 | F79: =SUM(F80:F82) -> 29.962533
C80: =Tekstnøgler!C176 -> Varetransport i fysiske enheder | D80: =SUM('Delresultater (GHG)'!D80:F80) -> 546.56 | E80: =IF($D$98 = 0,0,$D80/$D$98) -> 0.053423997 | F80: ='Delresultater (GHG)'!D164 -> 29.962533
C81: =Tekstnøgler!C177 -> Varetransport i monetære enheder (beløb i DKK) | D81: =SUM('Delresultater (GHG)'!D81:F81) -> 0 | E81: =IF($D$98 = 0,0,$D81/$D$98) -> 0 | F81: ='Delresultater (GHG)'!D165 -> 0
C82: =Tekstnøgler!C178 -> Varetransport fra virksomhed til kunde med egne emissionsfaktorer | D82: =SUM('Delresultater (GHG)'!D82:F82) -> 0 | E82: =IF($D$98 = 0,0,$D82/$D$98) -> 0 | F82: ='Delresultater (GHG)'!D166 -> 0
C83: =Tekstnøgler!C179 -> Andet udledning ved transport | D83: =SUM('Delresultater (GHG)'!D83:F83) -> 0 | E83: =IF($D$98 = 0,0,$D83/$D$98) -> 0 | F83: ='Delresultater (GHG)'!D167 -> 0
C84: =Tekstnøgler!C93 -> Affald og genbrug | D84: =D85+D88 -> 0 | E84: =E85+E88 -> 0 | F84: =F85+F88 -> -128.21782
C85: =Tekstnøgler!C181 -> Affald | D85: =SUM(D86:D87) -> 0 | E85: =SUM(E86:E87) -> 0 | F85: =SUM(F86:F87) -> -128.21782
C86: =Tekstnøgler!C182 -> Affald | D86: =SUM('Delresultater (GHG)'!D86:F86) -> 0 | E86: =IF($D$98 = 0,0,$D86/$D$98) -> 0 | F86: ='Delresultater (GHG)'!D170 -> -128.21782
C87: =Tekstnøgler!C183 -> Affald med egne emissionsfaktorer | D87: =SUM('Delresultater (GHG)'!D87:F87) -> 0 | E87: =IF($D$98 = 0,0,$D87/$D$98) -> 0 | F87: ='Delresultater (GHG)'!D171 -> 0
C88: =Tekstnøgler!C184 -> Andet udledning ved affald | D88: =SUM('Delresultater (GHG)'!D88:F88) -> 0 | E88: =IF($D$98 = 0,0,$D88/$D$98) -> 0 | F88: ='Delresultater (GHG)'!D172 -> 0
C89: =Tekstnøgler!C94 -> Solgte produkter | D89: =D90+D91+D94+D97 -> 0 | E89: =E90+E91+E94+E97 -> 0 | F89: =F90+F91+F94+F97 -> -111.89732
C90: =Tekstnøgler!C186 -> Forarbejdning og processering af solgte produkter | D90: =SUM('Delresultater (GHG)'!D90:F90) -> 0 | E90: =IF($D$98 = 0,0,$D90/$D$98) -> 0 | F90: ='Delresultater (GHG)'!D174 -> 0
C91: =Tekstnøgler!C187 -> Brug af solgte og udlejede produkter | D91: =SUM(D92:D93) -> 0 | E91: =SUM(E92:E93) -> 0 | F91: =SUM(F92:F93) -> 0
C92: =Tekstnøgler!C188 -> Brug af solgte og udlejede produkter | D92: =SUM('Delresultater (GHG)'!D92:F92) -> 0 | E92: =IF($D$98 = 0,0,$D92/$D$98) -> 0 | F92: ='Delresultater (GHG)'!D176 -> 0
C93: =Tekstnøgler!C189 -> Brug af solgte og udlejede produkter med egne emissionsfaktorer | D93: =SUM('Delresultater (GHG)'!D93:F93) -> 0 | E93: =IF($D$98 = 0,0,$D93/$D$98) -> 0 | F93: ='Delresultater (GHG)'!D177 -> 0
C94: =Tekstnøgler!C190 -> End-of-life behandling | D94: =SUM(D95:D96) -> 0 | E94: =SUM(E95:E96) -> 0 | F94: =SUM(F95:F96) -> -111.89732
C95: =Tekstnøgler!C191 -> Håndtering af affaldsprodukt | D95: =SUM('Delresultater (GHG)'!D95:F95) -> 0 | E95: =IF($D$98 = 0,0,$D95/$D$98) -> 0 | F95: ='Delresultater (GHG)'!D179 -> -111.89732
C96: =Tekstnøgler!C192 -> Håndtering af affaldsprodukt med egne emissionsfaktorer | D96: =SUM('Delresultater (GHG)'!D96:F96) -> 0 | E96: =IF($D$98 = 0,0,$D96/$D$98) -> 0 | F96: ='Delresultater (GHG)'!D180 -> 0
C97: =Tekstnøgler!C193 -> Andet udledning ved solgte og udlejede produkter | D97: =SUM('Delresultater (GHG)'!D97:F97) -> 0 | E97: =IF($D$98 = 0,0,$D97/$D$98) -> 0 | F97: ='Delresultater (GHG)'!D181 -> 0
C98: =Tekstnøgler!C95 -> Total | D98: =D24+D36+D65+D84+D89 -> 10230.609 | E98: =E24+E36+E65+E84+E89 -> 1 | F98: =F24+F36+F65+F84+F89 -> -60.675259

Sheet Hovedresultater (GHG)
C2: =Tekstnøgler!C196 -> Resultat (GHG) | I2: =Tekstnøgler!C2 -> <-- Gå til forsiden
C5: =Hovedresultater!C5 -> Resultat for 0 (År) - Tiltagscase
C6: =Hovedresultater!C6 -> 10.230,61 ton CO₂e
C8: =Tekstnøgler!C71 -> Metodevalg
C10: =Tekstnøgler!C72 -> Resultaterne baserer sig på en række metodiske valg, der er foretaget i forbindelse med beregningerne. I nedenstående tabel kan du se, hvorvidt Radiative Forcing Index (RFI) er medregnet i forbindelse med udledninger fra flytransport. At medregne (eller korrigere for) RFI betyder, at der er taget højde for, at CO₂e udledt højere oppe i atmosfæren har en større drivhuseffekt end CO₂e udledt ved landjorden. Tabellen viser også, om emissionsfaktoren for el baserer sig på det årlige gennemsnit for sammensætningen af produktionen af el (miljødeklaration), eller om der i emissionsfaktoren korrigeres for virksomheders køb af grønne certifikater, såkaldte oprindelsesgarantier (eldeklaration).
C12: =Tekstnøgler!C73 -> Emissionsfaktor | E12: =Tekstnøgler!C74 -> Metodevalg
C13: =Tekstnøgler!C75 -> Valg af emissionsfaktor for elektricitet | E13: =IF(ISBLANK(Hovedresultater!$E13),"",Hovedresultater!$E13) -> Eldeklaration
C14: =Tekstnøgler!C76 -> Emissionsfaktor for flytransport | E14: =IF(ISBLANK(Hovedresultater!$E14),"",Hovedresultater!$E14) -> Inkluder RFI
C17: =Tekstnøgler!C197 -> Hovedresultater (GHG)
C19: =Tekstnøgler!C198 -> Virksomhedens samlede CO₂e-udledning er angivet i tabel 1. CO₂e-udledningen er angivet i ton CO₂-ækvivalenter, og tabellen viser udledningen fordelt på scope 1, 2 og 3 jf. GHG-protokollen. Udledningen udenfor scopes medregnes ikke jf. GHG-protokollen og indgår derfor ikke i totalen.
C20: =Tekstnøgler!C199 -> Tabel 1: Oversigt over virksomhedens samlede CO₂e-udledninger
C21: =Tekstnøgler!C200 -> Scope | D21: =Tekstnøgler!C201 -> Ton CO₂e | E21: =Tekstnøgler!C202 -> Andel af udledning
C22: =Tekstnøgler!C203 -> Scope 1 | D22: ='Delresultater (GHG)'!D98 -> 443.36484 | E22: =IF(ISBLANK($D22),,$D22/$D$25) -> 0.043337094
C23: =Tekstnøgler!C204 -> Scope 2 | D23: ='Delresultater (GHG)'!E98 -> 1851.795 | E23: =IF(ISBLANK($D23),,$D23/$D$25) -> 0.18100536
C24: =Tekstnøgler!C205 -> Scope 3 | D24: ='Delresultater (GHG)'!F98 -> 7935.4487 | E24: =IF(ISBLANK($D24),,$D24/$D$25) -> 0.77565754
C25: =Tekstnøgler!C95 -> Total | D25: =SUM(D22:D24) -> 10230.609 | E25: =SUM(E22:E24) -> 1
C28: =Tekstnøgler!C207 -> Opsummering af virksomhedens beregnede CO2e-udledning
C30: =Tekstnøgler!C208 -> Nedenstående figurer viser grafiske fremstillinger af virksomhedens beregnede CO₂e-udledning. Figur 1 angiver virksomhedens absolutte udledning i ton CO₂-ækvivalenter fordelt på scope 1, 2, og 3. Figur 2 viser den procentuelle fordeling af CO₂e-udledningen fordelt på scope 1, 2 og 3.
C31: =Tekstnøgler!C209 -> Figur 1: Virksomhedens samlede CO₂e-udledning i ton fordelt på scopes | H31: =Tekstnøgler!C210 -> Figur 2: Procentfordeling af CO₂e-udledning fordelt på scopes
C50: =Tekstnøgler!C211 -> Nøgletal
C52: =Tekstnøgler!C212 -> Denne tabel viser beregninger af nøgletal i tilfælde af, at der under Stamdata er indtastet data for hhv. antal fuldtidsansatte i virksomheden, nettoomsætning og areal.
C54: =Tekstnøgler!C213 -> Nøgletalsberegninger | E54: =Tekstnøgler!C214 -> Ton CO₂e
C55: =Tekstnøgler!C215 -> CO₂e pr. ansat | E55: =IF(ISBLANK(Hovedresultater!E82),"",Hovedresultater!E82) -> 204.61217
C56: =Tekstnøgler!C216 -> CO₂e pr. mio. kr. nettoomsætning | E56: =IF(ISBLANK(Hovedresultater!E83),"",Hovedresultater!E83) -> 444.80907
C57: =Tekstnøgler!C217 -> CO₂e pr. m2 | E57: =IF(ISBLANK(Hovedresultater!E84),"",Hovedresultater!E84) -> 2.0461217
C60: =Tekstnøgler!C218 -> Udenfor scopes resultater
C62: =Tekstnøgler!C219 -> I en række tilfælde vil Klimakompasset vise nogle resultater i 'udenfor scope'. Dette gælder fx biogen CO₂e-udledning fra forbrænding af biobrændsel. Dette gælder også evt. undgåede udledninger som fx undgået produktion af nye materialer ved at sende affald til genanvendelse. Jf. GHG-protokollen medregnes disse udledninger ikke under scope 1, 2 og 3 og indgår derfor ikke i totalen.
C64: =Tekstnøgler!C220 -> Udenfor scopes resultater
C65: =Tekstnøgler!C221 -> Scope | D65: =Tekstnøgler!C222 -> Ton CO₂e | E65: =Tekstnøgler!C223 -> Andel af udledning
C66: =Tekstnøgler!C224 -> Udenfor scope | D66: ='Delresultater (GHG)'!D182 -> -60.675259 | E66: =D66/D25 -> -0.0059307576
C69: =Tekstnøgler!C109 -> Egne bemærkninger
C71: =IF(ISTEXT(Hovedresultater!C89),Hovedresultater!C89,"")

Sheet Delresultater (GHG)
C2: =Tekstnøgler!C196 -> Resultat (GHG) | F2: =Tekstnøgler!C2 -> <-- Gå til forsiden
C5: =Hovedresultater!C5 -> Resultat for 0 (År) - Tiltagscase
C6: =Hovedresultater!C6 -> 10.230,61 ton CO₂e
C8: =Tekstnøgler!C71 -> Metodevalg
C10: =Tekstnøgler!C72 -> Resultaterne baserer sig på en række metodiske valg, der er foretaget i forbindelse med beregningerne. I nedenstående tabel kan du se, hvorvidt Radiative Forcing Index (RFI) er medregnet i forbindelse med udledninger fra flytransport. At medregne (eller korrigere for) RFI betyder, at der er taget højde for, at CO₂e udledt højere oppe i atmosfæren har en større drivhuseffekt end CO₂e udledt ved landjorden. Tabellen viser også, om emissionsfaktoren for el baserer sig på det årlige gennemsnit for sammensætningen af produktionen af el (miljødeklaration), eller om der i emissionsfaktoren korrigeres for virksomheders køb af grønne certifikater, såkaldte oprindelsesgarantier (eldeklaration).
C12: =Tekstnøgler!C73 -> Emissionsfaktor | D12: =Tekstnøgler!C74 -> Metodevalg
C13: =Tekstnøgler!C75 -> Valg af emissionsfaktor for elektricitet | D13: =IF(ISBLANK(Hovedresultater!$E13),"",Hovedresultater!$E13) -> Eldeklaration
C14: =Tekstnøgler!C76 -> Emissionsfaktor for flytransport | D14: =IF(ISBLANK(Hovedresultater!$E14),"",Hovedresultater!$E14) -> Inkluder RFI
C17: =Tekstnøgler!C227 -> Delresultater (GHG)
C19: =Tekstnøgler!C228 -> Her ses en mere detaljeret resultatvisning. Tabellen viser alle underkategorierne, der kan angives data for, den tilhørende udledning i ton CO₂e og underkategoriens samlede andel af de totale udledninger.
C21: =Tekstnøgler!C226 -> Oversigt over CO₂e-udledningen fordelt på hoved- og underkategorier
C22: =Tekstnøgler!C115 -> Hovedkategori | D22: =Tekstnøgler!C203 -> Scope 1 | E22: =Tekstnøgler!C204 -> Scope 2 | F22: =Tekstnøgler!C205 -> Scope 3 | G22: =Tekstnøgler!C230 -> Samlede CO₂e udledning i ton (scope 1+2+3)
D23: =Tekstnøgler!C229 -> (ton CO₂e) | E23: =Tekstnøgler!C229 -> (ton CO₂e) | F23: =Tekstnøgler!C229 -> (ton CO₂e) | G23: =Tekstnøgler!C229 -> (ton CO₂e)
C24: =Tekstnøgler!C90 -> Energi og processer | D24: =D25+D28+D32+D35 -> 435.44571 | E24: =E25+E28+E32+E35 -> 1851.795 | F24: =F25+F28+F32+F35 -> 412.59541 | G24: =G25+G28+G32+G35 -> 2699.8361
C25: =Tekstnøgler!C121 -> Elektricitet | D25: =SUM(D26:D27) -> 0 | E25: =SUM(E26:E27) -> 1851.795 | F25: =SUM(F26:F27) -> 331.10115 | G25: =SUM(G26:G27) -> 2182.8961
C26: =Tekstnøgler!C122 -> Forbrug af elektricitet | D26: 0 | E26: 1851.795 | F26: 331.10115 | G26: =D26+E26+F26 -> 2182.8961
C27: =Tekstnøgler!C123 -> Forbrug af elektricitet med egne emissionsfaktorer | D27: 0 | E27: 0 | F27: 0 | G27: =D27+E27+F27 -> 0
C28: =Tekstnøgler!C124 -> Varme og procesenergi | D28: =SUM(D29:D31) -> 435.44571 | E28: =SUM(E29:E31) -> 0 | F28: =SUM(F29:F31) -> 81.494262 | G28: =SUM(G29:G31) -> 516.93997
C29: =Tekstnøgler!C125 -> Fjernvarme | D29: 0 | E29: 0 | F29: 0 | G29: =D29+E29+F29 -> 0
C30: =Tekstnøgler!C126 -> Brændsler | D30: 435.44571 | E30: 0 | F30: 81.494262 | G30: =D30+E30+F30 -> 516.93997
C31: =Tekstnøgler!C127 -> Varme og procesenergi med egne emissionsfaktorer | D31: 0 | E31: 0 | F31: 0 | G31: =D31+E31+F31 -> 0
C32: =Tekstnøgler!C128 -> Procesudledning | D32: =SUM(D33:D34) -> 0 | E32: =SUM(E33:E34) -> 0 | F32: =SUM(F33:F34) -> 0 | G32: =SUM(G33:G34) -> 0
C33: =Tekstnøgler!C129 -> Procesudledning | D33: 0 | E33: 0 | F33: 0 | G33: =D33+E33+F33 -> 0
C34: =Tekstnøgler!C130 -> Procesudledning med egne emissionsfaktorer | D34: 0 | E34: 0 | F34: 0 | G34: =D34+E34+F34 -> 0
C35: =Tekstnøgler!C131 -> Andet udledning ved energi og processer | D35: 0 | E35: 0 | F35: 0 | G35: =D35+E35+F35 -> 0
C36: =Tekstnøgler!C91 -> Indkøb | D36: =D37+D51 -> 0 | E36: =E37+E51 -> 0 | F36: =F37+F51 -> 6765.5856 | G36: =G37+G51 -> 6765.5856
C37: =Tekstnøgler!C133 -> Primære indkøb af råvarer til produktion | D37: =D38+D43+D48 -> 0 | E37: =E38+E43+E48 -> 0 | F37: =F38+F43+F48 -> 6765.5856 | G37: =G38+G43+G48 -> 6765.5856
C38: =Tekstnøgler!C134 -> Materialer (primære indkøb) | D38: =SUM(D39:D42) -> 0 | E38: =SUM(E39:E42) -> 0 | F38: =SUM(F39:F42) -> 6760.9302 | G38: =SUM(G39:G42) -> 6760.9302
C39: =Tekstnøgler!C135 -> Indkøb af materialer i fysiske enheder | D39: 0 | E39: 0 | F39: 6760.9302 | G39: =D39+E39+F39 -> 6760.9302
C40: =Tekstnøgler!C136 -> Indkøb af materialer i monetære enheder (beløb i DKK) | D40: 0 | E40: 0 | F40: 0 | G40: =D40+E40+F40 -> 0
C41: =Tekstnøgler!C137 -> Fysiske enheder med egne emissionsfaktorer | D41: 0 | E41: 0 | F41: 0 | G41: =D41+E41+F41 -> 0
C42: =Tekstnøgler!C138 -> Monetære enheder (beløb i DKK) med egne emissionsfaktorer | D42: 0 | E42: 0 | F42: 0 | G42: =D42+E42+F42 -> 0
C43: =Tekstnøgler!C139 -> Produkter og services (primære indkøb) | D43: =SUM(D44:D47) -> 0 | E43: =SUM(E44:E47) -> 0 | F43: =SUM(F44:F47) -> 4.6554366 | G43: =SUM(G44:G47) -> 4.6554366
C44: =Tekstnøgler!C140 -> Indkøb af produkter i fysiske enheder | D44: 0 | E44: 0 | F44: 4.6554366 | G44: =D44+E44+F44 -> 4.6554366
C45: =Tekstnøgler!C141 -> Indkøb af produkter i monetære enheder (beløb i DKK) | D45: 0 | E45: 0 | F45: 0 | G45: =D45+E45+F45 -> 0
C46: =Tekstnøgler!C142 -> Fysiske enheder med egne emissionsfaktorer | D46: 0 | E46: 0 | F46: 0 | G46: =D46+E46+F46 -> 0
C47: =Tekstnøgler!C143 -> Monetære enheder (beløb i DKK) med egne emissionsfaktorer | D47: 0 | E47: 0 | F47: 0 | G47: =D47+E47+F47 -> 0
C48: =Tekstnøgler!C144 -> Andet udledning ved primære indkøb | D48: =SUM(D49:D50) -> 0 | E48: =SUM(E49:E50) -> 0 | F48: =SUM(F49:F50) -> 0 | G48: =SUM(G49:G50) -> 0
C49: =Tekstnøgler!C145 -> Fysiske enheder med egne emissionsfaktorer | D49: 0 | E49: 0 | F49: 0 | G49: =D49+E49+F49 -> 0
C50: =Tekstnøgler!C146 -> Monetære enheder (beløb i DKK) med egne emissionsfaktorer | D50: 0 | E50: 0 | F50: 0 | G50: =D50+E50+F50 -> 0
C51: =Tekstnøgler!C147 -> Sekundære indkøb af hjælpematerialer og serviceydelser | D51: =D52+D57+D62 -> 0 | E51: =E52+E57+E62 -> 0 | F51: =F52+F57+F62 -> 0 | G51: =G52+G57+G62 -> 0
C52: =Tekstnøgler!C148 -> Materialer (sekundære indkøb) | D52: =SUM(D53:D56) -> 0 | E52: =SUM(E53:E56) -> 0 | F52: =SUM(F53:F56) -> 0 | G52: =SUM(G53:G56) -> 0
C53: =Tekstnøgler!C149 -> Indkøb af materialer i fysiske enheder | D53: 0 | E53: 0 | F53: 0 | G53: =D53+E53+F53 -> 0
C54: =Tekstnøgler!C150 -> Indkøb af materialer i monetære enheder (beløb i DKK) | D54: 0 | E54: 0 | F54: 0 | G54: =D54+E54+F54 -> 0
C55: =Tekstnøgler!C151 -> Fysiske enheder med egne emissionsfaktorer | D55: 0 | E55: 0 | F55: 0 | G55: =D55+E55+F55 -> 0
C56: =Tekstnøgler!C152 -> Monetære enheder (beløb i DKK) med egne emissionsfaktorer | D56: 0 | E56: 0 | F56: 0 | G56: =D56+E56+F56 -> 0
C57: =Tekstnøgler!C153 -> Produkter og services (sekundære indkøb) | D57: =SUM(D58:D61) -> 0 | E57: =SUM(E58:E61) -> 0 | F57: =SUM(F58:F61) -> 0 | G57: =SUM(G58:G61) -> 0
C58: =Tekstnøgler!C154 -> Indkøb af produkter i fysiske enheder | D58: 0 | E58: 0 | F58: 0 | G58: =D58+E58+F58 -> 0
C59: =Tekstnøgler!C155 -> Indkøb af produkter i monetære enheder (beløb i DKK) | D59: 0 | E59: 0 | F59: 0 | G59: =D59+E59+F59 -> 0
C60: =Tekstnøgler!C156 -> Fysiske enheder med egne emissionsfaktorer | D60: 0 | E60: 0 | F60: 0 | G60: =D60+E60+F60 -> 0
C61: =Tekstnøgler!C157 -> Monetære enheder (beløb i DKK) med egne emissionsfaktorer | D61: 0 | E61: 0 | F61: 0 | G61: =D61+E61+F61 -> 0
C62: =Tekstnøgler!C158 -> Andet udledning ved sekundære indkøb | D62: =SUM(D63:D64) -> 0 | E62: =SUM(E63:E64) -> 0 | F62: =SUM(F63:F64) -> 0 | G62: =SUM(G63:G64) -> 0
C63: =Tekstnøgler!C159 -> Fysiske enheder med egne emissionsfaktorer | D63: 0 | E63: 0 | F63: 0 | G63: =D63+E63+F63 -> 0
C64: =Tekstnøgler!C160 -> Monetære enheder (beløb i DKK) med egne emissionsfaktorer | D64: 0 | E64: 0 | F64: 0 | G64: =D64+E64+F64 -> 0
C65: =Tekstnøgler!C92 -> Transport | D65: =D66+D70+D75+D79+D83 -> 7.9191354 | E65: =E66+E70+E75+E79+E83 -> 0 | F65: =F66+F70+F75+F79+F83 -> 757.26767 | G65: =G66+G70+G75+G79+G83 -> 765.18681
C66: =Tekstnøgler!C162 -> Egne og leasede transportmidler | D66: =SUM(D67:D69) -> 7.9191354 | E66: =SUM(E67:E69) -> 0 | F66: =SUM(F67:F69) -> 2.1299865 | G66: =SUM(G67:G69) -> 10.049122
C67: =Tekstnøgler!C163 -> Egne og leasede transportmidler | D67: 7.9191354 | E67: 0 | F67: 2.1299865 | G67: =D67+E67+F67 -> 10.049122
C68: =Tekstnøgler!C164 -> Fly og Skibe | D68: 0 | E68: 0 | F68: 0 | G68: =D68+E68+F68 -> 0
C69: =Tekstnøgler!C165 -> Egne og leasede transportmidler med egne emissionsfaktorer | D69: 0 | E69: 0 | F69: 0 | G69: =D69+E69+F69 -> 0
C70: =Tekstnøgler!C166 -> Medarbejdertransport | D70: =SUM(D71:D74) -> 0 | E70: =SUM(E71:E74) -> 0 | F70: =SUM(F71:F74) -> 3.6176839 | G70: =SUM(G71:G74) -> 3.6176839
C71: =Tekstnøgler!C167 -> Pendling | D71: 0 | E71: 0 | F71: 3.6176839 | G71: =D71+E71+F71 -> 3.6176839
C72: =Tekstnøgler!C168 -> Rejser i forbindelse med arbejder - Fysiske enheder | D72: 0 | E72: 0 | F72: 0 | G72: =D72+E72+F72 -> 0
C73: =Tekstnøgler!C169 -> Rejser i forbindelse med arbejder - Monetære enheder (beløb i DKK) | D73: 0 | E73: 0 | F73: 0 | G73: =D73+E73+F73 -> 0
C74: =Tekstnøgler!C170 -> Medarbejdertransport med egne emissionsfaktorer | D74: 0 | E74: 0 | F74: 0 | G74: =D74+E74+F74 -> 0
C75: =Tekstnøgler!C171 -> Varetransport til virksomhed | D75: =SUM(D76:D78) -> 0 | E75: =SUM(E76:E78) -> 0 | F75: =SUM(F76:F78) -> 204.96 | G75: =SUM(G76:G78) -> 204.96
C76: =Tekstnøgler!C172 -> Varetransport i fysiske enheder | D76: 0 | E76: 0 | F76: 204.96 | G76: =D76+E76+F76 -> 204.96
C77: =Tekstnøgler!C173 -> Varetransport i monetære enheder (beløb i DKK) | D77: 0 | E77: 0 | F77: 0 | G77: =D77+E77+F77 -> 0
C78: =Tekstnøgler!C174 -> Varetransport til virksomhed med egne emissionsfaktorer | D78: 0 | E78: 0 | F78: 0 | G78: =D78+E78+F78 -> 0
C79: =Tekstnøgler!C175 -> Varetransport fra virksomhed til kunde | D79: =SUM(D80:D82) -> 0 | E79: =SUM(E80:E82) -> 0 | F79: =SUM(F80:F82) -> 546.56 | G79: =SUM(G80:G82) -> 546.56
C80: =Tekstnøgler!C176 -> Varetransport i fysiske enheder | D80: 0 | E80: 0 | F80: 546.56 | G80: =D80+E80+F80 -> 546.56
C81: =Tekstnøgler!C177 -> Varetransport i monetære enheder (beløb i DKK) | D81: 0 | E81: 0 | F81: 0 | G81: =D81+E81+F81 -> 0
C82: =Tekstnøgler!C178 -> Varetransport fra virksomhed til kunde med egne emissionsfaktorer | D82: 0 | E82: 0 | F82: 0 | G82: =D82+E82+F82 -> 0
C83: =Tekstnøgler!C179 -> Andet udledning ved transport | D83: 0 | E83: 0 | F83: 0 | G83: =D83+E83+F83 -> 0
C84: =Tekstnøgler!C93 -> Affald og genbrug | D84: =D85+D88 -> 0 | E84: =E85+E88 -> 0 | F84: =F85+F88 -> 0 | G84: =G85+G88 -> 0
C85: =Tekstnøgler!C181 -> Affald | D85: =SUM(D86:D87) -> 0 | E85: =SUM(E86:E87) -> 0 | F85: =SUM(F86:F87) -> 0 | G85: =SUM(G86:G87) -> 0
C86: =Tekstnøgler!C182 -> Affald | D86: 0 | E86: 0 | F86: 0 | G86: =D86+E86+F86 -> 0
C87: =Tekstnøgler!C183 -> Affald med egne emissionsfaktorer | D87: 0 | E87: 0 | F87: 0 | G87: =D87+E87+F87 -> 0
C88: =Tekstnøgler!C184 -> Andet udledning ved affald | D88: 0 | E88: 0 | F88: 0 | G88: =D88+E88+F88 -> 0
C89: =Tekstnøgler!C94 -> Solgte produkter | D89: =D90+D91+D94+D97 -> 0 | E89: =E90+E91+E94+E97 -> 0 | F89: =F90+F91+F94+F97 -> 0 | G89: =G90+G91+G94+G97 -> 0
C90: =Tekstnøgler!C186 -> Forarbejdning og processering af solgte produkter | D90: 0 | E90: 0 | F90: 0 | G90: =D90+E90+F90 -> 0
C91: =Tekstnøgler!C187 -> Brug af solgte og udlejede produkter | D91: =SUM(D92:D93) -> 0 | E91: =SUM(E92:E93) -> 0 | F91: =SUM(F92:F93) -> 0 | G91: =SUM(G92:G93) -> 0
C92: =Tekstnøgler!C188 -> Brug af solgte og udlejede produkter | D92: 0 | E92: 0 | F92: 0 | G92: =D92+E92+F92 -> 0
C93: =Tekstnøgler!C189 -> Brug af solgte og udlejede produkter med egne emissionsfaktorer | D93: 0 | E93: 0 | F93: 0 | G93: =D93+E93+F93 -> 0
C94: =Tekstnøgler!C190 -> End-of-life behandling | D94: =SUM(D95:D96) -> 0 | E94: =SUM(E95:E96) -> 0 | F94: =SUM(F95:F96) -> 0 | G94: =SUM(G95:G96) -> 0
C95: =Tekstnøgler!C191 -> Håndtering af affaldsprodukt | D95: 0 | E95: 0 | F95: 0 | G95: =D95+E95+F95 -> 0
C96: =Tekstnøgler!C192 -> Håndtering af affaldsprodukt med egne emissionsfaktorer | D96: 0 | E96: 0 | F96: 0 | G96: =D96+E96+F96 -> 0
C97: =Tekstnøgler!C193 -> Andet udledning ved solgte og udlejede produkter | D97: 0 | E97: 0 | F97: 0 | G97: =D97+E97+F97 -> 0
C98: =Tekstnøgler!C95 -> Total | D98: =D24+D36+D65+D84+D89 -> 443.36484 | E98: =E24+E36+E65+E84+E89 -> 1851.795 | F98: =F24+F36+F65+F84+F89 -> 7935.4487 | G98: =G24+G36+G65+G84+G89 -> 10230.609
C101: =Tekstnøgler!C231 -> Udenfor scopes resultater
C103: =Tekstnøgler!C232 -> Her ses en mere detaljeret resultatvisning for udenfor scopes. Tabellen viser den tilhørende udledning for alle underkategorierne, der er indtastet data for. Bemærk at udenfor scopes ikke medregnes i totalen jf. GHG-protokollen.
C105: =Tekstnøgler!C233 -> Oversigt af 'udenfor scopes' resultater over CO₂e-udledningen fordelt på hoved- og underkategorier
C106: =C22 -> Hovedkategori | D106: =Tekstnøgler!C234 -> Udenfor scopes i ton CO2e
D107: =Tekstnøgler!C229 -> (ton CO₂e)
C108: =C24 -> Energi og processer | D108: =D109+D112+D116+D119 -> 137.48754
C109: =C25 -> Elektricitet | D109: =SUM(D110:D111) -> 129.88681
C110: =C26 -> Forbrug af elektricitet | D110: 129.88681
C111: =C27 -> Forbrug af elektricitet med egne emissionsfaktorer | D111: 0
C112: =C28 -> Varme og procesenergi | D112: =SUM(D113:D115) -> 7.6007239
C113: =C29 -> Fjernvarme | D113: 0
C114: =C30 -> Brændsler | D114: 7.6007239
...

Sheet E-nøgletal (ESG)
C2: =Tekstnøgler!C33 -> Resultat | E2: =Tekstnøgler!C2 -> <-- Gå til forsiden
C5: =Hovedresultater!C5 -> Resultat for 0 (År) - Tiltagscase
C6: =Hovedresultater!C6 -> 10.230,61 ton CO₂e
C8: =Tekstnøgler!C71 -> Metodevalg
C10: =Tekstnøgler!C72 -> Resultaterne baserer sig på en række metodiske valg, der er foretaget i forbindelse med beregningerne. I nedenstående tabel kan du se, hvorvidt Radiative Forcing Index (RFI) er medregnet i forbindelse med udledninger fra flytransport. At medregne (eller korrigere for) RFI betyder, at der er taget højde for, at CO₂e udledt højere oppe i atmosfæren har en større drivhuseffekt end CO₂e udledt ved landjorden. Tabellen viser også, om emissionsfaktoren for el baserer sig på det årlige gennemsnit for sammensætningen af produktionen af el (miljødeklaration), eller om der i emissionsfaktoren korrigeres for virksomheders køb af grønne certifikater, såkaldte oprindelsesgarantier (eldeklaration).
C12: =Tekstnøgler!C73 -> Emissionsfaktor | D12: =Tekstnøgler!C74 -> Metodevalg
C13: =Tekstnøgler!C75 -> Valg af emissionsfaktor for elektricitet | D13: =IF(ISBLANK(Hovedresultater!$E13),"",Hovedresultater!$E13) -> Eldeklaration
C14: =Tekstnøgler!C76 -> Emissionsfaktor for flytransport | D14: =IF(ISBLANK(Hovedresultater!$E14),"",Hovedresultater!$E14) -> Inkluder RFI
C17: =Tekstnøgler!C238 -> E-nøgletal (ESG)
C19: =Tekstnøgler!C241 -> ESG står for Environment, Social og Governance og dækker over ikke-finansielle nøgletal, som kan indgå i din virksomheds opgørelse, dokumentation og rapportering af bæredygtighed ift. miljø- og klimamæssige forhold, sociale forhold samt god selskabsledelse. En række vejledende nøgletal under "E" kan beregnes med Klimakompasset, når du udarbejder dit klimaaftryk. Nøgletallene er kun vejledende og kan ikke bruges til at verificere din ESG-rapport. Læs mere om ESG på Virksomhedsguiden.
C21: =Tekstnøgler!C239 -> E-nøgletal
C23: =Tekstnøgler!C242 -> CO₂e-udledning | E23: =Tekstnøgler!C245 -> Resultat | G23: =Tekstnøgler!C244 -> Enhed
C24: =Tekstnøgler!C247 -> CO₂e-udledning inden for scope 1 | E24: ='Delresultater (GHG)'!D98 -> 443.36484 | G24: =Tekstnøgler!C263 -> Ton CO₂e
C25: =Tekstnøgler!C248 -> CO₂e-udledning inden for scope 2 | E25: ='Delresultater (GHG)'!E98 -> 1851.795 | G25: =Tekstnøgler!C263 -> Ton CO₂e
C26: =Tekstnøgler!C250 -> Samlet CO₂e-udledning (Scope 1 og 2) | E26: 2295.1598 | G26: =Tekstnøgler!C263 -> Ton CO₂e
C27: =Tekstnøgler!C253 -> CO₂ intensitet (CO₂e-udledning for scope 1 og 2 ift. nettoomsætning) | E27: =IF(AND(ISNUMBER(E66),ISNUMBER(E26),E66>0),E26/E66,Tekstnøgler!C269) -> 99.789558 | G27: =Tekstnøgler!C264 -> Ton CO₂e / mio. DKK
C28: =Tekstnøgler!C249 -> CO₂e-udledning inden for scope 3 | E28: ='Delresultater (GHG)'!F98 -> 7935.4487 | G28: =Tekstnøgler!C263 -> Ton CO₂e
C29: =Tekstnøgler!C251 -> Samlet CO₂e-udledning (Scope 1, 2 og 3) | E29: ='Delresultater (GHG)'!G98 -> 10230.609 | G29: =Tekstnøgler!C263 -> Ton CO₂e
C30: =Tekstnøgler!C252 -> CO₂ intensitet (Samlet CO₂e-udledning ift. nettoomsætning) | E30: =IF(AND(ISNUMBER(E66),ISNUMBER(E29),E66>0),E29/E66,Tekstnøgler!C269) -> 444.80907 | G30: =Tekstnøgler!C264 -> Ton CO₂e / mio. DKK
C32: =Tekstnøgler!C602 -> Her ses din virksomheds samlede forbrug af elektricitet, og heraf hvad som kommer fra vedvarende energikilder. Bemærk, at den nukleare energiandel er medregnet under vedvarende elektricitet. Det skyldes, at den nukleare andel ikke udleder CO₂e.
C34: =Tekstnøgler!C284 -> Energiforbrug | D34: =Tekstnøgler!C285 -> Vedvarende | E34: =Tekstnøgler!C286 -> Ikke vedvarende | F34: =Tekstnøgler!C287 -> Total | G34: =Tekstnøgler!C244 -> Enhed
C35: =Tekstnøgler!C293 -> Elektricitet | D35: 1819.6129 | E35: 2680.3871 | F35: =IF(OR(ISNUMBER(D35),ISNUMBER(E35)),SUM(D35:E35),Tekstnøgler!$C$269) -> 4500 | G35: =Tekstnøgler!C289 -> MWh
C36: =Tekstnøgler!C294 -> Brændsler | D36: 48.993722 | E36: 1940.8372 | F36: =IF(OR(ISNUMBER(D36),ISNUMBER(E36)),SUM(D36:E36),Tekstnøgler!$C$269) -> 1989.831 | G36: =Tekstnøgler!C289 -> MWh
C37: =Tekstnøgler!C295 -> Fjernvarme | D37: =Tekstnøgler!C269 -> (ikke angivet) | E37: =Tekstnøgler!C269 -> (ikke angivet) | F37: =IF(OR(ISNUMBER(D37),ISNUMBER(E37)),SUM(D37:E37),Tekstnøgler!$C$269) -> (ikke angivet) | G37: =Tekstnøgler!C289 -> MWh
C38: =Tekstnøgler!C287 -> Total | D38: =IF(OR(ISNUMBER(D35),ISNUMBER(D36),ISNUMBER(D37)),SUM(D35:D37),Tekstnøgler!$C$269) -> 1868.6067 | E38: =IF(OR(ISNUMBER(E35),ISNUMBER(E36),ISNUMBER(E37)),SUM(E35:E37),Tekstnøgler!$C$269) -> 4621.2243 | F38: =IF(OR(ISNUMBER(F35),ISNUMBER(F36),ISNUMBER(F37)),SUM(F35:F37),Tekstnøgler!$C$269) -> 6489.831 | G38: =Tekstnøgler!C289 -> MWh
C41: =Tekstnøgler!C240 -> Andre nøgletal
C43: =Tekstnøgler!C600 -> Her ses din virksomheds samlede energiforbrug, samt hvor stor andel af energiforbruget der kommer fra hhv. fossile kilder (såsom olie og gas), nukleare kilder (atomkraft) og vedvarende kilder (fx solcelle-energi).
C45: =Tekstnøgler!C282 -> Energiforbrug fordelt på kilder | E45: =Tekstnøgler!C245 -> Resultat | F45: =Tekstnøgler!C244 -> Enhed | G45: =Tekstnøgler!C246 -> Andel
C46: =Tekstnøgler!C254 -> Energiforbrug: Fossile kilder | E46: 4621.2243 | F46: =Tekstnøgler!C289 -> MWh | G46: =IF(AND(ISNUMBER(E46),ISNUMBER($E$49),$E$49<>0),E46/$E$49,Tekstnøgler!$C$269) -> 0.7120716
C47: =Tekstnøgler!C255 -> Energiforbrug: Nukleare kilder | E47: 1389.2904 | F47: =Tekstnøgler!C289 -> MWh | G47: =IF(AND(ISNUMBER(E47),ISNUMBER($E$49),$E$49<>0),E47/$E$49,Tekstnøgler!$C$269) -> 0.21407189
C48: =Tekstnøgler!C256 -> Energiforbrug: Vedvarende kilder | E48: 479.31625 | F48: =Tekstnøgler!C289 -> MWh | G48: =IF(AND(ISNUMBER(E48),ISNUMBER($E$49),$E$49<>0),E48/$E$49,Tekstnøgler!$C$269) -> 0.073856508
C49: =Tekstnøgler!C257 -> Samlet energiforbrug | E49: =IF(OR(ISNUMBER(E46),ISNUMBER(E47),ISNUMBER(E48)),SUM(E46:E48),Tekstnøgler!$C$269) -> 6489.831 | F49: =Tekstnøgler!C289 -> MWh | G49: =IF(ISNUMBER(E49),"100,00%",Tekstnøgler!$C$269) -> 100,00%
C51: =Tekstnøgler!C601 -> Her ses din virksomheds samlede vandforbrug, og hvad vandintensiteten er. Du kan også se virksomhedens samlede mængde affald, heraf hvor stor andel som er farligt affald og hvor stor andel som bliver sendt til genanvendelse eller genbrug.
C53: =Tekstnøgler!C283 -> Vand og affald | E53: =Tekstnøgler!C245 -> Resultat | G53: =Tekstnøgler!C244 -> Enhed
C54: =Tekstnøgler!C260 -> Samlet vandforbrug | E54: 2000 | G54: =Tekstnøgler!C290 -> m3
C55: =Tekstnøgler!C292 -> Samlet mængde affald | E55: 360 | G55: =Tekstnøgler!C280 -> Ton
C56: =Tekstnøgler!C261 -> Andel af farligt affald (Mængde af farligt affald ift. total mængde affald) | E56: =IF(AND(ISNUMBER(E68),ISNUMBER(E69)),E69/E68,Tekstnøgler!C269) -> (ikke angivet) | G56: =Tekstnøgler!C267 -> Pct. (%)
C57: =Tekstnøgler!C262 -> Andel affald sendt til genanvendelse og genbrug (Mængde af genanvendt affald ift. total mængde affald) | E57: =IF(AND(ISNUMBER(E68),ISNUMBER(E70)),E70/E68,Tekstnøgler!C269) -> 0.72222222 | G57: =Tekstnøgler!C267 -> Pct. (%)
C60: =Tekstnøgler!C270 -> Anvendte værdier i beregning af E-nøgletal (ESG)
C62: =Tekstnøgler!C271 -> I følgende tabel kan du se de værdier, der er anvendt i beregningen af E-nøgletallene præsenteret i tabellen ovenfor
C64: =Tekstnøgler!C272 -> PARAMETRE BRUGT TIL BEREGNING AF E-NØGLETAL
C65: =Tekstnøgler!C243 -> Titel | D65: =Tekstnøgler!C244 -> Enhed | E65: =Tekstnøgler!C245 -> Resultat
C66: =Tekstnøgler!C273 -> Nettoomsætning | D66: =Tekstnøgler!C278 -> mio. DKK | E66: =IF(ISBLANK(Stamdata!B59),Tekstnøgler!C269,Stamdata!B59) -> 23
C67: =Tekstnøgler!C274 -> Vedvarende energiforbrug | D67: =Tekstnøgler!$C$289 -> MWh | E67: 479.31625
C68: =Tekstnøgler!C275 -> Total mængde af affald | D68: =Tekstnøgler!C280 -> Ton | E68: 360
C69: =Tekstnøgler!C276 -> Mængde af farligt affald | D69: =Tekstnøgler!C280 -> Ton | E69: =Tekstnøgler!C269 -> (ikke angivet) | F69: =IF(E69>E68,Tekstnøgler!C536,"") -> Mængde af farligt affald er større end den total mængde af affald
C70: =Tekstnøgler!C277 -> Mængde af genanvendt affald | D70: =Tekstnøgler!C280 -> Ton | E70: 260 | F70: =IF(E70>E68,Tekstnøgler!C537,"")

Sheet Scope 3 kategorier
C2: =Tekstnøgler!C33 -> Resultat | E2: =Tekstnøgler!C2 -> <-- Gå til forsiden
C5: =Hovedresultater!C5 -> Resultat for 0 (År) - Tiltagscase
C6: =Hovedresultater!C6 -> 10.230,61 ton CO₂e
C8: =Tekstnøgler!C71 -> Metodevalg
C10: =Tekstnøgler!C72 -> Resultaterne baserer sig på en række metodiske valg, der er foretaget i forbindelse med beregningerne. I nedenstående tabel kan du se, hvorvidt Radiative Forcing Index (RFI) er medregnet i forbindelse med udledninger fra flytransport. At medregne (eller korrigere for) RFI betyder, at der er taget højde for, at CO₂e udledt højere oppe i atmosfæren har en større drivhuseffekt end CO₂e udledt ved landjorden. Tabellen viser også, om emissionsfaktoren for el baserer sig på det årlige gennemsnit for sammensætningen af produktionen af el (miljødeklaration), eller om der i emissionsfaktoren korrigeres for virksomheders køb af grønne certifikater, såkaldte oprindelsesgarantier (eldeklaration).
C12: =Tekstnøgler!C73 -> Emissionsfaktor | D12: =Tekstnøgler!C74 -> Metodevalg
C13: =Tekstnøgler!C75 -> Valg af emissionsfaktor for elektricitet | D13: =IF(ISBLANK(Hovedresultater!$E13),"",Hovedresultater!$E13) -> Eldeklaration
C14: =Tekstnøgler!C76 -> Emissionsfaktor for flytransport | D14: =IF(ISBLANK(Hovedresultater!$E14),"",Hovedresultater!$E14) -> Inkluder RFI
C17: =Tekstnøgler!C299 -> Scope 3 kategorier
C19: =Tekstnøgler!C300 -> GHG protokollen opdeler scope 3 udledning i 15 kategorier for hhv. opstrømsudledninger, der opstår tidligere i virksomhedens værdikæde (fx indkøb af varer og services eller fragt til virksomheden) og for nedstrømsudledninger, der opstår senere i virksomhedens værdikæde (fx brug og bortskaffelse af virksomhedens produkter). Bemærk, at kategori 14 (franchises) og kategori 15 (investeringer) ikke er medtaget her, da de ligger udover Klimakompassets anvendelse. Vær opmærksom på, at der i visningen af dine scope 3 udledninger er mulighed for at vise dit forbrug af elektricitet opgjort enten ved brug af metoderne ”eldeklaration” eller ”miljødeklaration”. GHG-protokollen anbefaler, at du laver to ens opgørelser, hvor den eneste forskel er, hvilken deklaration der klikkes af i Klimakompasset. Virksomhedens CO₂e-udledninger inden for de forskellige scope 3 kategorier er vist i diagrammet samt i tabellen nedenfor.
C21: =Tekstnøgler!C301 -> SCOPE 3 KATEGORIER I TON CO₂e
C22: =Tekstnøgler!C302 -> Kategori | D22: =Tekstnøgler!C303 -> Opstrøms | E22: =Tekstnøgler!C304 -> Nedstrøms
C23: =Tekstnøgler!C305 -> 1. Indkøb af varer og tjenesteydelser | D23: 6765.5856
C24: =Tekstnøgler!C306 -> 2. Anlægsaktiver
C25: =Tekstnøgler!C307 -> 3. Brændsels- og energirelaterede aktiviteter | D25: 414.72539
C26: =Tekstnøgler!C308 -> 4. Opstrømstransport og distribution | D26: 204.96
C27: =Tekstnøgler!C309 -> 5. Affald fra drift | D27: 0
C28: =Tekstnøgler!C310 -> 6. Forretningsrejser
C29: =Tekstnøgler!C311 -> 7. Medarbejderpendling | D29: 3.6176839
C30: =Tekstnøgler!C312 -> 8. Opstrøms leasede aktiver
C31: =Tekstnøgler!C313 -> 9. Nedstrømstransport og distribution | E31: 546.56
C32: =Tekstnøgler!C314 -> 10. Forarbejdning af solgte produkter
C33: =Tekstnøgler!C315 -> 11. Brug af solgte produkter
C34: =Tekstnøgler!C316 -> 12. Behandling af solgte produkter efter endt levetid | E34: 0
C35: =Tekstnøgler!C317 -> 13. Nedstrøms leasede aktiver
C36: =Tekstnøgler!C318 -> Samlede CO₂e udledninger fordelt på opstrøm og nedstrøm (ton) | D36: =SUM(D23:D30) -> 7388.8887 | E36: =SUM(E31:E35) -> 546.56
C37: =Tekstnøgler!C319 -> Samlet CO₂e udledning i alt (ton) | E37: =D36+E36 -> 7935.4487 | F37: =IF(E37>'Delresultater (GHG)'!F98,Tekstnøgler!C538,"")
C39: =Tekstnøgler!C320 -> Opsummering af virksomhedens beregnede CO₂e-udledning
C41: =Tekstnøgler!C321 -> Nedenstående figur angiver virksomhedens opgjorte udledning i ton CO₂-ækvivalenter fordelt på scope 3 kategorier.
C42: =Tekstnøgler!C322 -> Figur 1: CO₂e udledning fordelt på scope 3 kategorier (ton)

Sheet Største udledningsposter
C2: =Tekstnøgler!C33 -> Resultat | E2: =Tekstnøgler!C2 -> <-- Gå til forsiden
C5: =Hovedresultater!C5 -> Resultat for 0 (År) - Tiltagscase
C6: =Hovedresultater!C6 -> 10.230,61 ton CO₂e
C8: =Tekstnøgler!C71 -> Metodevalg
C10: =Tekstnøgler!C72 -> Resultaterne baserer sig på en række metodiske valg, der er foretaget i forbindelse med beregningerne. I nedenstående tabel kan du se, hvorvidt Radiative Forcing Index (RFI) er medregnet i forbindelse med udledninger fra flytransport. At medregne (eller korrigere for) RFI betyder, at der er taget højde for, at CO₂e udledt højere oppe i atmosfæren har en større drivhuseffekt end CO₂e udledt ved landjorden. Tabellen viser også, om emissionsfaktoren for el baserer sig på det årlige gennemsnit for sammensætningen af produktionen af el (miljødeklaration), eller om der i emissionsfaktoren korrigeres for virksomheders køb af grønne certifikater, såkaldte oprindelsesgarantier (eldeklaration).
C12: =Tekstnøgler!C73 -> Emissionsfaktor | D12: =Tekstnøgler!C74 -> Metodevalg
C13: =Tekstnøgler!C75 -> Valg af emissionsfaktor for elektricitet | D13: =IF(ISBLANK(Hovedresultater!$E13),"",Hovedresultater!$E13) -> Eldeklaration
C14: =Tekstnøgler!C76 -> Emissionsfaktor for flytransport | D14: =IF(ISBLANK(Hovedresultater!$E14),"",Hovedresultater!$E14) -> Inkluder RFI
C17: =Tekstnøgler!C325 -> Største CO₂e-udledning
C19: =Tekstnøgler!C583 -> På denne side kan du få indblik i, hvilke af dine indtastninger i Klimakompasset, der fylder mest i din virksomheds klimaregnskab – en såkaldt hot spot analyse. Med udpegning af din virksomheds 20 største kilder til udledninger får du et hurtigt overblik over potentielle reduktionsmuligheder, så du kan fokusere på de vigtigste steder først, og prioritere de reducerende tiltag, der har størst effekt i din virksomhed. I tabellen nederst på siden kan du se de 20 indtastninger med størst udledning, og hvor stor en procentdel de udgør af virksomhedens samlede udledninger i scope 1, 2 og 3.
C21: =Tekstnøgler!C584 -> Figur 1: CO₂e-udledning i ton scope 1, 2 og 3 fordelt på poster
C39: =Tekstnøgler!C328 -> OVERSIGT OVER UDLEDNINGEN I TON CO₂-E FORDELT PÅ POSTER
C40: =Tekstnøgler!C329 -> Beskrivelse | D40: =Tekstnøgler!C330 -> Placering | E40: =Tekstnøgler!C203 -> Scope 1 | F40: =Tekstnøgler!C204 -> Scope 2 | G40: =Tekstnøgler!C205 -> Scope 3 | H40: =Tekstnøgler!C580 -> Scope 1, 2 og 3 udledning | I40: =Tekstnøgler!C581 -> Procentdel af udledning i scope 1, 2 og 3
C41: =Tekstnøgler!C374&" > "&Tekstnøgler!C557&" > "&Tekstnøgler!C135 -> Indkøb > Materialer > Indkøb af materialer i fysiske enheder | D41: Træ | E41: 0 | F41: 0 | G41: 3311.8492 | H41: =SUM(E41:G41) -> 3311.8492 | I41: =IF(ISBLANK($H41),,$H41/Hovedresultater!$D$29) -> 0.32371967
C42: =Tekstnøgler!C374&" > "&Tekstnøgler!C557&" > "&Tekstnøgler!C135 -> Indkøb > Materialer > Indkøb af materialer i fysiske enheder | D42: Nyt glas | E42: 0 | F42: 0 | G42: 2500.133 | H42: =SUM(E42:G42) -> 2500.133 | I42: =IF(ISBLANK($H42),,$H42/Hovedresultater!$D$29) -> 0.24437774
C43: =Tekstnøgler!C373&" > "&Tekstnøgler!C553&" > "&Tekstnøgler!C122 -> Energi og processer > Elektricitet > Forbrug af elektricitet | D43: Elektricitet | E43: 0 | F43: 1851.795 | G43: 331.10115 | H43: =SUM(E43:G43) -> 2182.8961 | I43: =IF(ISBLANK($H43),,$H43/Hovedresultater!$D$29) -> 0.21336914
C44: =Tekstnøgler!C374&" > "&Tekstnøgler!C557&" > "&Tekstnøgler!C135 -> Indkøb > Materialer > Indkøb af materialer i fysiske enheder | D44: Stål | E44: 0 | F44: 0 | G44: 948.94802 | H44: =SUM(E44:G44) -> 948.94802 | I44: =IF(ISBLANK($H44),,$H44/Hovedresultater!$D$29) -> 0.092755775
C45: =Tekstnøgler!C375&" > "&Tekstnøgler!C566&" > "&Tekstnøgler!C176 -> Transport > Varetransport til kunde > Varetransport i fysiske enheder | D45: Varetransport til ku | E45: 0 | F45: 0 | G45: 546.56 | H45: =SUM(E45:G45) -> 546.56 | I45: =IF(ISBLANK($H45),,$H45/Hovedresultater!$D$29) -> 0.053423997
C46: =Tekstnøgler!C373&" > "&Tekstnøgler!C554&" > "&Tekstnøgler!C126 -> Energi og processer > Varme og procesenergi > Brændsler | D46: Varme | E46: 326.8582 | F46: 0 | G46: 52.287801 | H46: =SUM(E46:G46) -> 379.146 | I46: =IF(ISBLANK($H46),,$H46/Hovedresultater!$D$29) -> 0.037059966
C47: =Tekstnøgler!C375&" > "&Tekstnøgler!C565&" > "&Tekstnøgler!C172 -> Transport > Varetransport til virksomhed > Varetransport i fysiske enheder | D47: Transport til virk | E47: 0 | F47: 0 | G47: 204.96 | H47: =SUM(E47:G47) -> 204.96 | I47: =IF(ISBLANK($H47),,$H47/Hovedresultater!$D$29) -> 0.020033999
C48: =Tekstnøgler!C373&" > "&Tekstnøgler!C554&" > "&Tekstnøgler!C126 -> Energi og processer > Varme og procesenergi > Brændsler | D48: Benzin | E48: 108.58751 | F48: 0 | G48: 29.206461 | H48: =SUM(E48:G48) -> 137.79397 | I48: =IF(ISBLANK($H48),,$H48/Hovedresultater!$D$29) -> 0.013468795
C49: =Tekstnøgler!C375&" > "&Tekstnøgler!C563&" > "&Tekstnøgler!C163 -> Transport > Egne og leasede transportmidler > Egne og leasede transportmidler | D49: Kundemøder | E49: 7.9191354 | F49: 0 | G49: 2.1299865 | H49: =SUM(E49:G49) -> 10.049122 | I49: =IF(ISBLANK($H49),,$H49/Hovedresultater!$D$29) -> 0.00098226042
C50: =Tekstnøgler!C374&" > "&Tekstnøgler!C558&" > "&Tekstnøgler!C140 -> Indkøb > Produkter og services > Indkøb af produkter i fysiske enheder | D50: Vand | E50: 0 | F50: 0 | G50: 4.6554366 | H50: =SUM(E50:G50) -> 4.6554366 | I50: =IF(ISBLANK($H50),,$H50/Hovedresultater!$D$29) -> 0.00045504982
C51: =Tekstnøgler!C375&" > "&Tekstnøgler!C564&" > "&Tekstnøgler!C167 -> Transport > Medarbejdertransport > Pendling | D51: Pendling | E51: 0 | F51: 0 | G51: 3.6176839 | H51: =SUM(E51:G51) -> 3.6176839 | I51: =IF(ISBLANK($H51),,$H51/Hovedresultater!$D$29) -> 0.00035361375
C52: =Tekstnøgler!C376&" > "&Tekstnøgler!C568&" > "&Tekstnøgler!C182 -> Affald og genbrug > Affald > Affald | D52: Glas | E52: 0 | F52: 0 | G52: 0 | H52: =SUM(E52:G52) -> 0 | I52: =IF(ISBLANK($H52),,$H52/Hovedresultater!$D$29) -> 0
C53: =Tekstnøgler!C376&" > "&Tekstnøgler!C568&" > "&Tekstnøgler!C182 -> Affald og genbrug > Affald > Affald | D53: Stål | E53: 0 | F53: 0 | G53: 0 | H53: =SUM(E53:G53) -> 0 | I53: =IF(ISBLANK($H53),,$H53/Hovedresultater!$D$29) -> 0
C54: =Tekstnøgler!C376&" > "&Tekstnøgler!C568&" > "&Tekstnøgler!C182 -> Affald og genbrug > Affald > Affald | D54: Træ | E54: 0 | F54: 0 | G54: 0 | H54: =SUM(E54:G54) -> 0 | I54: =IF(ISBLANK($H54),,$H54/Hovedresultater!$D$29) -> 0
C55: =Tekstnøgler!C377&" > "&Tekstnøgler!C573&" > "&Tekstnøgler!C191 -> Solgte produkter > End-of-life behandling > Håndtering af affaldsprodukt | D55: Glas | E55: 0 | F55: 0 | G55: 0 | H55: =SUM(E55:G55) -> 0 | I55: =IF(ISBLANK($H55),,$H55/Hovedresultater!$D$29) -> 0
C56: =Tekstnøgler!C377&" > "&Tekstnøgler!C573&" > "&Tekstnøgler!C191 -> Solgte produkter > End-of-life behandling > Håndtering af affaldsprodukt | D56: Træ | E56: 0 | F56: 0 | G56: 0 | H56: =SUM(E56:G56) -> 0 | I56: =IF(ISBLANK($H56),,$H56/Hovedresultater!$D$29) -> 0
C57: =Tekstnøgler!C377&" > "&Tekstnøgler!C573&" > "&Tekstnøgler!C191 -> Solgte produkter > End-of-life behandling > Håndtering af affaldsprodukt | D57: Stål | E57: 0 | F57: 0 | G57: 0 | H57: =SUM(E57:G57) -> 0 | I57: =IF(ISBLANK($H57),,$H57/Hovedresultater!$D$29) -> 0
H58: =SUM(E58:G58) -> 0 | I58: =IF(ISBLANK($H58),,$H58/Hovedresultater!$D$29) -> 0
H59: =SUM(E59:G59) -> 0 | I59: =IF(ISBLANK($H59),,$H59/Hovedresultater!$D$29) -> 0
H60: =SUM(E60:G60) -> 0 | I60: =IF(ISBLANK($H60),,$H60/Hovedresultater!$D$29) -> 0
C61: =Tekstnøgler!C105 -> Ton CO₂e | E61: =SUM(E41:E60) -> 443.36484 | F61: =SUM(F41:F60) -> 1851.795 | G61: =SUM(G41:G60) -> 7935.4487 | H61: =SUM(H41:H60) -> 10230.609 | I61: =SUM(I41:I60) -> 1

Sheet Fremskrivning - Hovedresultater
C2: =Tekstnøgler!C335 -> Resultater for fremskrivning | H2: =Tekstnøgler!C2 -> <-- Gå til forsiden
C5: =Tekstnøgler!C336 -> Fremskrivning for
C7: =Tekstnøgler!C337 -> Basisberegning
C8: [TITEL]
C10: =Tekstnøgler!C339 -> Basisår | D10: =Tekstnøgler!C340 -> Slutår | E10: =Tekstnøgler!C588 -> Emissionsfaktorår
C11: 2015 | D11: 2030 | E11: =Emissionsfaktorer!B5 -> 2021
C13: =Tekstnøgler!C341 -> Valg af årlig vækst
C14: =Tekstnøgler!C342 -> Årlig vækstrate | D14: 0.03
C15: =Tekstnøgler!C343 -> Type af vækstrate | D15: Ekspotentiel
C18: =Tekstnøgler!C344 -> Hovedresultater
C20: =IF('Fremskrivning - Delresultater'!M28-'Fremskrivning - Delresultater'!H28>=0,Tekstnøgler!C386&'Fremskrivning - Hovedresultater'!D14*100&"% ("&'Fremskrivning - Hovedresultater'!D15&Tekstnøgler!C387&ROUND('Fremskrivning - Delresultater'!Z27*100,0)&Tekstnøgler!C389&'Fremskrivning - Hovedresultater'!D11&".",Tekstnøgler!C386&'Fremskrivning - Hovedresultater'!D14*100&"% ("&'Fremskrivning - Hovedresultater'!D15&Tekstnøgler!C388&ROUND('Fremskrivning - Delresultater'!Z26*100,0)&Tekstnøgler!C389&'Fremskrivning - Hovedresultater'!D11&".") -> Med en årlig vækst på 3% (Ekspotentiel) estimeres det, at din virksomheds CO₂e-udledninger vil falde med -50% frem mod år2030.
C22: =Tekstnøgler!C346 -> Tabel 1: Oversigt over virksomhedens CO₂e-udledninger fordelt på scopes
C23: =Tekstnøgler!C347 -> Titel | D23: =Tekstnøgler!C348 -> Ton CO₂e | F23: =Tekstnøgler!C349 -> Fordeling i %
D24: =$C$11 -> 2015 | E24: =$D$11 -> 2030 | F24: =$C$11 -> 2015 | G24: =$D$11 -> 2030
C25: =Tekstnøgler!C351 -> Scope 1 | D25: =LOOKUP($C$11,'Fremskrivning - Delresultater'!$D$15:$X$15,'Fremskrivning - Delresultater'!D16:X16) -> 11 | E25: =LOOKUP($D$11,'Fremskrivning - Delresultater'!$D$15:$X$15,'Fremskrivning - Delresultater'!D16:X16) -> 4 | F25: =IF($D$28 = 0,"",D25/$D$28) -> 0.42307692 | G25: =IF($E$28 = 0,"",E25/$E$28) -> 0.30769231
C26: =Tekstnøgler!C352 -> Scope 2 | D26: =LOOKUP($C$11,'Fremskrivning - Delresultater'!$D$15:$X$15,'Fremskrivning - Delresultater'!D17:X17) -> 7 | E26: =LOOKUP($D$11,'Fremskrivning - Delresultater'!$D$15:$X$15,'Fremskrivning - Delresultater'!D17:X17) -> 4 | F26: =IF($D$28 = 0,"",D26/$D$28) -> 0.26923077 | G26: =IF($E$28 = 0,"",E26/$E$28) -> 0.30769231
C27: =Tekstnøgler!C353 -> Scope 3 | D27: =LOOKUP($C$11,'Fremskrivning - Delresultater'!$D$15:$X$15,'Fremskrivning - Delresultater'!D18:X18) -> 8 | E27: =LOOKUP($D$11,'Fremskrivning - Delresultater'!$D$15:$X$15,'Fremskrivning - Delresultater'!D18:X18) -> 5 | F27: =IF($D$28 = 0,"",D27/$D$28) -> 0.30769231 | G27: =IF($E$28 = 0,"",E27/$E$28) -> 0.38461538
C28: =Tekstnøgler!C95 -> Total | D28: =SUM(D25:D27) -> 26 | E28: =SUM(E25:E27) -> 13 | F28: =SUM(F25:F27) -> 1 | G28: =SUM(G25:G27) -> 1
C29: =Tekstnøgler!C355 -> Udenfor scopes | D29: =LOOKUP($C$11,'Fremskrivning - Delresultater'!D117:X117,'Fremskrivning - Delresultater'!D193:X193) -> 8 | E29: =LOOKUP($D$11,'Fremskrivning - Delresultater'!D117:X117,'Fremskrivning - Delresultater'!D193:X193) -> 8
A30: Ny | C30: =IF(E25>D25,"Målsætning for scope 1 fratrukket reduktionen","Målsætning for scope 1") -> Målsætning for scope 1 | I30: =MIN(E25,D25) -> 4 | L30: Skjult række
A31: Ny | C31: =IF(D25>E25,Tekstnøgler!C356,Tekstnøgler!C359) -> Reduktion opnået (scope 1) | I31: =IF(-MIN(E25-D25,0)=0,"",-MIN(E25-D25,0)) -> 7 | L31: Skjult række
A32: Ny | C32: =IF(D25<=E25,Tekstnøgler!C358,Tekstnøgler!C359) -> (ikke relevant) | I32: =IF(MAX(E25-D25,0)=0,"",MAX(E25-D25,0)) | L32: Skjult række
A33: Ny | C33: =IF(E25>D25,"Målsætning for scope 1 fratrukket reduktionen (visning)","Målsætning for scope 1 (visning)") -> Målsætning for scope 1 (visning) | J33: =I30 -> 4 | L33: Skjult række
A34: Ny | C34: =IF(D25>E25,"Reduktion opnået for scope 1 (visning)","") -> Reduktion opnået for scope 1 (visning) | J34: =I31 -> 7 | L34: Skjult række
A35: Ny | C35: =IF(D25<=E25,"Forskel til målet for scope 1 (visning)","") | J35: =I32 | L35: Skjult række
A36: Ny | C36: Etikets værdi for scope 1 (reduktion) | J36: =IF(E25-D25<0,ROUND((E25-D25)/D25,3),"") -> -0.636 | L36: Skjult række
A37: Ny | C37: Etikets værdi for scope 1 (stigning) | J37: =IF(E25-D25>=0,ROUND((E25-D25)/D25,3),"") | L37: Skjult række
A38: Ny | L38: Skjult række
A39: Ny | D39: =$D$24 -> 2015 | E39: =$E$24 -> 2030 | L39: Skjult række
A40: Ny | C40: =$C$26 -> Scope 2 | D40: =$D26 -> 7 | E40: =$E26 -> 4 | L40: Skjult række
A41: Ny | C41: =IF(E26>D26,"Målsætning for scope 2 fratrukket reduktionen","Målsætning for scope 2") -> Målsætning for scope 2 | I41: =MIN(E26,D26) -> 4 | L41: Skjult række
A42: Ny | C42: =IF(D26>E26,Tekstnøgler!C360,Tekstnøgler!C363) -> Reduktion opnået (scope 2) | I42: =IF(-MIN(E26-D26,0)=0,"",-MIN(E26-D26,0)) -> 3 | L42: Skjult række
A43: Ny | C43: =IF(D26<=E26,Tekstnøgler!C362,Tekstnøgler!C363) -> (ikke relevant) | I43: =IF(MAX(E26-D26,0)=0,"",MAX(E26-D26,0)) | L43: Skjult række
A44: Ny | C44: =IF(E26>D26,"Målsætning for scope 2 fratrukket reduktionen (visning)","Målsætning for scope 2 (visning)") -> Målsætning for scope 2 (visning) | J44: =I41 -> 4 | L44: Skjult række
A45: Ny | C45: =IF(D26>E26,"Reduktion opnået for scope 2 (visning)","") -> Reduktion opnået for scope 2 (visning) | J45: =I42 -> 3 | L45: Skjult række
A46: Ny | C46: =IF(D26<=E26,"Stigning af scope 2 udledninger (visning)","") | J46: =I43 | L46: Skjult række
A47: Ny | C47: Etikets værdi for scope 2 (reduktion) | J47: =IF(E26-D26<0,ROUND((E26-D26)/D26,3),"") -> -0.429 | L47: Skjult række
A48: Ny | C48: Etikets værdi for scope 2 (stigning) | J48: =IF(E26-D26>=0,ROUND((E26-D26)/D26,3),"") | L48: Skjult række
A49: Ny | L49: Skjult række
A50: Ny | D50: =$D$24 -> 2015 | E50: =$E$24 -> 2030 | L50: Skjult række
A51: Ny | C51: =$C$27 -> Scope 3 | D51: =$D27 -> 8 | E51: =$E27 -> 5 | L51: Skjult række
A52: Ny | C52: =IF(E27>D27,"Målsætning for scope 3 fratrukket reduktionen","Målsætning for scope 3") -> Målsætning for scope 3 | I52: =MIN(E27,D27) -> 5 | L52: Skjult række
A53: Ny | C53: =IF(D27>E27,Tekstnøgler!C364,Tekstnøgler!C367) -> Reduktion opnået (scope 3) | I53: =IF(-MIN(E27-D27,0)=0,"",-MIN(E27-D27,0)) -> 3 | L53: Skjult række
A54: Ny | C54: =IF(D27<=E27,Tekstnøgler!C366,Tekstnøgler!C367) -> (ikke relevant) | I54: =IF(MAX(E27-D27,0)=0,"",MAX(E27-D27,0)) | L54: Skjult række
A55: Ny | C55: =IF(E27>D27,"Målsætning for scope 3 fratrukket reduktionen (visning)","Målsætning for scope 3 (visning)") -> Målsætning for scope 3 (visning) | J55: =I52 -> 5 | L55: Skjult række
A56: Ny | C56: =IF(D27>E27,"Reduktion opnået for scope 3 (visning)","") -> Reduktion opnået for scope 3 (visning) | J56: =I53 -> 3 | L56: Skjult række
A57: Ny | C57: =IF(D27<=E27,"Stigning af scope 3 udledninger (visning)","") | J57: =I54 | L57: Skjult række
A58: Ny | C58: Etikets værdi for scope 3 (reduktion) | J58: =IF(E27-D27<0,ROUND((E27-D27)/D27,3),"") -> -0.375 | L58: Skjult række
A59: Ny | C59: Label scope 3 (stigning) | J59: =IF(E27-D27>=0,ROUND((E27-D27)/D27,3),"") | L59: Skjult række
C62: =Tekstnøgler!C368 -> Tabel 2: Oversigt over virksomhedens CO₂e-udledninger fordelt på hovedkategorier
D63: =Tekstnøgler!C370 -> Ton CO₂e | F63: =Tekstnøgler!C371 -> Fordeling i %
C64: =Tekstnøgler!C372 -> Hovedkategori | D64: =$C$11 -> 2015 | E64: =$D$11 -> 2030 | F64: =$C$11 -> 2015 | G64: =$D$11 -> 2030
C65: =Tekstnøgler!C373 -> Energi og processer | D65: 1000 | E65: 2000 | F65: =IF(ISBLANK(D65),,D65/$D$70) -> 0.16666667 | G65: =IF(ISBLANK(E65),,E65/$E$70) -> 0.16666667
C66: =Tekstnøgler!C374 -> Indkøb | D66: 1500 | E66: 2000 | F66: =IF(ISBLANK(D66),,D66/$D$70) -> 0.25 | G66: =IF(ISBLANK(E66),,E66/$E$70) -> 0.16666667
C67: =Tekstnøgler!C375 -> Transport | E67: 2000 | F67: =IF(ISBLANK(D67),,D67/$D$70) -> 0 | G67: =IF(ISBLANK(E67),,E67/$E$70) -> 0.16666667
C68: =Tekstnøgler!C376 -> Affald og genbrug | D68: 500 | E68: 2000 | F68: =IF(ISBLANK(D68),,D68/$D$70) -> 0.083333333 | G68: =IF(ISBLANK(E68),,E68/$E$70) -> 0.16666667
C69: =Tekstnøgler!C377 -> Solgte produkter | D69: 3000 | E69: 4000 | F69: =IF(ISBLANK(D69),,D69/$D$70) -> 0.5 | G69: =IF(ISBLANK(E69),,E69/$E$70) -> 0.33333333
C70: =Tekstnøgler!C378 -> Total | D70: =SUM(D65:D69) -> 6000 | E70: =SUM(E65:E69) -> 12000 | F70: =SUM(F65:F69) -> 1 | G70: =SUM(G65:G69) -> 1
C74: =Tekstnøgler!C379 -> Opsummering af virksomhedens estimerede fremskrivning på scopes og hovedkategorier
C76: =Tekstnøgler!C380 -> Nedenstående figurer opsummerer virksomhedens estimerede udledninger i de kommende 10 år. Figur 1 angiver virksomhedens estimerede CO₂e-udledning i ton CO₂e-ækvivalenter fordelt på scopes for alle fremskrevne år. Figur 2 viser den fordeling af CO₂e-udledningen fordelt på hovedkategorier for slut- og basisår.
C77: =Tekstnøgler!C381 -> Figur 1: Fremskrevne CO₂e-udledninger fordelt på scopes (ton)
C98: =Tekstnøgler!C382 -> Figur 2: Fremskrevne CO₂e-udledninger fordelt på hovedkategorier (ton) | F98: =Tekstnøgler!C383 -> Figur 3: Fremskrevne CO₂e-udledninger fordelt på hovedkategorier - Scope 1 (ton)
C118: =Tekstnøgler!C384 -> Figur 4: Fremskrevne CO₂e-udledninger fordelt på hovedkategorier - Scope 2 (ton) | F118: =Tekstnøgler!C385 -> Figur 5: Fremskrevne CO₂e-udledninger fordelt på hovedkategorier - Scope 3 (ton)

Sheet Fremskrivning - Delresultater
C2: =Tekstnøgler!C392 -> Resultat | J2: =Tekstnøgler!C2 -> <-- Gå til forsiden
C5: =Tekstnøgler!C393 -> Delresultat for fremskrivning
C6: =Tekstnøgler!C394 -> Delresultat for fremskrivning
C10: =Tekstnøgler!C395 -> Delresultatet
C12: =Tekstnøgler!C396 -> Her ses en mere detaljeret resultatvisning for fremskrivning. Tabellen viser den tilhørende udledning i ton CO₂e for alle underkategorierne, som der er indtastet data for.
C13: =Tekstnøgler!C397 -> Tabel 1: Oversigt over virksomhedens CO₂e-udledninger fordelt på scopes
C14: =Tekstnøgler!C200 -> Scope | D14: =Tekstnøgler!C105 -> Ton CO₂e
D15: 2015 | E15: 2016 | F15: 2017 | G15: 2018 | H15: 2019 | I15: 2020 | J15: 2021 | K15: 2022 | L15: 2023 | M15: 2024 | N15: 2025 | O15: 2026 | P15: 2027 | Q15: 2028 | R15: 2029 | S15: 2030 | T15: 2031 | U15: 2032 | V15: 2033 | W15: 2034 | X15: 2035
C16: =Tekstnøgler!C203 -> Scope 1 | D16: =D109 -> 11 | E16: =H109 -> 8 | F16: =L109 -> 8 | G16: =P109 -> 8 | H16: =T109 -> 8 | I16: =X109 -> 8 | J16: =AB109 -> 8 | K16: =AF109 -> 8 | L16: =AJ109 -> 8 | M16: =AN109 -> 8 | N16: =AR109 -> 8 | O16: =AV109 -> 8 | P16: =AZ109 -> 8 | Q16: =BD109 -> 8 | R16: =BH109 -> 8 | S16: =BL109 -> 4 | T16: =BP109 -> 8 | U16: =BT109 -> 8 | V16: =BX109 -> 8 | W16: =CB109 -> 8 | X16: =CF109 -> 8
C17: =Tekstnøgler!C204 -> Scope 2 | D17: =E109 -> 7 | E17: =I109 -> 8 | F17: =M109 -> 8 | G17: =Q109 -> 8 | H17: =U109 -> 8 | I17: =Y109 -> 20 | J17: =AC109 -> 8 | K17: =AG109 -> 8 | L17: =AK109 -> 8 | M17: =AO109 -> 8 | N17: =AS109 -> 8 | O17: =AW109 -> 8 | P17: =BA109 -> 8 | Q17: =BE109 -> 8 | R17: =BI109 -> 21 | S17: =BM109 -> 4 | T17: =BQ109 -> 8 | U17: =BU109 -> 8 | V17: =BY109 -> 8 | W17: =CC109 -> 8 | X17: =CG109 -> 8
C18: =Tekstnøgler!C205 -> Scope 3 | D18: =F109 -> 8 | E18: =J109 -> 8 | F18: =N109 -> 8 | G18: =R109 -> 8 | H18: =V109 -> 8 | I18: =Z109 -> 8 | J18: =AD109 -> 8 | K18: =AH109 -> 8 | L18: =AL109 -> 8 | M18: =AP109 -> 8 | N18: =AT109 -> 8 | O18: =AX109 -> 8 | P18: =BB109 -> 8 | Q18: =BF109 -> 20 | R18: =BJ109 -> 8 | S18: =BN109 -> 5 | T18: =BR109 -> 8 | U18: =BV109 -> 8 | V18: =BZ109 -> 8 | W18: =CD109 -> 8 | X18: =CH109 -> 8
C19: =Tekstnøgler!C402 -> Total | D19: =SUM(D16:D18) -> 26 | E19: =SUM(E16:E18) -> 24 | F19: =SUM(F16:F18) -> 24 | G19: =SUM(G16:G18) -> 24 | H19: =SUM(H16:H18) -> 24 | I19: =SUM(I16:I18) -> 36 | J19: =SUM(J16:J18) -> 24 | K19: =SUM(K16:K18) -> 24 | ... X19: =SUM(X16:X18) -> 24
A20: Ny | C20: =IF(M28>H28,"Scopes 1+2+3 i basis år","Scopes 1+2+3 i målår") -> Scopes 1+2+3 i målår | Y20: =MIN(M28,H28) -> 13 | AA20: Skjult rækker
A21: Ny | C21: =IF(M28<H28,Tekstnøgler!C403,Tekstnøgler!C404) -> Reduktion opnået (scope 1+2+3) | Y21: =-MIN(M28-H28,0) -> 13 | AA21: Skjult rækker
A22: Ny | C22: =IF(M28>=H28,Tekstnøgler!C405,Tekstnøgler!C406) -> (ikke relevant) | Y22: =MAX(M28-H28,0) -> 0 | AA22: Skjult rækker
A23: Ny | C23: =IF(M28>H28,"Scopes 1+2+3 i basis år (visning)","Scopes 1+2+3 i målår (visning)") -> Scopes 1+2+3 i målår (visning) | Z23: =Y20 -> 13 | AA23: Skjult rækker
A24: Ny | C24: =IF(M28<H28,"Reduktion opnået for alle scopes (visning)","") -> Reduktion opnået for alle scopes (visning) | Z24: =Y21 -> 13 | AA24: Skjult rækker
A25: Ny | C25: =IF(M28>=H28,"Manglende reduktion for alle scopes (visning)","") | Z25: =Y22 -> 0 | AA25: Skjult rækker
A26: Ny | C26: Etikets værdi for scope 1+2+3 (reduktion) | Z26: =IF(M28-H28<0,ROUND((M28-H28)/H28,3),"") -> -0.5 | AA26: Skjult rækker
A27: Ny | C27: Etikets værdi for scope 1+2+3 (stigning) | Z27: =IF(M28-H28>=0,ROUND((M28-H28)/H28,3),"") | AA27: Skjult rækker
A28: Ny | E28: Scope 1+2+3 for basisår: | H28: =LOOKUP('Fremskrivning - Hovedresultater'!C11,'Fremskrivning - Delresultater'!D15:X15,'Fremskrivning - Delresultater'!D19:X19) -> 26 | J28: Scope 1+2+3 for slutår: | M28: =LOOKUP('Fremskrivning - Hovedresultater'!D11,'Fremskrivning - Delresultater'!D15:X15,'Fremskrivning - Delresultater'!D19:X19) -> 13 | AA28: Skjult rækker
C31: =Tekstnøgler!C408 -> Tabel 2. Oversigt over CO₂e-udledningen fordelt på hoved- og underkategorier
C32: År | D32: 2015 | H32: 2016 | L32: 2017 | P32: 2018 | T32: 2019 | X32: 2020 | AB32: 2021 | AF32: 2022 | AJ32: 2023 | AN32: 2024 | AR32: 2025 | AV32: 2026 | AZ32: 2027 | BD32: 2028 | BH32: 2029 | BL32: 2030 | BP32: 2031 | BT32: 2032 | BX32: 2033 | CB32: 2034 | CF32: 2035
C33: =Tekstnøgler!C115 -> Hovedkategori | D33: =Tekstnøgler!$C$409 -> Scope 1 - faktor | E33: =Tekstnøgler!$C$410 -> Scope 2 - faktor | F33: =Tekstnøgler!$C$411 -> Scope 3 - faktor | G33: =Tekstnøgler!$C$412 -> Samlede CO₂e udledning | H33: =Tekstnøgler!$C$409 -> Scope 1 - faktor | I33: =Tekstnøgler!$C$410 -> Scope 2 - faktor | J33: =Tekstnøgler!$C$411 -> Scope 3 - faktor | K33: =Tekstnøgler!$C$412 -> Samlede CO₂e udledning | L33: =Tekstnøgler!$C$409 -> Scope 1 - faktor | M33: =Tekstnøgler!$C$410 -> Scope 2 - faktor | N33: =Tekstnøgler!$C$411 -> Scope 3 - faktor | O33: =Tekstnøgler!$C$412 -> Samlede CO₂e udledning | P33: =Tekstnøgler!$C$409 -> Scope 1 - faktor | Q33: =Tekstnøgler!$C$410 -> Scope 2 - faktor | R33: =Tekstnøgler!$C$411 -> Scope 3 - faktor | S33: =Tekstnøgler!$C$412 -> Samlede CO₂e udledning | T33: =Tekstnøgler!$C$409 -> Scope 1 - faktor | U33: =Tekstnøgler!$C$410 -> Scope 2 - faktor | V33: =Tekstnøgler!$C$411 -> Scope 3 - faktor | W33: =Tekstnøgler!$C$412 -> Samlede CO₂e udledning | X33: =Tekstnøgler!$C$409 -> Scope 1 - faktor | Y33: =Tekstnøgler!$C$410 -> Scope 2 - faktor | Z33: =Tekstnøgler!$C$411 -> Scope 3 - faktor | AA33: =Tekstnøgler!$C$412 -> Samlede CO₂e udledning | AB33: =Tekstnøgler!$C$409 -> Scope 1 - faktor | AC33: =Tekstnøgler!$C$410 -> Scope 2 - faktor | AD33: =Tekstnøgler!$C$411 -> Scope 3 - faktor | AE33: =Tekstnøgler!$C$412 -> Samlede CO₂e udledning | AF33: =Tekstnøgler!$C$409 -> Scope 1 - faktor | AG33: =Tekstnøgler!$C$410 -> Scope 2 - faktor | AH33: =Tekstnøgler!$C$411 -> Scope 3 - faktor | AI33: =Tekstnøgler!$C$412 -> Samlede CO₂e udledning | AJ33: =Tekstnøgler!$C$409 -> Scope 1 - faktor | AK33: =Tekstnøgler!$C$410 -> Scope 2 - faktor | AL33: =Tekstnøgler!$C$411 -> Scope 3 - faktor | AM33: =Tekstnøgler!$C$412 -> Samlede CO₂e udledning | AN33: =Tekstnøgler!$C$409 -> Scope 1 - faktor | AO33: =Tekstnøgler!$C$410 -> Scope 2 - faktor | AP33: =Tekstnøgler!$C$411 -> Scope 3 - faktor | AQ33: =Tekstnøgler!$C$412 -> Samlede CO₂e udledning | AR33: =Tekstnøgler!$C$409 -> Scope 1 - faktor | AS33: =Tekstnøgler!$C$410 -> Scope 2 - faktor | AT33: =Tekstnøgler!$C$411 -> Scope 3 - faktor | AU33: =Tekstnøgler!$C$412 -> Samlede CO₂e udledning | AV33: =Tekstnøgler!$C$409 -> Scope 1 - faktor | AW33: =Tekstnøgler!$C$410 -> Scope 2 - faktor | AX33: =Tekstnøgler!$C$411 -> Scope 3 - faktor | AY33: =Tekstnøgler!$C$412 -> Samlede CO₂e udledning | AZ33: =Tekstnøgler!$C$409 -> Scope 1 - faktor | BA33: =Tekstnøgler!$C$410 -> Scope 2 - faktor | BB33: =Tekstnøgler!$C$411 -> Scope 3 - faktor | BC33: =Tekstnøgler!$C$412 -> Samlede CO₂e udledning | BD33: =Tekstnøgler!$C$409 -> Scope 1 - faktor | BE33: =Tekstnøgler!$C$410 -> Scope 2 - faktor | BF33: =Tekstnøgler!$C$411 -> Scope 3 - faktor | BG33: =Tekstnøgler!$C$412 -> Samlede CO₂e udledning | BH33: =Tekstnøgler!$C$409 -> Scope 1 - faktor | BI33: =Tekstnøgler!$C$410 -> Scope 2 - faktor | BJ33: =Tekstnøgler!$C$411 -> Scope 3 - faktor | BK33: =Tekstnøgler!$C$412 -> Samlede CO₂e udledning | BL33: =Tekstnøgler!$C$409 -> Scope 1 - faktor | BM33: =Tekstnøgler!$C$410 -> Scope 2 - faktor | BN33: =Tekstnøgler!$C$411 -> Scope 3 - faktor | BO33: =Tekstnøgler!$C$412 -> Samlede CO₂e udledning | BP33: =Tekstnøgler!$C$409 -> Scope 1 - faktor | BQ33: =Tekstnøgler!$C$410 -> Scope 2 - faktor | BR33: =Tekstnøgler!$C$411 -> Scope 3 - faktor | BS33: =Tekstnøgler!$C$412 -> Samlede CO₂e udledning | BT33: =Tekstnøgler!$C$409 -> Scope 1 - faktor | BU33: =Tekstnøgler!$C$410 -> Scope 2 - faktor | BV33: =Tekstnøgler!$C$411 -> Scope 3 - faktor | BW33: =Tekstnøgler!$C$412 -> Samlede CO₂e udledning | BX33: =Tekstnøgler!$C$409 -> Scope 1 - faktor | BY33: =Tekstnøgler!$C$410 -> Scope 2 - faktor | BZ33: =Tekstnøgler!$C$411 -> Scope 3 - faktor | CA33: =Tekstnøgler!$C$412 -> Samlede CO₂e udledning | CB33: =Tekstnøgler!$C$409 -> Scope 1 - faktor | CC33: =Tekstnøgler!$C$410 -> Scope 2 - faktor | CD33: =Tekstnøgler!$C$411 -> Scope 3 - faktor | CE33: =Tekstnøgler!$C$412 -> Samlede CO₂e udledning | CF33: =Tekstnøgler!$C$409 -> Scope 1 - faktor | CG33: =Tekstnøgler!$C$410 -> Scope 2 - faktor | CH33: =Tekstnøgler!$C$411 -> Scope 3 - faktor | CI33: =Tekstnøgler!$C$412 -> Samlede CO₂e udledning
D34: =Tekstnøgler!$C$413 -> (ton CO₂e) | E34: =Tekstnøgler!$C$413 -> (ton CO₂e) | F34: =Tekstnøgler!$C$413 -> (ton CO₂e) | G34: =Tekstnøgler!$C$413 -> (ton CO₂e) | H34: =Tekstnøgler!$C$413 -> (ton CO₂e) | I34: =Tekstnøgler!$C$413 -> (ton CO₂e) | J34: =Tekstnøgler!$C$413 -> (ton CO₂e) | K34: =Tekstnøgler!$C$413 -> (ton CO₂e) | ... CI34: =Tekstnøgler!$C$413 -> (ton CO₂e)
C35: =Tekstnøgler!C120 -> Energi og processer | D35: =D36+D39+D43+D46 -> 8 | E35: =E36+E39+E43+E46 -> 4 | F35: =F36+F39+F43+F46 -> 5 | G35: =G36+G39+G43+G46 -> 17 | H35: =H36+H39+H43+H46 -> 5 | I35: =I36+I39+I43+I46 -> 5 | J35: =J36+J39+J43+J46 -> 5 | K35: =K36+K39+K43+K46 -> 15 | ... CI35: =CI36+CI39+CI43+CI46 -> 15
C36: =Tekstnøgler!C121 -> Elektricitet | D36: =SUM(D37:D38) -> 5 | E36: =SUM(E37:E38) -> 4 | F36: =SUM(F37:F38) -> 5 | G36: =SUM(G37:G38) -> 14 | H36: =SUM(H37:H38) -> 5 | I36: =SUM(I37:I38) -> 5 | J36: =SUM(J37:J38) -> 5 | K36: =SUM(K37:K38) -> 15 | ... CI36: =SUM(CI37:CI38) -> 15
C37: =Tekstnøgler!C122 -> Forbrug af elektricitet | G37: =D37+E37+F37 -> 0 | K37: =H37+I37+J37 -> 0 | O37: =L37+M37+N37 -> 0 | S37: =P37+Q37+R37 -> 0 | W37: =T37+U37+V37 -> 0 | AA37: =X37+Y37+Z37 -> 0 | AE37: =AB37+AC37+AD37 -> 0 | AI37: =AF37+AG37+AH37 -> 0 | AM37: =AJ37+AK37+AL37 -> 0 | AQ37: =AN37+AO37+AP37 -> 0 | AU37: =AR37+AS37+AT37 -> 0 | AY37: =AV37+AW37+AX37 -> 0 | BC37: =AZ37+BA37+BB37 -> 0 | BG37: =BD37+BE37+BF37 -> 0 | BK37: =BH37+BI37+BJ37 -> 0 | BO37: =BL37+BM37+BN37 -> 0 | BS37: =BP37+BQ37+BR37 -> 0 | BW37: =BT37+BU37+BV37 -> 0 | CA37: =BX37+BY37+BZ37 -> 0 | CE37: =CB37+CC37+CD37 -> 0 | CI37: =CF37+CG37+CH37 -> 0
C38: =Tekstnøgler!C123 -> Forbrug af elektricitet med egne emissionsfaktorer | D38: 5 | E38: 4 | F38: 5 | G38: =D38+E38+F38 -> 14 | H38: 5 | I38: 5 | J38: 5 | K38: =H38+I38+J38 -> 15 | L38: 5 | M38: 5 | N38: 5 | O38: =L38+M38+N38 -> 15 | P38: 5 | Q38: 5 | R38: 5 | S38: =P38+Q38+R38 -> 15 | T38: 5 | U38: 5 | V38: 5 | W38: =T38+U38+V38 -> 15 | X38: 5 | Y38: 5 | Z38: 5 | AA38: =X38+Y38+Z38 -> 15 | AB38: 5 | AC38: 5 | AD38: 5 | AE38: =AB38+AC38+AD38 -> 15 | AF38: 5 | AG38: 5 | AH38: 5 | AI38: =AF38+AG38+AH38 -> 15 | AJ38: 5 | AK38: 5 | AL38: 5 | AM38: =AJ38+AK38+AL38 -> 15 | AN38: 5 | AO38: 5 | AP38: 5 | AQ38: =AN38+AO38+AP38 -> 15 | AR38: 5 | AS38: 5 | AT38: 5 | AU38: =AR38+AS38+AT38 -> 15 | AV38: 5 | AW38: 5 | AX38: 5 | AY38: =AV38+AW38+AX38 -> 15 | AZ38: 5 | BA38: 5 | BB38: 5 | BC38: =AZ38+BA38+BB38 -> 15 | BD38: 5 | BE38: 5 | BF38: 5 | BG38: =BD38+BE38+BF38 -> 15 | BH38: 5 | BI38: 5 | BJ38: 5 | BK38: =BH38+BI38+BJ38 -> 15 | BL38: 1 | BM38: 1 | BN38: 1 | BO38: =BL38+BM38+BN38 -> 3 | BP38: 5 | BQ38: 5 | BR38: 5 | BS38: =BP38+BQ38+BR38 -> 15 | BT38: 5 | BU38: 5 | BV38: 5 | BW38: =BT38+BU38+BV38 -> 15 | BX38: 5 | BY38: 5 | BZ38: 5 | CA38: =BX38+BY38+BZ38 -> 15 | CB38: 5 | CC38: 5 | CD38: 5 | CE38: =CB38+CC38+CD38 -> 15 | CF38: 5 | CG38: 5 | CH38: 5 | CI38: =CF38+CG38+CH38 -> 15
C39: =Tekstnøgler!C124 -> Varme og procesenergi | D39: =SUM(D40:D42) -> 3 | E39: =SUM(E40:E42) -> 0 | F39: =SUM(F40:F42) -> 0 | G39: =SUM(G40:G42) -> 3 | H39: =SUM(H40:H42) -> 0 | I39: =SUM(I40:I42) -> 0 | J39: =SUM(J40:J42) -> 0 | K39: =SUM(K40:K42) -> 0 | ... CI39: =SUM(CI40:CI42) -> 0
C40: =Tekstnøgler!C125 -> Fjernvarme | G40: =D40+E40+F40 -> 0 | K40: =H40+I40+J40 -> 0 | O40: =L40+M40+N40 -> 0 | S40: =P40+Q40+R40 -> 0 | W40: =T40+U40+V40 -> 0 | AA40: =X40+Y40+Z40 -> 0 | AE40: =AB40+AC40+AD40 -> 0 | AI40: =AF40+AG40+AH40 -> 0 | AM40: =AJ40+AK40+AL40 -> 0 | AQ40: =AN40+AO40+AP40 -> 0 | AU40: =AR40+AS40+AT40 -> 0 | AY40: =AV40+AW40+AX40 -> 0 | BC40: =AZ40+BA40+BB40 -> 0 | BG40: =BD40+BE40+BF40 -> 0 | BK40: =BH40+BI40+BJ40 -> 0 | BO40: =BL40+BM40+BN40 -> 0 | BS40: =BP40+BQ40+BR40 -> 0 | BW40: =BT40+BU40+BV40 -> 0 | CA40: =BX40+BY40+BZ40 -> 0 | CE40: =CB40+CC40+CD40 -> 0 | CI40: =CF40+CG40+CH40 -> 0
C41: =Tekstnøgler!C126 -> Brændsler | D41: 3 | G41: =D41+E41+F41 -> 3 | K41: =H41+I41+J41 -> 0 | O41: =L41+M41+N41 -> 0 | S41: =P41+Q41+R41 -> 0 | W41: =T41+U41+V41 -> 0 | AA41: =X41+Y41+Z41 -> 0 | AE41: =AB41+AC41+AD41 -> 0 | AI41: =AF41+AG41+AH41 -> 0 | AM41: =AJ41+AK41+AL41 -> 0 | AQ41: =AN41+AO41+AP41 -> 0 | AU41: =AR41+AS41+AT41 -> 0 | AY41: =AV41+AW41+AX41 -> 0 | BC41: =AZ41+BA41+BB41 -> 0 | BG41: =BD41+BE41+BF41 -> 0 | BK41: =BH41+BI41+BJ41 -> 0 | BO41: =BL41+BM41+BN41 -> 0 | BS41: =BP41+BQ41+BR41 -> 0 | BW41: =BT41+BU41+BV41 -> 0 | CA41: =BX41+BY41+BZ41 -> 0 | CE41: =CB41+CC41+CD41 -> 0 | CI41: =CF41+CG41+CH41 -> 0
C42: =Tekstnøgler!C127 -> Varme og procesenergi med egne emissionsfaktorer | G42: =D42+E42+F42 -> 0 | K42: =H42+I42+J42 -> 0 | O42: =L42+M42+N42 -> 0 | S42: =P42+Q42+R42 -> 0 | W42: =T42+U42+V42 -> 0 | AA42: =X42+Y42+Z42 -> 0 | AE42: =AB42+AC42+AD42 -> 0 | AI42: =AF42+AG42+AH42 -> 0 | AM42: =AJ42+AK42+AL42 -> 0 | AQ42: =AN42+AO42+AP42 -> 0 | AU42: =AR42+AS42+AT42 -> 0 | AY42: =AV42+AW42+AX42 -> 0 | BC42: =AZ42+BA42+BB42 -> 0 | BG42: =BD42+BE42+BF42 -> 0 | BK42: =BH42+BI42+BJ42 -> 0 | BO42: =BL42+BM42+BN42 -> 0 | BS42: =BP42+BQ42+BR42 -> 0 | BW42: =BT42+BU42+BV42 -> 0 | CA42: =BX42+BY42+BZ42 -> 0 | CE42: =CB42+CC42+CD42 -> 0 | CI42: =CF42+CG42+CH42 -> 0
C43: =Tekstnøgler!C128 -> Procesudledning | D43: =SUM(D44:D45) -> 0 | E43: =SUM(E44:E45) -> 0 | F43: =SUM(F44:F45) -> 0 | G43: =SUM(G44:G45) -> 0 | H43: =SUM(H44:H45) -> 0 | I43: =SUM(I44:I45) -> 0 | J43: =SUM(J44:J45) -> 0 | K43: =SUM(K44:K45) -> 0 | ... CI43: =SUM(CI44:CI45) -> 0
C44: =Tekstnøgler!C129 -> Procesudledning | G44: =D44+E44+F44 -> 0 | K44: =H44+I44+J44 -> 0 | O44: =L44+M44+N44 -> 0 | S44: =P44+Q44+R44 -> 0 | W44: =T44+U44+V44 -> 0 | AA44: =X44+Y44+Z44 -> 0 | AE44: =AB44+AC44+AD44 -> 0 | AI44: =AF44+AG44+AH44 -> 0 | AM44: =AJ44+AK44+AL44 -> 0 | AQ44: =AN44+AO44+AP44 -> 0 | AU44: =AR44+AS44+AT44 -> 0 | AY44: =AV44+AW44+AX44 -> 0 | BC44: =AZ44+BA44+BB44 -> 0 | BG44: =BD44+BE44+BF44 -> 0 | BK44: =BH44+BI44+BJ44 -> 0 | BN44: 1 | BO44: =BL44+BM44+BN44 -> 1 | BS44: =BP44+BQ44+BR44 -> 0 | BW44: =BT44+BU44+BV44 -> 0 | CA44: =BX44+BY44+BZ44 -> 0 | CE44: =CB44+CC44+CD44 -> 0 | CI44: =CF44+CG44+CH44 -> 0
C45: =Tekstnøgler!C130 -> Procesudledning med egne emissionsfaktorer | G45: =D45+E45+F45 -> 0 | K45: =H45+I45+J45 -> 0 | O45: =L45+M45+N45 -> 0 | S45: =P45+Q45+R45 -> 0 | W45: =T45+U45+V45 -> 0 | AA45: =X45+Y45+Z45 -> 0 | AE45: =AB45+AC45+AD45 -> 0 | AI45: =AF45+AG45+AH45 -> 0 | AM45: =AJ45+AK45+AL45 -> 0 | AQ45: =AN45+AO45+AP45 -> 0 | AU45: =AR45+AS45+AT45 -> 0 | AY45: =AV45+AW45+AX45 -> 0 | BC45: =AZ45+BA45+BB45 -> 0 | BG45: =BD45+BE45+BF45 -> 0 | BK45: =BH45+BI45+BJ45 -> 0 | BO45: =BL45+BM45+BN45 -> 0 | BS45: =BP45+BQ45+BR45 -> 0 | BW45: =BT45+BU45+BV45 -> 0 | CA45: =BX45+BY45+BZ45 -> 0 | CE45: =CB45+CC45+CD45 -> 0 | CI45: =CF45+CG45+CH45 -> 0
C46: =Tekstnøgler!C131 -> Andet udledning ved energi og processer | G46: =D46+E46+F46 -> 0 | K46: =H46+I46+J46 -> 0 | O46: =L46+M46+N46 -> 0 | S46: =P46+Q46+R46 -> 0 | W46: =T46+U46+V46 -> 0 | AA46: =X46+Y46+Z46 -> 0 | AE46: =AB46+AC46+AD46 -> 0 | AI46: =AF46+AG46+AH46 -> 0 | AM46: =AJ46+AK46+AL46 -> 0 | AQ46: =AN46+AO46+AP46 -> 0 | AU46: =AR46+AS46+AT46 -> 0 | AY46: =AV46+AW46+AX46 -> 0 | BC46: =AZ46+BA46+BB46 -> 0 | BG46: =BD46+BE46+BF46 -> 0 | BK46: =BH46+BI46+BJ46 -> 0 | BO46: =BL46+BM46+BN46 -> 0 | BS46: =BP46+BQ46+BR46 -> 0 | BW46: =BT46+BU46+BV46 -> 0 | CA46: =BX46+BY46+BZ46 -> 0 | CE46: =CB46+CC46+CD46 -> 0 | CI46: =CF46+CG46+CH46 -> 0
C47: =Tekstnøgler!C132 -> Indkøb | D47: =D48+D62 -> 0 | E47: =E48+E62 -> 0 | F47: =F48+F62 -> 0 | G47: =G48+G62 -> 0 | H47: =H48+H62 -> 0 | I47: =I48+I62 -> 0 | J47: =J48+J62 -> 0 | K47: =K48+K62 -> 0 | ... CI47: =CI48+CI62 -> 0
C48: =Tekstnøgler!C133 -> Primære indkøb af råvarer til produktion | D48: =D49+D54+D59 -> 0 | E48: =E49+E54+E59 -> 0 | F48: =F49+F54+F59 -> 0 | G48: =G49+G54+G59 -> 0 | H48: =H49+H54+H59 -> 0 | I48: =I49+I54+I59 -> 0 | J48: =J49+J54+J59 -> 0 | K48: =K49+K54+K59 -> 0 | ... CI48: =CI49+CI54+CI59 -> 0
C49: =Tekstnøgler!C134 -> Materialer (primære indkøb) | D49: =SUM(D50:D53) -> 0 | E49: =SUM(E50:E53) -> 0 | F49: =SUM(F50:F53) -> 0 | G49: =SUM(G50:G53) -> 0 | H49: =SUM(H50:H53) -> 0 | I49: =SUM(I50:I53) -> 0 | J49: =SUM(J50:J53) -> 0 | K49: =SUM(K50:K53) -> 0 | ... CI49: =SUM(CI50:CI53) -> 0
C50: =Tekstnøgler!C135 -> Indkøb af materialer i fysiske enheder | G50: =D50+E50+F50 -> 0 | K50: =H50+I50+J50 -> 0 | O50: =L50+M50+N50 -> 0 | S50: =P50+Q50+R50 -> 0 | W50: =T50+U50+V50 -> 0 | AA50: =X50+Y50+Z50 -> 0 | AE50: =AB50+AC50+AD50 -> 0 | AI50: =AF50+AG50+AH50 -> 0 | AM50: =AJ50+AK50+AL50 -> 0 | AQ50: =AN50+AO50+AP50 -> 0 | AU50: =AR50+AS50+AT50 -> 0 | AY50: =AV50+AW50+AX50 -> 0 | BC50: =AZ50+BA50+BB50 -> 0 | BG50: =BD50+BE50+BF50 -> 0 | BK50: =BH50+BI50+BJ50 -> 0 | BO50: =BL50+BM50+BN50 -> 0 | BS50: =BP50+BQ50+BR50 -> 0 | BW50: =BT50+BU50+BV50 -> 0 | CA50: =BX50+BY50+BZ50 -> 0 | CE50: =CB50+CC50+CD50 -> 0 | CI50: =CF50+CG50+CH50 -> 0
C51: =Tekstnøgler!C136 -> Indkøb af materialer i monetære enheder (beløb i DKK) | G51: =D51+E51+F51 -> 0 | K51: =H51+I51+J51 -> 0 | O51: =L51+M51+N51 -> 0 | S51: =P51+Q51+R51 -> 0 | W51: =T51+U51+V51 -> 0 | Y51: 12 | AA51: =X51+Y51+Z51 -> 12 | AE51: =AB51+AC51+AD51 -> 0 | AI51: =AF51+AG51+AH51 -> 0 | AM51: =AJ51+AK51+AL51 -> 0 | AQ51: =AN51+AO51+AP51 -> 0 | AU51: =AR51+AS51+AT51 -> 0 | AY51: =AV51+AW51+AX51 -> 0 | BC51: =AZ51+BA51+BB51 -> 0 | BG51: =BD51+BE51+BF51 -> 0 | BK51: =BH51+BI51+BJ51 -> 0 | BO51: =BL51+BM51+BN51 -> 0 | BS51: =BP51+BQ51+BR51 -> 0 | BW51: =BT51+BU51+BV51 -> 0 | CA51: =BX51+BY51+BZ51 -> 0 | CE51: =CB51+CC51+CD51 -> 0 | CI51: =CF51+CG51+CH51 -> 0
C52: =Tekstnøgler!C137 -> Fysiske enheder med egne emissionsfaktorer | G52: =D52+E52+F52 -> 0 | K52: =H52+I52+J52 -> 0 | O52: =L52+M52+N52 -> 0 | S52: =P52+Q52+R52 -> 0 | W52: =T52+U52+V52 -> 0 | AA52: =X52+Y52+Z52 -> 0 | AE52: =AB52+AC52+AD52 -> 0 | AI52: =AF52+AG52+AH52 -> 0 | AM52: =AJ52+AK52+AL52 -> 0 | AQ52: =AN52+AO52+AP52 -> 0 | AU52: =AR52+AS52+AT52 -> 0 | AY52: =AV52+AW52+AX52 -> 0 | BC52: =AZ52+BA52+BB52 -> 0 | BF52: 12 | BG52: =BD52+BE52+BF52 -> 12 | BK52: =BH52+BI52+BJ52 -> 0 | BO52: =BL52+BM52+BN52 -> 0 | BS52: =BP52+BQ52+BR52 -> 0 | BW52: =BT52+BU52+BV52 -> 0 | CA52: =BX52+BY52+BZ52 -> 0 | CE52: =CB52+CC52+CD52 -> 0 | CI52: =CF52+CG52+CH52 -> 0
C53: =Tekstnøgler!C138 -> Monetære enheder (beløb i DKK) med egne emissionsfaktorer | G53: =D53+E53+F53 -> 0 | K53: =H53+I53+J53 -> 0 | O53: =L53+M53+N53 -> 0 | S53: =P53+Q53+R53 -> 0 | W53: =T53+U53+V53 -> 0 | AA53: =X53+Y53+Z53 -> 0 | AE53: =AB53+AC53+AD53 -> 0 | AI53: =AF53+AG53+AH53 -> 0 | AM53: =AJ53+AK53+AL53 -> 0 | AQ53: =AN53+AO53+AP53 -> 0 | AU53: =AR53+AS53+AT53 -> 0 | AY53: =AV53+AW53+AX53 -> 0 | BC53: =AZ53+BA53+BB53 -> 0 | BG53: =BD53+BE53+BF53 -> 0 | BK53: =BH53+BI53+BJ53 -> 0 | BO53: =BL53+BM53+BN53 -> 0 | BS53: =BP53+BQ53+BR53 -> 0 | BW53: =BT53+BU53+BV53 -> 0 | CA53: =BX53+BY53+BZ53 -> 0 | CE53: =CB53+CC53+CD53 -> 0 | CI53: =CF53+CG53+CH53 -> 0
C54: =Tekstnøgler!C139 -> Produkter og services (primære indkøb) | D54: =SUM(D55:D58) -> 0 | E54: =SUM(E55:E58) -> 0 | F54: =SUM(F55:F58) -> 0 | G54: =SUM(G55:G58) -> 0 | H54: =SUM(H55:H58) -> 0 | I54: =SUM(I55:I58) -> 0 | J54: =SUM(J55:J58) -> 0 | K54: =SUM(K55:K58) -> 0 | ... CI54: =SUM(CI55:CI58) -> 0
C55: =Tekstnøgler!C140 -> Indkøb af produkter i fysiske enheder | G55: =D55+E55+F55 -> 0 | K55: =H55+I55+J55 -> 0 | O55: =L55+M55+N55 -> 0 | S55: =P55+Q55+R55 -> 0 | W55: =T55+U55+V55 -> 0 | AA55: =X55+Y55+Z55 -> 0 | AE55: =AB55+AC55+AD55 -> 0 | AI55: =AF55+AG55+AH55 -> 0 | AM55: =AJ55+AK55+AL55 -> 0 | AQ55: =AN55+AO55+AP55 -> 0 | AU55: =AR55+AS55+AT55 -> 0 | AY55: =AV55+AW55+AX55 -> 0 | BC55: =AZ55+BA55+BB55 -> 0 | BG55: =BD55+BE55+BF55 -> 0 | BK55: =BH55+BI55+BJ55 -> 0 | BO55: =BL55+BM55+BN55 -> 0 | BS55: =BP55+BQ55+BR55 -> 0 | BW55: =BT55+BU55+BV55 -> 0 | CA55: =BX55+BY55+BZ55 -> 0 | CE55: =CB55+CC55+CD55 -> 0 | CI55: =CF55+CG55+CH55 -> 0
C56: =Tekstnøgler!C141 -> Indkøb af produkter i monetære enheder (beløb i DKK) | G56: =D56+E56+F56 -> 0 | K56: =H56+I56+J56 -> 0 | O56: =L56+M56+N56 -> 0 | S56: =P56+Q56+R56 -> 0 | W56: =T56+U56+V56 -> 0 | AA56: =X56+Y56+Z56 -> 0 | AE56: =AB56+AC56+AD56 -> 0 | AI56: =AF56+AG56+AH56 -> 0 | AM56: =AJ56+AK56+AL56 -> 0 | AQ56: =AN56+AO56+AP56 -> 0 | AU56: =AR56+AS56+AT56 -> 0 | AY56: =AV56+AW56+AX56 -> 0 | BC56: =AZ56+BA56+BB56 -> 0 | BG56: =BD56+BE56+BF56 -> 0 | BK56: =BH56+BI56+BJ56 -> 0 | BO56: =BL56+BM56+BN56 -> 0 | BS56: =BP56+BQ56+BR56 -> 0 | BW56: =BT56+BU56+BV56 -> 0 | CA56: =BX56+BY56+BZ56 -> 0 | CE56: =CB56+CC56+CD56 -> 0 | CI56: =CF56+CG56+CH56 -> 0
C57: =Tekstnøgler!C142 -> Fysiske enheder med egne emissionsfaktorer | G57: =D57+E57+F57 -> 0 | K57: =H57+I57+J57 -> 0 | O57: =L57+M57+N57 -> 0 | S57: =P57+Q57+R57 -> 0 | W57: =T57+U57+V57 -> 0 | AA57: =X57+Y57+Z57 -> 0 | AE57: =AB57+AC57+AD57 -> 0 | AI57: =AF57+AG57+AH57 -> 0 | AM57: =AJ57+AK57+AL57 -> 0 | AQ57: =AN57+AO57+AP57 -> 0 | AU57: =AR57+AS57+AT57 -> 0 | AY57: =AV57+AW57+AX57 -> 0 | BC57: =AZ57+BA57+BB57 -> 0 | BG57: =BD57+BE57+BF57 -> 0 | BK57: =BH57+BI57+BJ57 -> 0 | BO57: =BL57+BM57+BN57 -> 0 | BS57: =BP57+BQ57+BR57 -> 0 | BW57: =BT57+BU57+BV57 -> 0 | CA57: =BX57+BY57+BZ57 -> 0 | CE57: =CB57+CC57+CD57 -> 0 | CI57: =CF57+CG57+CH57 -> 0
C58: =Tekstnøgler!C143 -> Monetære enheder (beløb i DKK) med egne emissionsfaktorer | G58: =D58+E58+F58 -> 0 | K58: =H58+I58+J58 -> 0 | O58: =L58+M58+N58 -> 0 | S58: =P58+Q58+R58 -> 0 | W58: =T58+U58+V58 -> 0 | AA58: =X58+Y58+Z58 -> 0 | AE58: =AB58+AC58+AD58 -> 0 | AI58: =AF58+AG58+AH58 -> 0 | AM58: =AJ58+AK58+AL58 -> 0 | AQ58: =AN58+AO58+AP58 -> 0 | AU58: =AR58+AS58+AT58 -> 0 | AY58: =AV58+AW58+AX58 -> 0 | BC58: =AZ58+BA58+BB58 -> 0 | BG58: =BD58+BE58+BF58 -> 0 | BK58: =BH58+BI58+BJ58 -> 0 | BO58: =BL58+BM58+BN58 -> 0 | BS58: =BP58+BQ58+BR58 -> 0 | BW58: =BT58+BU58+BV58 -> 0 | CA58: =BX58+BY58+BZ58 -> 0 | CE58: =CB58+CC58+CD58 -> 0 | CI58: =CF58+CG58+CH58 -> 0
C59: =Tekstnøgler!C144 -> Andet udledning ved primære indkøb | D59: =SUM(D60:D61) -> 0 | E59: =SUM(E60:E61) -> 0 | F59: =SUM(F60:F61) -> 0 | G59: =SUM(G60:G61) -> 0 | H59: =SUM(H60:H61) -> 0 | I59: =SUM(I60:I61) -> 0 | J59: =SUM(J60:J61) -> 0 | K59: =SUM(K60:K61) -> 0 | ... CI59: =SUM(CI60:CI61) -> 0
C60: =Tekstnøgler!C145 -> Fysiske enheder med egne emissionsfaktorer | G60: =D60+E60+F60 -> 0 | K60: =H60+I60+J60 -> 0 | O60: =L60+M60+N60 -> 0 | S60: =P60+Q60+R60 -> 0 | W60: =T60+U60+V60 -> 0 | AA60: =X60+Y60+Z60 -> 0 | AE60: =AB60+AC60+AD60 -> 0 | AI60: =AF60+AG60+AH60 -> 0 | AM60: =AJ60+AK60+AL60 -> 0 | AQ60: =AN60+AO60+AP60 -> 0 | AU60: =AR60+AS60+AT60 -> 0 | AY60: =AV60+AW60+AX60 -> 0 | BC60: =AZ60+BA60+BB60 -> 0 | BG60: =BD60+BE60+BF60 -> 0 | BK60: =BH60+BI60+BJ60 -> 0 | BO60: =BL60+BM60+BN60 -> 0 | BS60: =BP60+BQ60+BR60 -> 0 | BW60: =BT60+BU60+BV60 -> 0 | CA60: =BX60+BY60+BZ60 -> 0 | CE60: =CB60+CC60+CD60 -> 0 | CI60: =CF60+CG60+CH60 -> 0
C61: =Tekstnøgler!C146 -> Monetære enheder (beløb i DKK) med egne emissionsfaktorer | G61: =D61+E61+F61 -> 0 | K61: =H61+I61+J61 -> 0 | O61: =L61+M61+N61 -> 0 | S61: =P61+Q61+R61 -> 0 | W61: =T61+U61+V61 -> 0 | AA61: =X61+Y61+Z61 -> 0 | AE61: =AB61+AC61+AD61 -> 0 | AI61: =AF61+AG61+AH61 -> 0 | AM61: =AJ61+AK61+AL61 -> 0 | AQ61: =AN61+AO61+AP61 -> 0 | AU61: =AR61+AS61+AT61 -> 0 | AY61: =AV61+AW61+AX61 -> 0 | BC61: =AZ61+BA61+BB61 -> 0 | BG61: =BD61+BE61+BF61 -> 0 | BK61: =BH61+BI61+BJ61 -> 0 | BO61: =BL61+BM61+BN61 -> 0 | BS61: =BP61+BQ61+BR61 -> 0 | BW61: =BT61+BU61+BV61 -> 0 | CA61: =BX61+BY61+BZ61 -> 0 | CE61: =CB61+CC61+CD61 -> 0 | CI61: =CF61+CG61+CH61 -> 0
C62: =Tekstnøgler!C147 -> Sekundære indkøb af hjælpematerialer og serviceydelser | D62: =D63+D68+D73 -> 0 | E62: =E63+E68+E73 -> 0 | F62: =F63+F68+F73 -> 0 | G62: =G63+G68+G73 -> 0 | H62: =H63+H68+H73 -> 0 | I62: =I63+I68+I73 -> 0 | J62: =J63+J68+J73 -> 0 | K62: =K63+K68+K73 -> 0 | ... CI62: =CI63+CI68+CI73 -> 0
C63: =Tekstnøgler!C148 -> Materialer (sekundære indkøb) | D63: =SUM(D64:D67) -> 0 | E63: =SUM(E64:E67) -> 0 | F63: =SUM(F64:F67) -> 0 | G63: =SUM(G64:G67) -> 0 | H63: =SUM(H64:H67) -> 0 | I63: =SUM(I64:I67) -> 0 | J63: =SUM(J64:J67) -> 0 | K63: =SUM(K64:K67) -> 0 | ... CI63: =SUM(CI64:CI67) -> 0
C64: =Tekstnøgler!C149 -> Indkøb af materialer i fysiske enheder | G64: =D64+E64+F64 -> 0 | K64: =H64+I64+J64 -> 0 | O64: =L64+M64+N64 -> 0 | S64: =P64+Q64+R64 -> 0 | W64: =T64+U64+V64 -> 0 | AA64: =X64+Y64+Z64 -> 0 | AE64: =AB64+AC64+AD64 -> 0 | AI64: =AF64+AG64+AH64 -> 0 | AM64: =AJ64+AK64+AL64 -> 0 | AQ64: =AN64+AO64+AP64 -> 0 | AU64: =AR64+AS64+AT64 -> 0 | AY64: =AV64+AW64+AX64 -> 0 | BC64: =AZ64+BA64+BB64 -> 0 | BG64: =BD64+BE64+BF64 -> 0 | BK64: =BH64+BI64+BJ64 -> 0 | BO64: =BL64+BM64+BN64 -> 0 | BS64: =BP64+BQ64+BR64 -> 0 | BW64: =BT64+BU64+BV64 -> 0 | CA64: =BX64+BY64+BZ64 -> 0 | CE64: =CB64+CC64+CD64 -> 0 | CI64: =CF64+CG64+CH64 -> 0
C65: =Tekstnøgler!C150 -> Indkøb af materialer i monetære enheder (beløb i DKK) | G65: =D65+E65+F65 -> 0 | K65: =H65+I65+J65 -> 0 | O65: =L65+M65+N65 -> 0 | S65: =P65+Q65+R65 -> 0 | W65: =T65+U65+V65 -> 0 | AA65: =X65+Y65+Z65 -> 0 | AE65: =AB65+AC65+AD65 -> 0 | AI65: =AF65+AG65+AH65 -> 0 | AM65: =AJ65+AK65+AL65 -> 0 | AQ65: =AN65+AO65+AP65 -> 0 | AU65: =AR65+AS65+AT65 -> 0 | AY65: =AV65+AW65+AX65 -> 0 | BC65: =AZ65+BA65+BB65 -> 0 | BG65: =BD65+BE65+BF65 -> 0 | BK65: =BH65+BI65+BJ65 -> 0 | BO65: =BL65+BM65+BN65 -> 0 | BS65: =BP65+BQ65+BR65 -> 0 | BW65: =BT65+BU65+BV65 -> 0 | CA65: =BX65+BY65+BZ65 -> 0 | CE65: =CB65+CC65+CD65 -> 0 | CI65: =CF65+CG65+CH65 -> 0
C66: =Tekstnøgler!C151 -> Fysiske enheder med egne emissionsfaktorer | G66: =D66+E66+F66 -> 0 | K66: =H66+I66+J66 -> 0 | O66: =L66+M66+N66 -> 0 | S66: =P66+Q66+R66 -> 0 | W66: =T66+U66+V66 -> 0 | AA66: =X66+Y66+Z66 -> 0 | AE66: =AB66+AC66+AD66 -> 0 | AI66: =AF66+AG66+AH66 -> 0 | AM66: =AJ66+AK66+AL66 -> 0 | AQ66: =AN66+AO66+AP66 -> 0 | AU66: =AR66+AS66+AT66 -> 0 | AY66: =AV66+AW66+AX66 -> 0 | BC66: =AZ66+BA66+BB66 -> 0 | BG66: =BD66+BE66+BF66 -> 0 | BK66: =BH66+BI66+BJ66 -> 0 | BO66: =BL66+BM66+BN66 -> 0 | BS66: =BP66+BQ66+BR66 -> 0 | BW66: =BT66+BU66+BV66 -> 0 | CA66: =BX66+BY66+BZ66 -> 0 | CE66: =CB66+CC66+CD66 -> 0 | CI66: =CF66+CG66+CH66 -> 0
C67: =Tekstnøgler!C152 -> Monetære enheder (beløb i DKK) med egne emissionsfaktorer | G67: =D67+E67+F67 -> 0 | K67: =H67+I67+J67 -> 0 | O67: =L67+M67+N67 -> 0 | S67: =P67+Q67+R67 -> 0 | W67: =T67+U67+V67 -> 0 | AA67: =X67+Y67+Z67 -> 0 | AE67: =AB67+AC67+AD67 -> 0 | AI67: =AF67+AG67+AH67 -> 0 | AM67: =AJ67+AK67+AL67 -> 0 | AQ67: =AN67+AO67+AP67 -> 0 | AU67: =AR67+AS67+AT67 -> 0 | AY67: =AV67+AW67+AX67 -> 0 | BC67: =AZ67+BA67+BB67 -> 0 | BG67: =BD67+BE67+BF67 -> 0 | BK67: =BH67+BI67+BJ67 -> 0 | BO67: =BL67+BM67+BN67 -> 0 | BS67: =BP67+BQ67+BR67 -> 0 | BW67: =BT67+BU67+BV67 -> 0 | CA67: =BX67+BY67+BZ67 -> 0 | CE67: =CB67+CC67+CD67 -> 0 | CI67: =CF67+CG67+CH67 -> 0
C68: =Tekstnøgler!C153 -> Produkter og services (sekundære indkøb) | D68: =SUM(D69:D72) -> 0 | E68: =SUM(E69:E72) -> 0 | F68: =SUM(F69:F72) -> 0 | G68: =SUM(G69:G72) -> 0 | H68: =SUM(H69:H72) -> 0 | I68: =SUM(I69:I72) -> 0 | J68: =SUM(J69:J72) -> 0 | K68: =SUM(K69:K72) -> 0 | ... CI68: =SUM(CI69:CI72) -> 0
C69: =Tekstnøgler!C154 -> Indkøb af produkter i fysiske enheder | G69: =D69+E69+F69 -> 0 | K69: =H69+I69+J69 -> 0 | O69: =L69+M69+N69 -> 0 | S69: =P69+Q69+R69 -> 0 | W69: =T69+U69+V69 -> 0 | AA69: =X69+Y69+Z69 -> 0 | AE69: =AB69+AC69+AD69 -> 0 | AI69: =AF69+AG69+AH69 -> 0 | AM69: =AJ69+AK69+AL69 -> 0 | AQ69: =AN69+AO69+AP69 -> 0 | AU69: =AR69+AS69+AT69 -> 0 | AY69: =AV69+AW69+AX69 -> 0 | BC69: =AZ69+BA69+BB69 -> 0 | BG69: =BD69+BE69+BF69 -> 0 | BK69: =BH69+BI69+BJ69 -> 0 | BO69: =BL69+BM69+BN69 -> 0 | BS69: =BP69+BQ69+BR69 -> 0 | BW69: =BT69+BU69+BV69 -> 0 | CA69: =BX69+BY69+BZ69 -> 0 | CE69: =CB69+CC69+CD69 -> 0 | CI69: =CF69+CG69+CH69 -> 0
C70: =Tekstnøgler!C155 -> Indkøb af produkter i monetære enheder (beløb i DKK) | G70: =D70+E70+F70 -> 0 | K70: =H70+I70+J70 -> 0 | O70: =L70+M70+N70 -> 0 | S70: =P70+Q70+R70 -> 0 | W70: =T70+U70+V70 -> 0 | AA70: =X70+Y70+Z70 -> 0 | AE70: =AB70+AC70+AD70 -> 0 | AI70: =AF70+AG70+AH70 -> 0 | AM70: =AJ70+AK70+AL70 -> 0 | AQ70: =AN70+AO70+AP70 -> 0 | AU70: =AR70+AS70+AT70 -> 0 | AY70: =AV70+AW70+AX70 -> 0 | BC70: =AZ70+BA70+BB70 -> 0 | BG70: =BD70+BE70+BF70 -> 0 | BK70: =BH70+BI70+BJ70 -> 0 | BO70: =BL70+BM70+BN70 -> 0 | BS70: =BP70+BQ70+BR70 -> 0 | BW70: =BT70+BU70+BV70 -> 0 | CA70: =BX70+BY70+BZ70 -> 0 | CE70: =CB70+CC70+CD70 -> 0 | CI70: =CF70+CG70+CH70 -> 0
C71: =Tekstnøgler!C156 -> Fysiske enheder med egne emissionsfaktorer | G71: =D71+E71+F71 -> 0 | K71: =H71+I71+J71 -> 0 | O71: =L71+M71+N71 -> 0 | S71: =P71+Q71+R71 -> 0 | W71: =T71+U71+V71 -> 0 | AA71: =X71+Y71+Z71 -> 0 | AE71: =AB71+AC71+AD71 -> 0 | AI71: =AF71+AG71+AH71 -> 0 | AM71: =AJ71+AK71+AL71 -> 0 | AQ71: =AN71+AO71+AP71 -> 0 | AU71: =AR71+AS71+AT71 -> 0 | AY71: =AV71+AW71+AX71 -> 0 | BC71: =AZ71+BA71+BB71 -> 0 | BG71: =BD71+BE71+BF71 -> 0 | BK71: =BH71+BI71+BJ71 -> 0 | BO71: =BL71+BM71+BN71 -> 0 | BS71: =BP71+BQ71+BR71 -> 0 | BW71: =BT71+BU71+BV71 -> 0 | CA71: =BX71+BY71+BZ71 -> 0 | CE71: =CB71+CC71+CD71 -> 0 | CI71: =CF71+CG71+CH71 -> 0
C72: =Tekstnøgler!C157 -> Monetære enheder (beløb i DKK) med egne emissionsfaktorer | G72: =D72+E72+F72 -> 0 | K72: =H72+I72+J72 -> 0 | O72: =L72+M72+N72 -> 0 | S72: =P72+Q72+R72 -> 0 | W72: =T72+U72+V72 -> 0 | AA72: =X72+Y72+Z72 -> 0 | AE72: =AB72+AC72+AD72 -> 0 | AI72: =AF72+AG72+AH72 -> 0 | AM72: =AJ72+AK72+AL72 -> 0 | AQ72: =AN72+AO72+AP72 -> 0 | AU72: =AR72+AS72+AT72 -> 0 | AY72: =AV72+AW72+AX72 -> 0 | BC72: =AZ72+BA72+BB72 -> 0 | BG72: =BD72+BE72+BF72 -> 0 | BK72: =BH72+BI72+BJ72 -> 0 | BO72: =BL72+BM72+BN72 -> 0 | BS72: =BP72+BQ72+BR72 -> 0 | BW72: =BT72+BU72+BV72 -> 0 | CA72: =BX72+BY72+BZ72 -> 0 | CE72: =CB72+CC72+CD72 -> 0 | CI72: =CF72+CG72+CH72 -> 0
C73: =Tekstnøgler!C158 -> Andet udledning ved sekundære indkøb | D73: =SUM(D74:D75) -> 0 | E73: =SUM(E74:E75) -> 0 | F73: =SUM(F74:F75) -> 0 | G73: =SUM(G74:G75) -> 0 | H73: =SUM(H74:H75) -> 0 | I73: =SUM(I74:I75) -> 0 | J73: =SUM(J74:J75) -> 0 | K73: =SUM(K74:K75) -> 0 | ... CI73: =SUM(CI74:CI75) -> 0
C74: =Tekstnøgler!C159 -> Fysiske enheder med egne emissionsfaktorer | G74: =D74+E74+F74 -> 0 | K74: =H74+I74+J74 -> 0 | O74: =L74+M74+N74 -> 0 | S74: =P74+Q74+R74 -> 0 | W74: =T74+U74+V74 -> 0 | AA74: =X74+Y74+Z74 -> 0 | AE74: =AB74+AC74+AD74 -> 0 | AI74: =AF74+AG74+AH74 -> 0 | AM74: =AJ74+AK74+AL74 -> 0 | AQ74: =AN74+AO74+AP74 -> 0 | AU74: =AR74+AS74+AT74 -> 0 | AY74: =AV74+AW74+AX74 -> 0 | BC74: =AZ74+BA74+BB74 -> 0 | BG74: =BD74+BE74+BF74 -> 0 | BK74: =BH74+BI74+BJ74 -> 0 | BO74: =BL74+BM74+BN74 -> 0 | BS74: =BP74+BQ74+BR74 -> 0 | BW74: =BT74+BU74+BV74 -> 0 | CA74: =BX74+BY74+BZ74 -> 0 | CE74: =CB74+CC74+CD74 -> 0 | CI74: =CF74+CG74+CH74 -> 0
C75: =Tekstnøgler!C160 -> Monetære enheder (beløb i DKK) med egne emissionsfaktorer | G75: =D75+E75+F75 -> 0 | K75: =H75+I75+J75 -> 0 | O75: =L75+M75+N75 -> 0 | S75: =P75+Q75+R75 -> 0 | W75: =T75+U75+V75 -> 0 | AA75: =X75+Y75+Z75 -> 0 | AE75: =AB75+AC75+AD75 -> 0 | AI75: =AF75+AG75+AH75 -> 0 | AM75: =AJ75+AK75+AL75 -> 0 | AQ75: =AN75+AO75+AP75 -> 0 | AU75: =AR75+AS75+AT75 -> 0 | AY75: =AV75+AW75+AX75 -> 0 | BC75: =AZ75+BA75+BB75 -> 0 | BG75: =BD75+BE75+BF75 -> 0 | BK75: =BH75+BI75+BJ75 -> 0 | BO75: =BL75+BM75+BN75 -> 0 | BS75: =BP75+BQ75+BR75 -> 0 | BW75: =BT75+BU75+BV75 -> 0 | CA75: =BX75+BY75+BZ75 -> 0 | CE75: =CB75+CC75+CD75 -> 0 | CI75: =CF75+CG75+CH75 -> 0
C76: =Tekstnøgler!C161 -> Transport | D76: =D77+D81+D86+D90+D94 -> 3 | E76: =E77+E81+E86+E90+E94 -> 3 | F76: =F77+F81+F86+F90+F94 -> 3 | G76: =G77+G81+G86+G90+G94 -> 9 | H76: =H77+H81+H86+H90+H94 -> 3 | I76: =I77+I81+I86+I90+I94 -> 3 | J76: =J77+J81+J86+J90+J94 -> 3 | K76: =K77+K81+K86+K90+K94 -> 9 | ... CI76: =CI77+CI81+CI86+CI90+CI94 -> 9
C77: =Tekstnøgler!C162 -> Egne og leasede transportmidler | D77: =SUM(D78:D80) -> 0 | E77: =SUM(E78:E80) -> 0 | F77: =SUM(F78:F80) -> 0 | G77: =SUM(G78:G80) -> 0 | H77: =SUM(H78:H80) -> 0 | I77: =SUM(I78:I80) -> 0 | J77: =SUM(J78:J80) -> 0 | K77: =SUM(K78:K80) -> 0 | ... CI77: =SUM(CI78:CI80) -> 0
C78: =Tekstnøgler!C163 -> Egne og leasede transportmidler | G78: =D78+E78+F78 -> 0 | K78: =H78+I78+J78 -> 0 | O78: =L78+M78+N78 -> 0 | S78: =P78+Q78+R78 -> 0 | W78: =T78+U78+V78 -> 0 | AA78: =X78+Y78+Z78 -> 0 | AE78: =AB78+AC78+AD78 -> 0 | AI78: =AF78+AG78+AH78 -> 0 | AM78: =AJ78+AK78+AL78 -> 0 | AQ78: =AN78+AO78+AP78 -> 0 | AU78: =AR78+AS78+AT78 -> 0 | AY78: =AV78+AW78+AX78 -> 0 | BC78: =AZ78+BA78+BB78 -> 0 | BG78: =BD78+BE78+BF78 -> 0 | BK78: =BH78+BI78+BJ78 -> 0 | BO78: =BL78+BM78+BN78 -> 0 | BS78: =BP78+BQ78+BR78 -> 0 | BW78: =BT78+BU78+BV78 -> 0 | CA78: =BX78+BY78+BZ78 -> 0 | CE78: =CB78+CC78+CD78 -> 0 | CI78: =CF78+CG78+CH78 -> 0
C79: =Tekstnøgler!C164 -> Fly og Skibe | G79: =D79+E79+F79 -> 0 | K79: =H79+I79+J79 -> 0 | O79: =L79+M79+N79 -> 0 | S79: =P79+Q79+R79 -> 0 | W79: =T79+U79+V79 -> 0 | AA79: =X79+Y79+Z79 -> 0 | AE79: =AB79+AC79+AD79 -> 0 | AI79: =AF79+AG79+AH79 -> 0 | AM79: =AJ79+AK79+AL79 -> 0 | AQ79: =AN79+AO79+AP79 -> 0 | AU79: =AR79+AS79+AT79 -> 0 | AY79: =AV79+AW79+AX79 -> 0 | BC79: =AZ79+BA79+BB79 -> 0 | BG79: =BD79+BE79+BF79 -> 0 | BI79: 13 | BK79: =BH79+BI79+BJ79 -> 13 | BO79: =BL79+BM79+BN79 -> 0 | BS79: =BP79+BQ79+BR79 -> 0 | BW79: =BT79+BU79+BV79 -> 0 | CA79: =BX79+BY79+BZ79 -> 0 | CE79: =CB79+CC79+CD79 -> 0 | CI79: =CF79+CG79+CH79 -> 0
C80: =Tekstnøgler!C165 -> Egne og leasede transportmidler med egne emissionsfaktorer | G80: =D80+E80+F80 -> 0 | K80: =H80+I80+J80 -> 0 | O80: =L80+M80+N80 -> 0 | S80: =P80+Q80+R80 -> 0 | W80: =T80+U80+V80 -> 0 | AA80: =X80+Y80+Z80 -> 0 | AE80: =AB80+AC80+AD80 -> 0 | AI80: =AF80+AG80+AH80 -> 0 | AM80: =AJ80+AK80+AL80 -> 0 | AQ80: =AN80+AO80+AP80 -> 0 | AU80: =AR80+AS80+AT80 -> 0 | AY80: =AV80+AW80+AX80 -> 0 | BC80: =AZ80+BA80+BB80 -> 0 | BG80: =BD80+BE80+BF80 -> 0 | BK80: =BH80+BI80+BJ80 -> 0 | BO80: =BL80+BM80+BN80 -> 0 | BS80: =BP80+BQ80+BR80 -> 0 | BW80: =BT80+BU80+BV80 -> 0 | CA80: =BX80+BY80+BZ80 -> 0 | CE80: =CB80+CC80+CD80 -> 0 | CI80: =CF80+CG80+CH80 -> 0
C81: =Tekstnøgler!C166 -> Medarbejdertransport | D81: =SUM(D82:D85) -> 3 | E81: =SUM(E82:E85) -> 3 | F81: =SUM(F82:F85) -> 3 | G81: =SUM(G82:G85) -> 9 | H81: =SUM(H82:H85) -> 3 | I81: =SUM(I82:I85) -> 3 | J81: =SUM(J82:J85) -> 3 | K81: =SUM(K82:K85) -> 9 | ... CI81: =SUM(CI82:CI85) -> 9
C82: =Tekstnøgler!C167 -> Pendling | G82: =D82+E82+F82 -> 0 | K82: =H82+I82+J82 -> 0 | O82: =L82+M82+N82 -> 0 | S82: =P82+Q82+R82 -> 0 | W82: =T82+U82+V82 -> 0 | AA82: =X82+Y82+Z82 -> 0 | AE82: =AB82+AC82+AD82 -> 0 | AI82: =AF82+AG82+AH82 -> 0 | AM82: =AJ82+AK82+AL82 -> 0 | AQ82: =AN82+AO82+AP82 -> 0 | AU82: =AR82+AS82+AT82 -> 0 | AY82: =AV82+AW82+AX82 -> 0 | BC82: =AZ82+BA82+BB82 -> 0 | BG82: =BD82+BE82+BF82 -> 0 | BK82: =BH82+BI82+BJ82 -> 0 | BO82: =BL82+BM82+BN82 -> 0 | BS82: =BP82+BQ82+BR82 -> 0 | BW82: =BT82+BU82+BV82 -> 0 | CA82: =BX82+BY82+BZ82 -> 0 | CE82: =CB82+CC82+CD82 -> 0 | CI82: =CF82+CG82+CH82 -> 0
C83: =Tekstnøgler!C168 -> Rejser i forbindelse med arbejder - Fysiske enheder | G83: =D83+E83+F83 -> 0 | K83: =H83+I83+J83 -> 0 | O83: =L83+M83+N83 -> 0 | S83: =P83+Q83+R83 -> 0 | W83: =T83+U83+V83 -> 0 | AA83: =X83+Y83+Z83 -> 0 | AE83: =AB83+AC83+AD83 -> 0 | AI83: =AF83+AG83+AH83 -> 0 | AM83: =AJ83+AK83+AL83 -> 0 | AQ83: =AN83+AO83+AP83 -> 0 | AU83: =AR83+AS83+AT83 -> 0 | AY83: =AV83+AW83+AX83 -> 0 | BC83: =AZ83+BA83+BB83 -> 0 | BG83: =BD83+BE83+BF83 -> 0 | BK83: =BH83+BI83+BJ83 -> 0 | BO83: =BL83+BM83+BN83 -> 0 | BS83: =BP83+BQ83+BR83 -> 0 | BW83: =BT83+BU83+BV83 -> 0 | CA83: =BX83+BY83+BZ83 -> 0 | CE83: =CB83+CC83+CD83 -> 0 | CI83: =CF83+CG83+CH83 -> 0
C84: =Tekstnøgler!C169 -> Rejser i forbindelse med arbejder - Monetære enheder (beløb i DKK) | G84: =D84+E84+F84 -> 0 | K84: =H84+I84+J84 -> 0 | O84: =L84+M84+N84 -> 0 | S84: =P84+Q84+R84 -> 0 | W84: =T84+U84+V84 -> 0 | AA84: =X84+Y84+Z84 -> 0 | AE84: =AB84+AC84+AD84 -> 0 | AI84: =AF84+AG84+AH84 -> 0 | AM84: =AJ84+AK84+AL84 -> 0 | AQ84: =AN84+AO84+AP84 -> 0 | AU84: =AR84+AS84+AT84 -> 0 | AY84: =AV84+AW84+AX84 -> 0 | BC84: =AZ84+BA84+BB84 -> 0 | BG84: =BD84+BE84+BF84 -> 0 | BK84: =BH84+BI84+BJ84 -> 0 | BO84: =BL84+BM84+BN84 -> 0 | BS84: =BP84+BQ84+BR84 -> 0 | BW84: =BT84+BU84+BV84 -> 0 | CA84: =BX84+BY84+BZ84 -> 0 | CE84: =CB84+CC84+CD84 -> 0 | CI84: =CF84+CG84+CH84 -> 0
C85: =Tekstnøgler!C170 -> Medarbejdertransport med egne emissionsfaktorer | D85: 3 | E85: 3 | F85: 3 | G85: =D85+E85+F85 -> 9 | H85: 3 | I85: 3 | J85: 3 | K85: =H85+I85+J85 -> 9 | L85: 3 | M85: 3 | N85: 3 | O85: =L85+M85+N85 -> 9 | P85: 3 | Q85: 3 | R85: 3 | S85: =P85+Q85+R85 -> 9 | T85: 3 | U85: 3 | V85: 3 | W85: =T85+U85+V85 -> 9 | X85: 3 | Y85: 3 | Z85: 3 | AA85: =X85+Y85+Z85 -> 9 | AB85: 3 | AC85: 3 | AD85: 3 | AE85: =AB85+AC85+AD85 -> 9 | AF85: 3 | AG85: 3 | AH85: 3 | AI85: =AF85+AG85+AH85 -> 9 | AJ85: 3 | AK85: 3 | AL85: 3 | AM85: =AJ85+AK85+AL85 -> 9 | AN85: 3 | AO85: 3 | AP85: 3 | AQ85: =AN85+AO85+AP85 -> 9 | AR85: 3 | AS85: 3 | AT85: 3 | AU85: =AR85+AS85+AT85 -> 9 | AV85: 3 | AW85: 3 | AX85: 3 | AY85: =AV85+AW85+AX85 -> 9 | AZ85: 3 | BA85: 3 | BB85: 3 | BC85: =AZ85+BA85+BB85 -> 9 | BD85: 3 | BE85: 3 | BF85: 3 | BG85: =BD85+BE85+BF85 -> 9 | BH85: 3 | BI85: 3 | BJ85: 3 | BK85: =BH85+BI85+BJ85 -> 9 | BL85: 3 | BM85: 3 | BN85: 3 | BO85: =BL85+BM85+BN85 -> 9 | BP85: 3 | BQ85: 3 | BR85: 3 | BS85: =BP85+BQ85+BR85 -> 9 | BT85: 3 | BU85: 3 | BV85: 3 | BW85: =BT85+BU85+BV85 -> 9 | BX85: 3 | BY85: 3 | BZ85: 3 | CA85: =BX85+BY85+BZ85 -> 9 | CB85: 3 | CC85: 3 | CD85: 3 | CE85: =CB85+CC85+CD85 -> 9 | CF85: 3 | CG85: 3 | CH85: 3 | CI85: =CF85+CG85+CH85 -> 9
C86: =Tekstnøgler!C171 -> Varetransport til virksomhed | D86: =SUM(D87:D89) -> 0 | E86: =SUM(E87:E89) -> 0 | F86: =SUM(F87:F89) -> 0 | G86: =SUM(G87:G89) -> 0 | H86: =SUM(H87:H89) -> 0 | I86: =SUM(I87:I89) -> 0 | J86: =SUM(J87:J89) -> 0 | K86: =SUM(K87:K89) -> 0 | ... CI86: =SUM(CI87:CI89) -> 0
C87: =Tekstnøgler!C172 -> Varetransport i fysiske enheder | G87: =D87+E87+F87 -> 0 | K87: =H87+I87+J87 -> 0 | O87: =L87+M87+N87 -> 0 | S87: =P87+Q87+R87 -> 0 | W87: =T87+U87+V87 -> 0 | AA87: =X87+Y87+Z87 -> 0 | AE87: =AB87+AC87+AD87 -> 0 | AI87: =AF87+AG87+AH87 -> 0 | AM87: =AJ87+AK87+AL87 -> 0 | AQ87: =AN87+AO87+AP87 -> 0 | AU87: =AR87+AS87+AT87 -> 0 | AY87: =AV87+AW87+AX87 -> 0 | BC87: =AZ87+BA87+BB87 -> 0 | BG87: =BD87+BE87+BF87 -> 0 | BK87: =BH87+BI87+BJ87 -> 0 | BO87: =BL87+BM87+BN87 -> 0 | BS87: =BP87+BQ87+BR87 -> 0 | BW87: =BT87+BU87+BV87 -> 0 | CA87: =BX87+BY87+BZ87 -> 0 | CE87: =CB87+CC87+CD87 -> 0 | CI87: =CF87+CG87+CH87 -> 0
C88: =Tekstnøgler!C173 -> Varetransport i monetære enheder (beløb i DKK) | G88: =D88+E88+F88 -> 0 | K88: =H88+I88+J88 -> 0 | O88: =L88+M88+N88 -> 0 | S88: =P88+Q88+R88 -> 0 | W88: =T88+U88+V88 -> 0 | AA88: =X88+Y88+Z88 -> 0 | AE88: =AB88+AC88+AD88 -> 0 | AI88: =AF88+AG88+AH88 -> 0 | AM88: =AJ88+AK88+AL88 -> 0 | AQ88: =AN88+AO88+AP88 -> 0 | AU88: =AR88+AS88+AT88 -> 0 | AY88: =AV88+AW88+AX88 -> 0 | BC88: =AZ88+BA88+BB88 -> 0 | BG88: =BD88+BE88+BF88 -> 0 | BK88: =BH88+BI88+BJ88 -> 0 | BO88: =BL88+BM88+BN88 -> 0 | BS88: =BP88+BQ88+BR88 -> 0 | BW88: =BT88+BU88+BV88 -> 0 | CA88: =BX88+BY88+BZ88 -> 0 | CE88: =CB88+CC88+CD88 -> 0 | CI88: =CF88+CG88+CH88 -> 0
C89: =Tekstnøgler!C174 -> Varetransport til virksomhed med egne emissionsfaktorer | G89: =D89+E89+F89 -> 0 | K89: =H89+I89+J89 -> 0 | O89: =L89+M89+N89 -> 0 | S89: =P89+Q89+R89 -> 0 | W89: =T89+U89+V89 -> 0 | AA89: =X89+Y89+Z89 -> 0 | AE89: =AB89+AC89+AD89 -> 0 | AI89: =AF89+AG89+AH89 -> 0 | AM89: =AJ89+AK89+AL89 -> 0 | AQ89: =AN89+AO89+AP89 -> 0 | AU89: =AR89+AS89+AT89 -> 0 | AY89: =AV89+AW89+AX89 -> 0 | BC89: =AZ89+BA89+BB89 -> 0 | BG89: =BD89+BE89+BF89 -> 0 | BK89: =BH89+BI89+BJ89 -> 0 | BO89: =BL89+BM89+BN89 -> 0 | BS89: =BP89+BQ89+BR89 -> 0 | BW89: =BT89+BU89+BV89 -> 0 | CA89: =BX89+BY89+BZ89 -> 0 | CE89: =CB89+CC89+CD89 -> 0 | CI89: =CF89+CG89+CH89 -> 0
C90: =Tekstnøgler!C175 -> Varetransport fra virksomhed til kunde | D90: =SUM(D91:D93) -> 0 | E90: =SUM(E91:E93) -> 0 | F90: =SUM(F91:F93) -> 0 | G90: =SUM(G91:G93) -> 0 | H90: =SUM(H91:H93) -> 0 | I90: =SUM(I91:I93) -> 0 | J90: =SUM(J91:J93) -> 0 | K90: =SUM(K91:K93) -> 0 | ... CI90: =SUM(CI91:CI93) -> 0
C91: =Tekstnøgler!C176 -> Varetransport i fysiske enheder | G91: =D91+E91+F91 -> 0 | K91: =H91+I91+J91 -> 0 | O91: =L91+M91+N91 -> 0 | S91: =P91+Q91+R91 -> 0 | W91: =T91+U91+V91 -> 0 | AA91: =X91+Y91+Z91 -> 0 | AE91: =AB91+AC91+AD91 -> 0 | AI91: =AF91+AG91+AH91 -> 0 | AM91: =AJ91+AK91+AL91 -> 0 | AQ91: =AN91+AO91+AP91 -> 0 | AU91: =AR91+AS91+AT91 -> 0 | AY91: =AV91+AW91+AX91 -> 0 | BC91: =AZ91+BA91+BB91 -> 0 | BG91: =BD91+BE91+BF91 -> 0 | BK91: =BH91+BI91+BJ91 -> 0 | BO91: =BL91+BM91+BN91 -> 0 | BS91: =BP91+BQ91+BR91 -> 0 | BW91: =BT91+BU91+BV91 -> 0 | CA91: =BX91+BY91+BZ91 -> 0 | CE91: =CB91+CC91+CD91 -> 0 | CI91: =CF91+CG91+CH91 -> 0
C92: =Tekstnøgler!C177 -> Varetransport i monetære enheder (beløb i DKK) | G92: =D92+E92+F92 -> 0 | K92: =H92+I92+J92 -> 0 | O92: =L92+M92+N92 -> 0 | S92: =P92+Q92+R92 -> 0 | W92: =T92+U92+V92 -> 0 | AA92: =X92+Y92+Z92 -> 0 | AE92: =AB92+AC92+AD92 -> 0 | AI92: =AF92+AG92+AH92 -> 0 | AM92: =AJ92+AK92+AL92 -> 0 | AQ92: =AN92+AO92+AP92 -> 0 | AU92: =AR92+AS92+AT92 -> 0 | AY92: =AV92+AW92+AX92 -> 0 | BC92: =AZ92+BA92+BB92 -> 0 | BG92: =BD92+BE92+BF92 -> 0 | BK92: =BH92+BI92+BJ92 -> 0 | BO92: =BL92+BM92+BN92 -> 0 | BS92: =BP92+BQ92+BR92 -> 0 | BW92: =BT92+BU92+BV92 -> 0 | CA92: =BX92+BY92+BZ92 -> 0 | CE92: =CB92+CC92+CD92 -> 0 | CI92: =CF92+CG92+CH92 -> 0
C93: =Tekstnøgler!C178 -> Varetransport fra virksomhed til kunde med egne emissionsfaktorer | G93: =D93+E93+F93 -> 0 | K93: =H93+I93+J93 -> 0 | O93: =L93+M93+N93 -> 0 | S93: =P93+Q93+R93 -> 0 | W93: =T93+U93+V93 -> 0 | AA93: =X93+Y93+Z93 -> 0 | AE93: =AB93+AC93+AD93 -> 0 | AI93: =AF93+AG93+AH93 -> 0 | AM93: =AJ93+AK93+AL93 -> 0 | AQ93: =AN93+AO93+AP93 -> 0 | AU93: =AR93+AS93+AT93 -> 0 | AY93: =AV93+AW93+AX93 -> 0 | BC93: =AZ93+BA93+BB93 -> 0 | BG93: =BD93+BE93+BF93 -> 0 | BK93: =BH93+BI93+BJ93 -> 0 | BO93: =BL93+BM93+BN93 -> 0 | BS93: =BP93+BQ93+BR93 -> 0 | BW93: =BT93+BU93+BV93 -> 0 | CA93: =BX93+BY93+BZ93 -> 0 | CE93: =CB93+CC93+CD93 -> 0 | CI93: =CF93+CG93+CH93 -> 0
C94: =Tekstnøgler!C179 -> Andet udledning ved transport | G94: =D94+E94+F94 -> 0 | K94: =H94+I94+J94 -> 0 | O94: =L94+M94+N94 -> 0 | S94: =P94+Q94+R94 -> 0 | W94: =T94+U94+V94 -> 0 | AA94: =X94+Y94+Z94 -> 0 | AE94: =AB94+AC94+AD94 -> 0 | AI94: =AF94+AG94+AH94 -> 0 | AM94: =AJ94+AK94+AL94 -> 0 | AQ94: =AN94+AO94+AP94 -> 0 | AU94: =AR94+AS94+AT94 -> 0 | AY94: =AV94+AW94+AX94 -> 0 | BC94: =AZ94+BA94+BB94 -> 0 | BG94: =BD94+BE94+BF94 -> 0 | BK94: =BH94+BI94+BJ94 -> 0 | BO94: =BL94+BM94+BN94 -> 0 | BS94: =BP94+BQ94+BR94 -> 0 | BW94: =BT94+BU94+BV94 -> 0 | CA94: =BX94+BY94+BZ94 -> 0 | CE94: =CB94+CC94+CD94 -> 0 | CI94: =CF94+CG94+CH94 -> 0
C95: =Tekstnøgler!C180 -> Affald og genbrug | D95: =D96+D99 -> 0 | E95: =E96+E99 -> 0 | F95: =F96+F99 -> 0 | G95: =G96+G99 -> 0 | H95: =H96+H99 -> 0 | I95: =I96+I99 -> 0 | J95: =J96+J99 -> 0 | K95: =K96+K99 -> 0 | ... CI95: =CI96+CI99 -> 0
C96: =Tekstnøgler!C181 -> Affald | D96: =SUM(D97:D98) -> 0 | E96: =SUM(E97:E98) -> 0 | F96: =SUM(F97:F98) -> 0 | G96: =SUM(G97:G98) -> 0 | H96: =SUM(H97:H98) -> 0 | I96: =SUM(I97:I98) -> 0 | J96: =SUM(J97:J98) -> 0 | K96: =SUM(K97:K98) -> 0 | ... CI96: =SUM(CI97:CI98) -> 0
C97: =Tekstnøgler!C182 -> Affald | G97: =D97+E97+F97 -> 0 | K97: =H97+I97+J97 -> 0 | O97: =L97+M97+N97 -> 0 | S97: =P97+Q97+R97 -> 0 | W97: =T97+U97+V97 -> 0 | AA97: =X97+Y97+Z97 -> 0 | AE97: =AB97+AC97+AD97 -> 0 | AI97: =AF97+AG97+AH97 -> 0 | AM97: =AJ97+AK97+AL97 -> 0 | AQ97: =AN97+AO97+AP97 -> 0 | AU97: =AR97+AS97+AT97 -> 0 | AY97: =AV97+AW97+AX97 -> 0 | BC97: =AZ97+BA97+BB97 -> 0 | BG97: =BD97+BE97+BF97 -> 0 | BK97: =BH97+BI97+BJ97 -> 0 | BO97: =BL97+BM97+BN97 -> 0 | BS97: =BP97+BQ97+BR97 -> 0 | BW97: =BT97+BU97+BV97 -> 0 | CA97: =BX97+BY97+BZ97 -> 0 | CE97: =CB97+CC97+CD97 -> 0 | CI97: =CF97+CG97+CH97 -> 0
C98: =Tekstnøgler!C183 -> Affald med egne emissionsfaktorer | G98: =D98+E98+F98 -> 0 | K98: =H98+I98+J98 -> 0 | O98: =L98+M98+N98 -> 0 | S98: =P98+Q98+R98 -> 0 | W98: =T98+U98+V98 -> 0 | AA98: =X98+Y98+Z98 -> 0 | AE98: =AB98+AC98+AD98 -> 0 | AI98: =AF98+AG98+AH98 -> 0 | AM98: =AJ98+AK98+AL98 -> 0 | AQ98: =AN98+AO98+AP98 -> 0 | AU98: =AR98+AS98+AT98 -> 0 | AY98: =AV98+AW98+AX98 -> 0 | BC98: =AZ98+BA98+BB98 -> 0 | BG98: =BD98+BE98+BF98 -> 0 | BK98: =BH98+BI98+BJ98 -> 0 | BO98: =BL98+BM98+BN98 -> 0 | BS98: =BP98+BQ98+BR98 -> 0 | BW98: =BT98+BU98+BV98 -> 0 | CA98: =BX98+BY98+BZ98 -> 0 | CE98: =CB98+CC98+CD98 -> 0 | CI98: =CF98+CG98+CH98 -> 0
C99: =Tekstnøgler!C184 -> Andet udledning ved affald | G99: =D99+E99+F99 -> 0 | K99: =H99+I99+J99 -> 0 | O99: =L99+M99+N99 -> 0 | S99: =P99+Q99+R99 -> 0 | W99: =T99+U99+V99 -> 0 | AA99: =X99+Y99+Z99 -> 0 | AE99: =AB99+AC99+AD99 -> 0 | AI99: =AF99+AG99+AH99 -> 0 | AM99: =AJ99+AK99+AL99 -> 0 | AQ99: =AN99+AO99+AP99 -> 0 | AU99: =AR99+AS99+AT99 -> 0 | AY99: =AV99+AW99+AX99 -> 0 | BC99: =AZ99+BA99+BB99 -> 0 | BG99: =BD99+BE99+BF99 -> 0 | BK99: =BH99+BI99+BJ99 -> 0 | BO99: =BL99+BM99+BN99 -> 0 | BS99: =BP99+BQ99+BR99 -> 0 | BW99: =BT99+BU99+BV99 -> 0 | CA99: =BX99+BY99+BZ99 -> 0 | CE99: =CB99+CC99+CD99 -> 0 | CI99: =CF99+CG99+CH99 -> 0
C100: =Tekstnøgler!C185 -> Solgte produkter | D100: =D101+D102+D105+D108 -> 0 | E100: =E101+E102+E105+E108 -> 0 | F100: =F101+F102+F105+F108 -> 0 | G100: =G101+G102+G105+G108 -> 0 | H100: =H101+H102+H105+H108 -> 0 | I100: =I101+I102+I105+I108 -> 0 | J100: =J101+J102+J105+J108 -> 0 | K100: =K101+K102+K105+K108 -> 0 | ... CI100: =CI101+CI102+CI105+CI108 -> 0
C101: =Tekstnøgler!C186 -> Forarbejdning og processering af solgte produkter | G101: =D101+E101+F101 -> 0 | K101: =H101+I101+J101 -> 0 | O101: =L101+M101+N101 -> 0 | S101: =P101+Q101+R101 -> 0 | W101: =T101+U101+V101 -> 0 | AA101: =X101+Y101+Z101 -> 0 | AE101: =AB101+AC101+AD101 -> 0 | AI101: =AF101+AG101+AH101 -> 0 | AM101: =AJ101+AK101+AL101 -> 0 | AQ101: =AN101+AO101+AP101 -> 0 | AU101: =AR101+AS101+AT101 -> 0 | AY101: =AV101+AW101+AX101 -> 0 | BC101: =AZ101+BA101+BB101 -> 0 | BG101: =BD101+BE101+BF101 -> 0 | BK101: =BH101+BI101+BJ101 -> 0 | BO101: =BL101+BM101+BN101 -> 0 | BS101: =BP101+BQ101+BR101 -> 0 | BW101: =BT101+BU101+BV101 -> 0 | CA101: =BX101+BY101+BZ101 -> 0 | CE101: =CB101+CC101+CD101 -> 0 | CI101: =CF101+CG101+CH101 -> 0
C102: =Tekstnøgler!C187 -> Brug af solgte og udlejede produkter | D102: =SUM(D103:D104) -> 0 | E102: =SUM(E103:E104) -> 0 | F102: =SUM(F103:F104) -> 0 | G102: =SUM(G103:G104) -> 0 | H102: =SUM(H103:H104) -> 0 | I102: =SUM(I103:I104) -> 0 | J102: =SUM(J103:J104) -> 0 | K102: =SUM(K103:K104) -> 0 | ... CI102: =SUM(CI103:CI104) -> 0
C103: =Tekstnøgler!C188 -> Brug af solgte og udlejede produkter | G103: =D103+E103+F103 -> 0 | K103: =H103+I103+J103 -> 0 | O103: =L103+M103+N103 -> 0 | S103: =P103+Q103+R103 -> 0 | W103: =T103+U103+V103 -> 0 | AA103: =X103+Y103+Z103 -> 0 | AE103: =AB103+AC103+AD103 -> 0 | AI103: =AF103+AG103+AH103 -> 0 | AM103: =AJ103+AK103+AL103 -> 0 | AQ103: =AN103+AO103+AP103 -> 0 | AU103: =AR103+AS103+AT103 -> 0 | AY103: =AV103+AW103+AX103 -> 0 | BC103: =AZ103+BA103+BB103 -> 0 | BG103: =BD103+BE103+BF103 -> 0 | BK103: =BH103+BI103+BJ103 -> 0 | BO103: =BL103+BM103+BN103 -> 0 | BS103: =BP103+BQ103+BR103 -> 0 | BW103: =BT103+BU103+BV103 -> 0 | CA103: =BX103+BY103+BZ103 -> 0 | CE103: =CB103+CC103+CD103 -> 0 | CI103: =CF103+CG103+CH103 -> 0
C104: =Tekstnøgler!C189 -> Brug af solgte og udlejede produkter med egne emissionsfaktorer | G104: =D104+E104+F104 -> 0 | K104: =H104+I104+J104 -> 0 | O104: =L104+M104+N104 -> 0 | S104: =P104+Q104+R104 -> 0 | W104: =T104+U104+V104 -> 0 | AA104: =X104+Y104+Z104 -> 0 | AE104: =AB104+AC104+AD104 -> 0 | AI104: =AF104+AG104+AH104 -> 0 | AM104: =AJ104+AK104+AL104 -> 0 | AQ104: =AN104+AO104+AP104 -> 0 | AU104: =AR104+AS104+AT104 -> 0 | AY104: =AV104+AW104+AX104 -> 0 | BC104: =AZ104+BA104+BB104 -> 0 | BG104: =BD104+BE104+BF104 -> 0 | BK104: =BH104+BI104+BJ104 -> 0 | BO104: =BL104+BM104+BN104 -> 0 | BS104: =BP104+BQ104+BR104 -> 0 | BW104: =BT104+BU104+BV104 -> 0 | CA104: =BX104+BY104+BZ104 -> 0 | CE104: =CB104+CC104+CD104 -> 0 | CI104: =CF104+CG104+CH104 -> 0
C105: =Tekstnøgler!C190 -> End-of-life behandling | D105: =SUM(D106:D107) -> 0 | E105: =SUM(E106:E107) -> 0 | F105: =SUM(F106:F107) -> 0 | G105: =SUM(G106:G107) -> 0 | H105: =SUM(H106:H107) -> 0 | I105: =SUM(I106:I107) -> 0 | J105: =SUM(J106:J107) -> 0 | K105: =SUM(K106:K107) -> 0 | ... CI105: =SUM(CI106:CI107) -> 0
C106: =Tekstnøgler!C191 -> Håndtering af affaldsprodukt | G106: =D106+E106+F106 -> 0 | K106: =H106+I106+J106 -> 0 | O106: =L106+M106+N106 -> 0 | S106: =P106+Q106+R106 -> 0 | W106: =T106+U106+V106 -> 0 | AA106: =X106+Y106+Z106 -> 0 | AE106: =AB106+AC106+AD106 -> 0 | AI106: =AF106+AG106+AH106 -> 0 | AM106: =AJ106+AK106+AL106 -> 0 | AQ106: =AN106+AO106+AP106 -> 0 | AU106: =AR106+AS106+AT106 -> 0 | AY106: =AV106+AW106+AX106 -> 0 | BC106: =AZ106+BA106+BB106 -> 0 | BG106: =BD106+BE106+BF106 -> 0 | BK106: =BH106+BI106+BJ106 -> 0 | BO106: =BL106+BM106+BN106 -> 0 | BS106: =BP106+BQ106+BR106 -> 0 | BW106: =BT106+BU106+BV106 -> 0 | CA106: =BX106+BY106+BZ106 -> 0 | CE106: =CB106+CC106+CD106 -> 0 | CI106: =CF106+CG106+CH106 -> 0
C107: =Tekstnøgler!C192 -> Håndtering af affaldsprodukt med egne emissionsfaktorer | G107: =D107+E107+F107 -> 0 | K107: =H107+I107+J107 -> 0 | O107: =L107+M107+N107 -> 0 | S107: =P107+Q107+R107 -> 0 | W107: =T107+U107+V107 -> 0 | AA107: =X107+Y107+Z107 -> 0 | AE107: =AB107+AC107+AD107 -> 0 | AI107: =AF107+AG107+AH107 -> 0 | AM107: =AJ107+AK107+AL107 -> 0 | AQ107: =AN107+AO107+AP107 -> 0 | AU107: =AR107+AS107+AT107 -> 0 | AY107: =AV107+AW107+AX107 -> 0 | BC107: =AZ107+BA107+BB107 -> 0 | BG107: =BD107+BE107+BF107 -> 0 | BK107: =BH107+BI107+BJ107 -> 0 | BO107: =BL107+BM107+BN107 -> 0 | BS107: =BP107+BQ107+BR107 -> 0 | BW107: =BT107+BU107+BV107 -> 0 | CA107: =BX107+BY107+BZ107 -> 0 | CE107: =CB107+CC107+CD107 -> 0 | CI107: =CF107+CG107+CH107 -> 0
C108: =Tekstnøgler!C193 -> Andet udledning ved solgte og udlejede produkter | G108: =D108+E108+F108 -> 0 | K108: =H108+I108+J108 -> 0 | O108: =L108+M108+N108 -> 0 | S108: =P108+Q108+R108 -> 0 | W108: =T108+U108+V108 -> 0 | AA108: =X108+Y108+Z108 -> 0 | AE108: =AB108+AC108+AD108 -> 0 | AI108: =AF108+AG108+AH108 -> 0 | AM108: =AJ108+AK108+AL108 -> 0 | AQ108: =AN108+AO108+AP108 -> 0 | AU108: =AR108+AS108+AT108 -> 0 | AY108: =AV108+AW108+AX108 -> 0 | BC108: =AZ108+BA108+BB108 -> 0 | BG108: =BD108+BE108+BF108 -> 0 | BK108: =BH108+BI108+BJ108 -> 0 | BO108: =BL108+BM108+BN108 -> 0 | BS108: =BP108+BQ108+BR108 -> 0 | BW108: =BT108+BU108+BV108 -> 0 | CA108: =BX108+BY108+BZ108 -> 0 | CE108: =CB108+CC108+CD108 -> 0 | CI108: =CF108+CG108+CH108 -> 0
C109: =Tekstnøgler!C402 -> Total | D109: =D35+D47+D76+D95+D100 -> 11 | E109: =E35+E47+E76+E95+E100 -> 7 | F109: =F35+F47+F76+F95+F100 -> 8 | G109: =G35+G47+G76+G95+G100 -> 26 | H109: =H35+H47+H76+H95+H100 -> 8 | I109: =I35+I47+I76+I95+I100 -> 8 | J109: =J35+J47+J76+J95+J100 -> 8 | K109: =K35+K47+K76+K95+K100 -> 24 | ... CI109: =CI35+CI47+CI76+CI95+CI100 -> 24
...

Sheet Reduktionsmålsætning
C2: =Tekstnøgler!C419 -> Reduktionsmålsætninger | J2: =Tekstnøgler!$C$2 -> <-- Gå til forsiden
C5: =Tekstnøgler!C420 -> Basisberegning
C6: [TITEL]
C9: =Tekstnøgler!C421 -> Målsætning baseret på fremskrivning
C11: =Tekstnøgler!C422 -> Resultater er baseret på din virksomheds fremskrevne CO₂e-udledninger samt dit valg målsætningsmetode, målsætningsår og målsætning i procent. Dine valg og indtastninger er skrevet op i boksen "Parametre" herunder. Du kan læse mere om, hvordan du kan sætte målsætninger i fanen "Reduktionsmålsætninger" på Klimakompassets hjemmeside
C13: =Tekstnøgler!$C$423 -> Parametre
C14: =Tekstnøgler!$C$424 -> Målsætningsmetode | D14: Manuel
C15: =Tekstnøgler!$C$425 -> Målsætningsår | D15: 2030 | E15: =IF(D15>MAX(2030,'Fremskrivning - Hovedresultater'!C11+10),"Målsætningsår må ikke være større end maks(2030;startår+10)","")
C16: =Tekstnøgler!$C$426 -> Målsætning | D16: 0.65 | E16: =IF(D16>1,"Målsætning må ikke være større end 100%","")
C17: =Tekstnøgler!$C$427 -> Målsætning (Ton CO₂e) | D17: =('Fremskrivning - Hovedresultater'!D25+'Fremskrivning - Hovedresultater'!D26)*(1-Reduktionsmålsætning!D16) -> 6.3
C18: =Tekstnøgler!$C$428 -> Fremskrevet udledning i målsætningsår | D18: =LOOKUP($D$15,D49:S49,D52:S52) -> 8
C19: =IF(D18>D17,Tekstnøgler!$C$430,Tekstnøgler!$C$429) -> Forskel til målet | D19: =IF(D18>D17,V61,V60) -> 0.2125
C21: =IF(AND(V60="",V61<>""),Tekstnøgler!C464&D16*100&Tekstnøgler!C470&D15&", "&CHAR(10)&Tekstnøgler!C465&ROUND(V61*100,0)&Tekstnøgler!C466,Tekstnøgler!C467&D16*100&Tekstnøgler!C469&D15&". "&CHAR(10)&Tekstnøgler!C468) -> For at nå det udledningsniveau, som lever op til jeres egen målsætning om en 65% reduktion af scope 3 CO₂e-udledninger i 2030, skal disse CO₂e-udledninger reduceres med yderligere 21% i forhold til jeres fremskrevne udledninger.
C23: =Tekstnøgler!C432 -> Figur 1: Fremskrivning og mål for udledninger i scope 1 og 2
C46: =Tekstnøgler!C433 -> Her ses tabelvisning af fremskevne udledninger til grund for målsætningen for scope 1 og 2 år for år
C47: =Tekstnøgler!C434 -> Tabel 1. Oversigt over virksomhedens CO₂e-udledninger fordelt på scope 1 og 2
C48: =Tekstnøgler!C200 -> Scope | D48: =Tekstnøgler!C348 -> Ton CO₂e
D49: 2015 | E49: 2016 | F49: 2017 | G49: 2018 | H49: 2019 | I49: 2020 | J49: 2021 | K49: 2022 | L49: 2023 | M49: 2024 | N49: 2025 | O49: 2026 | P49: 2027 | Q49: 2028 | R49: 2029 | S49: 2030 | T49: =Tekstnøgler!$C$435&" "&$D$15 -> Mål 2030
C50: =Tekstnøgler!C203 -> Scope 1 | D50: ='Fremskrivning - Delresultater'!D16 -> 11 | E50: ='Fremskrivning - Delresultater'!E16 -> 8 | F50: ='Fremskrivning - Delresultater'!F16 -> 8 | G50: ='Fremskrivning - Delresultater'!G16 -> 8 | H50: ='Fremskrivning - Delresultater'!H16 -> 8 | I50: ='Fremskrivning - Delresultater'!I16 -> 8 | J50: ='Fremskrivning - Delresultater'!J16 -> 8 | K50: ='Fremskrivning - Delresultater'!K16 -> 8 | ... S50: ='Fremskrivning - Delresultater'!S16 -> 4
C51: =Tekstnøgler!C204 -> Scope 2 | D51: ='Fremskrivning - Delresultater'!D17 -> 7 | E51: ='Fremskrivning - Delresultater'!E17 -> 8 | F51: ='Fremskrivning - Delresultater'!F17 -> 8 | G51: ='Fremskrivning - Delresultater'!G17 -> 8 | H51: ='Fremskrivning - Delresultater'!H17 -> 8 | I51: ='Fremskrivning - Delresultater'!I17 -> 20 | J51: ='Fremskrivning - Delresultater'!J17 -> 8 | K51: ='Fremskrivning - Delresultater'!K17 -> 8 | ... S51: ='Fremskrivning - Delresultater'!S17 -> 4
C52: =Tekstnøgler!C436 -> Scope 1 og 2 (total) | D52: =SUM(D50:D51) -> 18 | E52: =SUM(E50:E51) -> 16 | F52: =SUM(F50:F51) -> 16 | G52: =SUM(G50:G51) -> 16 | H52: =SUM(H50:H51) -> 16 | I52: =SUM(I50:I51) -> 28 | J52: =SUM(J50:J51) -> 16 | K52: =SUM(K50:K51) -> 16 | ... S52: =SUM(S50:S51) -> 8 | T52: =$D$17 -> 6.3
C53: =Tekstnøgler!C426 -> Målsætning | T53: =$D$17 -> 6.3 | W53: Skjult rækker
A54: Ny | U54: =MIN($D$17,$D$18) -> 6.3 | W54: Skjult rækker
C55: =IF($D$17>$D$18,Tekstnøgler!C437,Tekstnøgler!C449) -> (ikke relevant) | U55: =-MIN($D$18-$D$17,0) -> 0
A56: Ny | C56: =IF($D$17<=$D$18,Tekstnøgler!C439,Tekstnøgler!C440) -> Forskel til målet | U56: =MAX($D$18-$D$17,0) -> 1.7 | W56: Skjult rækker
C57: =IF($D$18<$D$17,Tekstnøgler!C594,Tekstnøgler!C595) -> Målsætning (%) | V57: =U54 -> 6.3
A58: Ny | C58: =IF($D$17>$D$18,Tekstnøgler!C437,"") | V58: =U55 -> 0 | W58: Skjult rækker
C59: =IF($D$17<=$D$18,Tekstnøgler!C596,"") -> Manglende reduction | V59: =U56 -> 1.7
A60: Ny | C60: Etikets værdi for Scope 1+2 (reduktion) | V60: =IF($D$17>$D$18,ROUND(($D$18-$D$17)/$D$18,3),"") | W60: Skjult rækker
A61: Ny | C61: Etikets værdi for Scope 1+2 (stigning) | V61: =IF(AND($D$18<>0,$D$18>=$D$17),($D$18-$D$17)/$D$18,"") -> 0.2125 | W61: Skjult rækker
C63: =Tekstnøgler!C441 -> Reduktionsmålsætning for Scope 3
C65: =Tekstnøgler!C442 -> Resultater er baseret på din virksomheds fremskrevne CO₂e-udledninger samt dit valg målsætningsmetode, målsætningsår og målsætning i procent. Dine valg og indtastninger er skrevet op i boksen "Parametre" herunder. Du kan læse mere om, hvordan du kan sætte målsætninger i fanen "Reduktionsmålsætninger" på Klimakompassets hjemmeside
C67: =Tekstnøgler!$C$423 -> Parametre
C68: =Tekstnøgler!$C$424 -> Målsætningsmetode | D68: SBTi
C69: =Tekstnøgler!$C$425 -> Målsætningsår | D69: 2030 | E69: =IF(D69>MAX(2030,'Fremskrivning - Hovedresultater'!C11+10),"Målsætningsår må ikke være større end maks(2030;Startår +10)","")
C70: =Tekstnøgler!$C$426 -> Målsætning | D70: 0.65 | E70: =IF(D70>1,"Målsætning må ikke være større end 100%","")
C71: =Tekstnøgler!$C$427 -> Målsætning (Ton CO₂e) | D71: =D103*(1-Reduktionsmålsætning!D70) -> 1.876
C72: =Tekstnøgler!$C$428 -> Fremskrevet udledning i målsætningsår | D72: =LOOKUP(D69,D102:S102,D103:S103) -> 3.35
C73: =IF(D72>D71,Tekstnøgler!$C$430,Tekstnøgler!$C$429) -> Forskel til målet | D73: =IF(D72>D71,V113,V112) -> 0.44
C75: =IF(V112="",Tekstnøgler!C464&D70*100&Tekstnøgler!C470&D69&", "&CHAR(10)&Tekstnøgler!C465&ROUND(V113*100,0)&Tekstnøgler!C466,Tekstnøgler!C467&D70*100&Tekstnøgler!C470&D69&". "&CHAR(10)&Tekstnøgler!C468) -> For at nå det udledningsniveau, som lever op til jeres egen målsætning om en 65% reduktion af scope 3 CO₂e-udledninger i 2030, skal disse CO₂e-udledninger reduceres med yderligere 44% i forhold til jeres fremskrevne udledninger.
C77: =Tekstnøgler!C444 -> Figur 2: Fremskrivning og mål for udledninger i scope 3
C98: =Tekstnøgler!C445 -> Her ses tabelvisning af fremskevne udledninger til grund for målsætningen for scope 3 år for år
C100: =Tekstnøgler!C446 -> Tabel 2. Oversigt over virksomhedens CO₂e-udledninger i scope 3
C101: =Tekstnøgler!C200 -> Scope | D101: =Tekstnøgler!C348 -> Ton CO₂e
D102: 2015 | E102: 2016 | F102: 2017 | G102: 2018 | H102: 2019 | I102: 2020 | J102: 2021 | K102: 2022 | L102: 2023 | M102: 2024 | N102: 2025 | O102: 2026 | P102: 2027 | Q102: 2028 | R102: 2029 | S102: 2030 | T102: =Tekstnøgler!$C$435&" "&$D$69 -> Mål 2030
C103: =Tekstnøgler!C205 -> Scope 3 | D103: =IF($D$68="SBTI",0.67*'Fremskrivning - Delresultater'!D18,'Fremskrivning - Delresultater'!D18) -> 5.36 | E103: =IF($D$68="SBTI",0.67*'Fremskrivning - Delresultater'!E18,'Fremskrivning - Delresultater'!E18) -> 5.36 | F103: =IF($D$68="SBTI",0.67*'Fremskrivning - Delresultater'!F18,'Fremskrivning - Delresultater'!F18) -> 5.36 | G103: =IF($D$68="SBTI",0.67*'Fremskrivning - Delresultater'!G18,'Fremskrivning - Delresultater'!G18) -> 5.36 | H103: =IF($D$68="SBTI",0.67*'Fremskrivning - Delresultater'!H18,'Fremskrivning - Delresultater'!H18) -> 5.36 | I103: =IF($D$68="SBTI",0.67*'Fremskrivning - Delresultater'!I18,'Fremskrivning - Delresultater'!I18) -> 5.36 | J103: =IF($D$68="SBTI",0.67*'Fremskrivning - Delresultater'!J18,'Fremskrivning - Delresultater'!J18) -> 5.36 | K103: =IF($D$68="SBTI",0.67*'Fremskrivning - Delresultater'!K18,'Fremskrivning - Delresultater'!K18) -> 5.36 | ... S103: =IF($D$68="SBTI",0.67*'Fremskrivning - Delresultater'!S18,'Fremskrivning - Delresultater'!S18) -> 3.35
C104: =Tekstnøgler!C599 -> Scope 3 andel, udenfor målsætning | D104: =IF($D$68="SBTI",0.33*'Fremskrivning - Delresultater'!D18,"") -> 2.64 | E104: =IF($D$68="SBTI",0.33*'Fremskrivning - Delresultater'!E18,"") -> 2.64 | F104: =IF($D$68="SBTI",0.33*'Fremskrivning - Delresultater'!F18,"") -> 2.64 | G104: =IF($D$68="SBTI",0.33*'Fremskrivning - Delresultater'!G18,"") -> 2.64 | H104: =IF($D$68="SBTI",0.33*'Fremskrivning - Delresultater'!H18,"") -> 2.64 | I104: =IF($D$68="SBTI",0.33*'Fremskrivning - Delresultater'!I18,"") -> 2.64 | J104: =IF($D$68="SBTI",0.33*'Fremskrivning - Delresultater'!J18,"") -> 2.64 | K104: =IF($D$68="SBTI",0.33*'Fremskrivning - Delresultater'!K18,"") -> 2.64 | ... S104: =IF($D$68="SBTI",0.33*'Fremskrivning - Delresultater'!S18,"") -> 1.65
C105: =Tekstnøgler!C597 -> Målsætning for scope 3 | T105: =$D$71 -> 1.876
A106: Ny | C106: =IF($D$71>$D$72,Tekstnøgler!C598,Tekstnøgler!C597) -> Målsætning for scope 3 | U106: =MIN($D$71,$D$72) -> 1.876 | W106: Skjult rækker
A107: Ny | C107: =IF($D$71>$D$72,Tekstnøgler!C448,Tekstnøgler!C449) -> (ikke relevant) | U107: =-MIN($D$72-$D$71,0) -> 0 | W107: Skjult rækker
A108: Ny | C108: =IF($D$71<=$D$72,Tekstnøgler!C450,Tekstnøgler!C451) -> Forskel til målet | U108: =MAX($D$72-$D$71,0) -> 1.474 | W108: Skjult rækker
A109: Ny | C109: =IF($D$72<$D$71,Tekstnøgler!C594,Tekstnøgler!C595) -> Målsætning (%) | V109: =U106 -> 1.876 | W109: Skjult rækker
A110: Ny | C110: =IF($D$71>$D$72,Tekstnøgler!C437,"") | V110: =U107 -> 0 | W110: Skjult rækker
A111: Ny | C111: =IF($D$71<=$D$72,Tekstnøgler!C596,"") -> Manglende reduction | V111: =U108 -> 1.474 | W111: Skjult rækker
A112: Ny | C112: Etikets værdi for scope 3 (reduktion) | V112: =IF($D$72<$D$71,ROUND(($D$72-$D$71)/$D$72,3),"") | W112: Skjult rækker
A113: Ny | C113: Etikets værdi for scope 3 (stigning) | V113: =IF($D$72>=$D$71,($D$72-$D$71)/$D$72,"") -> 0.44 | W113: Skjult rækker
C115: =Tekstnøgler!C452 -> Langsigtet net zero målsætning
C117: =Tekstnøgler!C453 -> Værd at vide om net zero målsætning: - Net Zero standarden er SBTi's ramme for en langsigtet målsætning, som følger Paris-aftalens 1,5 graders målsætning. - Net Zero standarden fastsætter, at virksomheder som minimum skal reducere 90% ift. basisåret senest i 2050. - Net zero målsætningen skal som minimum dække 95% af en virksomheds scope 1 og 2 udledninger og 90% af virksomhedens scope 3 udledninger. - Den viste net zero målsætning dækker din virksomheds samlede klimaaftryk.
C118: =Tekstnøgler!C454 -> Du kan læse mere om net zero standarden her:
C119: https://sciencebasedtargets.org/net-zero
C122: =Tekstnøgler!$C$423 -> Parametre
C123: =Tekstnøgler!$C$424 -> Målsætningsmetode | D123: Manuel
C124: =Tekstnøgler!$C$425 -> Målsætningsår | D124: 2050 | E124: =IF(D124>2050,"Målsætningsår må ikke være større end 2050","")
C125: =Tekstnøgler!$C$426 -> Målsætning | D125: 0.9 | E125: =IF(D125>1,"Målsætning må ikke være større end 100%","")
C126: =Tekstnøgler!C455 -> Resultater | D126: =Tekstnøgler!C105 -> Ton CO₂e
C127: =Tekstnøgler!C456 -> Scope 1 - Basisår | D127: =$D$50 -> 11
C128: =Tekstnøgler!C457 -> Scope 2 - Basisår | D128: =$D$51 -> 7
C129: =Tekstnøgler!C458 -> Scope 3 - Basisår | D129: ='Fremskrivning - Delresultater'!D18 -> 8
C130: =Tekstnøgler!C459 -> Total udledning i basisår | D130: =D127+D128+D129 -> 26
C131: =Tekstnøgler!C460 -> Udledning i målsætningsår | D131: =D130*(1-D125) -> 2.6
C133: =Tekstnøgler!C461 -> Du kan vælge at fastsætte en samlet kortsigtet målsætning for din virksomheds scope 1 og 2. Du kan vælge mellem to metoder: Manuel og Minimum Absolut Emissions Contractions (MAEC). Ved valg af manuel målsætning skal du selv fastsætte målsætningsår samt målsætning. Læs mere om målsætningsmetoderne øverst på siden.
C135: =Tekstnøgler!C462 -> Figur 4: Fordeling af udledninger i basisår (ton CO₂e) | G135: =Tekstnøgler!C463 -> Figur 5: Forskel i udledninger fra baisår til målsætningsår (ton CO₂e)

Sheet Emissionsfaktorer
B2: =Tekstnøgler!C473 -> Emissionsfaktorer | E2: =Tekstnøgler!$C$2 -> <-- Gå til forsiden
B4: =Tekstnøgler!C588 -> Emissionsfaktorår | C4: =Tekstnøgler!C591 -> Beregningens startår
B5: 2021 | C5: 2021
B8: =Tekstnøgler!C475 -> Tabel med emissionsfaktorer
K9: =Tekstnøgler!C608 -> Til opgørelse af E-nøgletal
B10: =Tekstnøgler!$C$476 -> Hovedkategori | C10: =Tekstnøgler!$C$491 -> Kategori | D10: =Tekstnøgler!$C$477 -> Parameter | E10: =Tekstnøgler!$C$478 -> Parameter 2 | F10: =Tekstnøgler!$C$479 -> Enhed | G10: =Tekstnøgler!C480 -> Scope 1 - faktor | H10: =Tekstnøgler!C481 -> Scope 2 - faktor | I10: =Tekstnøgler!C482 -> Scope 3 - faktor | J10: =Tekstnøgler!C483 -> Udenfor scope - faktor | K10: =Tekstnøgler!C604 -> Omregning til MWh | L10: =Tekstnøgler!C605 -> Vedvarende energiandel | M10: =Tekstnøgler!C606 -> Nuklear energiandel | N10: =Tekstnøgler!C607 -> Fossil energiandel | O10: =Tekstnøgler!C484 -> Kilde (år)
B11: =Tekstnøgler!C376 -> Affald og genbrug | C11: =Tekstnøgler!C182 -> Affald | E11: Glas | F11: ="Kg CO₂-e / "&Tekstnøgler!C750 -> Kg CO₂-e / Ton | G11: 0 | H11: 0 | I11: 0 | J11: 591.09109 | K11: =Tekstnøgler!C544 -> Ikke relevant | L11: =Tekstnøgler!C544 -> Ikke relevant | M11: =Tekstnøgler!C544 -> Ikke relevant | N11: =Tekstnøgler!C544 -> Ikke relevant | O11: EXIOBASE v3.3.16b2 (v. 2020 m. 2011-data)
B12: =Tekstnøgler!C376 -> Affald og genbrug | C12: =Tekstnøgler!C182 -> Affald | E12: Glas | F12: ="Kg CO₂-e / "&Tekstnøgler!C750 -> Kg CO₂-e / Ton | G12: 0 | H12: 0 | I12: 0 | J12: -312.10832 | K12: =Tekstnøgler!C544 -> Ikke relevant | L12: =Tekstnøgler!C544 -> Ikke relevant | M12: =Tekstnøgler!C544 -> Ikke relevant | N12: =Tekstnøgler!C544 -> Ikke relevant | O12: EXIOBASE v3.3.16b2 (v. 2020 m. 2011-data)
B13: =Tekstnøgler!C376 -> Affald og genbrug | C13: =Tekstnøgler!C182 -> Affald | E13: Stål og jern | F13: ="Kg CO₂-e / "&Tekstnøgler!C750 -> Kg CO₂-e / Ton | G13: 0 | H13: 0 | I13: 0 | J13: -2654.1136 | K13: =Tekstnøgler!C544 -> Ikke relevant | L13: =Tekstnøgler!C544 -> Ikke relevant | M13: =Tekstnøgler!C544 -> Ikke relevant | N13: =Tekstnøgler!C544 -> Ikke relevant | O13: EXIOBASE v3.3.16b2 (v. 2020 m. 2011-data)
B14: =Tekstnøgler!C376 -> Affald og genbrug | C14: =Tekstnøgler!C182 -> Affald | E14: Stål og jern | F14: ="Kg CO₂-e / "&Tekstnøgler!C750 -> Kg CO₂-e / Ton | G14: 0 | H14: 0 | I14: 0 | J14: -2654.1136 | K14: =Tekstnøgler!C544 -> Ikke relevant | L14: =Tekstnøgler!C544 -> Ikke relevant | M14: =Tekstnøgler!C544 -> Ikke relevant | N14: =Tekstnøgler!C544 -> Ikke relevant | O14: EXIOBASE v3.3.16b2 (v. 2020 m. 2011-data)
B15: =Tekstnøgler!C376 -> Affald og genbrug | C15: =Tekstnøgler!C182 -> Affald | E15: =Tekstnøgler!C979 -> Træ | F15: ="Kg CO₂-e / "&Tekstnøgler!C750 -> Kg CO₂-e / Ton | G15: 0 | H15: 0 | I15: 0 | J15: -140.40055 | K15: =Tekstnøgler!C544 -> Ikke relevant | L15: =Tekstnøgler!C544 -> Ikke relevant | M15: =Tekstnøgler!C544 -> Ikke relevant | N15: =Tekstnøgler!C544 -> Ikke relevant | O15: EXIOBASE v3.3.16b2 (v. 2020 m. 2011-data)
B16: =Tekstnøgler!C376 -> Affald og genbrug | C16: =Tekstnøgler!C182 -> Affald | E16: =Tekstnøgler!C979 -> Træ | F16: ="Kg CO₂-e / "&Tekstnøgler!C750 -> Kg CO₂-e / Ton | G16: 0 | H16: 0 | I16: 0 | J16: -1501.18 | K16: =Tekstnøgler!C544 -> Ikke relevant | L16: =Tekstnøgler!C544 -> Ikke relevant | M16: =Tekstnøgler!C544 -> Ikke relevant | N16: =Tekstnøgler!C544 -> Ikke relevant | O16: Beregnet fra: EXIOBASE v3.3.16b2 (v. 2020 m. 2011-data), under antagelse af en kreditering 1:1 af undgået produktion af jomfruelig material
B17: =Tekstnøgler!C373 -> Energi og processer | C17: =Tekstnøgler!C126 -> Brændsler | D17: =Tekstnøgler!C126 -> Brændsler | E17: =Tekstnøgler!C768 -> Benzin | F17: ="Kg CO₂-e / "&Tekstnøgler!C981 -> Kg CO₂-e / L | G17: 2.1717501 | H17: 0 | I17: 0.58412922 | J17: 0.15201448 | K17: 0.009125 | L17: 0.10000953 | M17: 0 | N17: 0.89999047 | O17: Beregnet fra: Iblandingsprocenter (ENS, 2020), Energistatistik 2021 (Energistyrelsen, 2022), og UK Government GHG Conversion Factors for Company Reporting (DEFRA, 2022)
B18: =Tekstnøgler!C373 -> Energi og processer | C18: =Tekstnøgler!C126 -> Brændsler | D18: =Tekstnøgler!C126 -> Brændsler | E18: =Tekstnøgler!C917 -> Biogas | F18: ="Kg CO₂-e / "&Tekstnøgler!C710 -> Kg CO₂-e / m3 | G18: 0.0014055556 | H18: 0 | I18: 0.18150833 | J18: 1.8837 | K18: 0.0060563929 | L18: 1 | M18: 0 | N18: 0 | O18: Beregnet fra: Energistatistik 2021 (Energistyrelsen, 2022) og UK Government GHG Conversion Factors for Company Reporting (DEFRA, 2022)
B19: =Tekstnøgler!C373 -> Energi og processer | C19: =Tekstnøgler!C126 -> Brændsler | D19: =Tekstnøgler!C126 -> Brændsler | E19: Naturgas (0% opgraderet biogas) | F19: ="Kg CO₂-e / "&Tekstnøgler!C710 -> Kg CO₂-e / m3 | G19: 2.1466404 | H19: 0 | I19: 0.3434 | J19: 0 | K19: 0.0098508547 | L19: 0 | M19: 0 | N19: 1 | O19: Beregnet fra: Energistatistik 2021 (Energistyrelsen, 2022), Energistyrelsens Standardfaktorer 2021 (Energistyrelsen, 2022) og UK Government GHG Conversion Factors for Company Reporting (DEFRA, 2022)
B20: =Tekstnøgler!C373 -> Energi og processer | C20: =Tekstnøgler!C122 -> Forbrug af elektricitet | E20: =Tekstnøgler!C79 -> Eldeklaration | F20: ="Kg CO₂-e / "&Tekstnøgler!C837 -> Kg CO₂-e / MWh | G20: 0 | H20: 411.51 | I20: 73.578032 | J20: 28.863736 | K20: 1 | L20: 0.095627229 | M20: 0.3087312 | N20: 0.59564157 | O20: Beregnet fra: Energinets miljødeklarationen, 2021 (Energinet, 2024) og UK Government GHG Conversion Factors for Company Reporting (DEFRA, 2022)
B21: =Tekstnøgler!C374 -> Indkøb | C21: =Tekstnøgler!C135 -> Indkøb af materialer i fysiske enheder | D21: =Tekstnøgler!C743 -> Metaller | E21: =Tekstnøgler!C765 -> Stål og jern (nyt) | F21: ="Kg CO₂-e / "&Tekstnøgler!C750 -> Kg CO₂-e / Ton | G21: 0 | H21: 0 | I21: 2372.3701 | J21: 0 | K21: =Tekstnøgler!C544 -> Ikke relevant | L21: =Tekstnøgler!C544 -> Ikke relevant | M21: =Tekstnøgler!C544 -> Ikke relevant | N21: =Tekstnøgler!C544 -> Ikke relevant | O21: EXIOBASE v3.8-hybrid beta 2 (v. 2024 m. 2016-data)
B22: =Tekstnøgler!C374 -> Indkøb | C22: =Tekstnøgler!C135 -> Indkøb af materialer i fysiske enheder | D22: =Tekstnøgler!C836 -> Øvrige | E22: =Tekstnøgler!C957 -> Glas (nyt) | F22: ="Kg CO₂-e / "&Tekstnøgler!C750 -> Kg CO₂-e / Ton | G22: 0 | H22: 0 | I22: 1000.0532 | J22: 0 | K22: =Tekstnøgler!C544 -> Ikke relevant | L22: =Tekstnøgler!C544 -> Ikke relevant | M22: =Tekstnøgler!C544 -> Ikke relevant | N22: =Tekstnøgler!C544 -> Ikke relevant | O22: EXIOBASE v3.3.16b2 (v. 2020 m. 2011-data)
B23: =Tekstnøgler!C374 -> Indkøb | C23: =Tekstnøgler!C135 -> Indkøb af materialer i fysiske enheder | D23: =Tekstnøgler!C836 -> Øvrige | E23: =Tekstnøgler!C983 -> Træ (nyt) | F23: ="Kg CO₂-e / "&Tekstnøgler!C750 -> Kg CO₂-e / Ton | G23: 0 | H23: 0 | I23: 946.24262 | J23: 0 | K23: =Tekstnøgler!C544 -> Ikke relevant | L23: =Tekstnøgler!C544 -> Ikke relevant | M23: =Tekstnøgler!C544 -> Ikke relevant | N23: =Tekstnøgler!C544 -> Ikke relevant | O23: EXIOBASE v3.8-hybrid beta 2 (v. 2024 m. 2016-data)
B24: =Tekstnøgler!C374 -> Indkøb | C24: =Tekstnøgler!C140 -> Indkøb af produkter i fysiske enheder | D24: =Tekstnøgler!C836 -> Øvrige | E24: =Tekstnøgler!C876 -> Vandforbrug | F24: ="Kg CO₂-e / "&Tekstnøgler!C981 -> Kg CO₂-e / L | G24: 0 | H24: 0 | I24: 0.0023277183 | J24: 0 | K24: =Tekstnøgler!C544 -> Ikke relevant | L24: =Tekstnøgler!C544 -> Ikke relevant | M24: =Tekstnøgler!C544 -> Ikke relevant | N24: =Tekstnøgler!C544 -> Ikke relevant | O24: Beregnet i EXIOBASE v3.8. (v. 2024 m. 2016-data)
B25: =Tekstnøgler!C375 -> Transport | C25: =Tekstnøgler!C163 -> Egne og leasede transportmidler | D25: =Tekstnøgler!C928 -> Personbiler | E25: =Tekstnøgler!C768 -> Benzin | F25: Kg CO₂-e / km | G25: 0.15838271 | H25: 0 | I25: 0.04259973 | J25: 0.011086204 | K25: 0.00067281106 | L25: 0.10000953 | M25: 0 | N25: 0.89999047 | O25: Beregnet fra: DCE, Persontransport efter transportmiddel (DST, 2021), og UK Government GHG Conversion Factors for Company Reporting (DEFRA, 2022)
B26: =Tekstnøgler!C375 -> Transport | C26: =Tekstnøgler!C167 -> Pendling | D26: =Tekstnøgler!C928 -> Personbiler | E26: =Tekstnøgler!C768 -> Benzin | F26: ="Kg CO₂-e / "&Tekstnøgler!C888 -> Kg CO₂-e / Person.km | G26: 0 | H26: 0 | I26: 0.20098244 | J26: 0.011086204 | K26: =Tekstnøgler!C544 -> Ikke relevant | L26: =Tekstnøgler!C544 -> Ikke relevant | M26: =Tekstnøgler!C544 -> Ikke relevant | N26: =Tekstnøgler!C544 -> Ikke relevant | O26: Beregnet fra: DCE og UK Government GHG Conversion Factors for Company Reporting (DEFRA, 2022)
B27: =Tekstnøgler!C375 -> Transport | C27: =Tekstnøgler!C172 -> Varetransport i fysiske enheder | D27: =Tekstnøgler!C934 -> Lastbiler | E27: =Tekstnøgler!C893 -> Diesel | F27: ="Kg CO₂-e / "&Tekstnøgler!C906 -> Kg CO₂-e / Ton.km | G27: 0 | H27: 0 | I27: 0.13664 | J27: 0.0074906332 | K27: =Tekstnøgler!C544 -> Ikke relevant | L27: =Tekstnøgler!C544 -> Ikke relevant | M27: =Tekstnøgler!C544 -> Ikke relevant | N27: =Tekstnøgler!C544 -> Ikke relevant | O27: Beregnet fra: Iblandingsprocenter (ENS, 2020), Energistatistik 2021 (Energistyrelsen, 2022), og UK Government GHG Conversion Factors for Company Reporting (DEFRA, 2022)

Sheet Egne emissionsfaktorer
B2: =Tekstnøgler!C487 -> Tabel med egne emissionsfaktorer | E2: =Tekstnøgler!$C$2 -> <-- Gå til forsiden
B4: =Tekstnøgler!C591 -> Beregningens startår
B5: =YEAR(Stamdata!B14) -> 2021
B8: =Tekstnøgler!C489 -> Tabel med egne emissionsfaktorer
J9: =Tekstnøgler!C608 -> Til opgørelse af E-nøgletal
B10: =Tekstnøgler!$C$490 -> Hovedkategori | C10: =Tekstnøgler!$C$491 -> Kategori | D10: =Tekstnøgler!$C$492 -> Beskrivelse | E10: =Tekstnøgler!$C$493 -> Enhed | F10: =Tekstnøgler!$C$494 -> Scope 1 - faktor | G10: =Tekstnøgler!$C$495 -> Scope 2 - faktor | H10: =Tekstnøgler!$C$496 -> Scope 3 - faktor | I10: =Tekstnøgler!$C$497 -> Udenfor scope - faktor | J10: =Tekstnøgler!C609 -> Medtaget i E-nøgletal | K10: =Tekstnøgler!C604 -> Omregning til MWh | L10: =Tekstnøgler!C605 -> Vedvarende energiandel | M10: =Tekstnøgler!C606 -> Nuklear energiandel | N10: =Tekstnøgler!C607 -> Fossil energiandel

Sheet Fremskrevne emissionsfaktorer
B2: =Tekstnøgler!C500 -> Emissionsfaktorer for fremskrivning | F2: =Tekstnøgler!$C$2 -> <-- Gå til forsiden
B4: =Tekstnøgler!C501 -> Basisår | C4: =Tekstnøgler!C502 -> Slutår | D4: =Tekstnøgler!C590 -> Emissionsfaktorår for basisår
B5: ='Fremskrivning - Hovedresultater'!C11 -> 2015 | C5: ='Fremskrivning - Hovedresultater'!D11 -> 2030 | D5: =Emissionsfaktorer!B5 -> 2021
B8: =Tekstnøgler!C503 -> Tabel med emissionsfaktorer
G9: 2015 | K9: 2016 | O9: 2017 | S9: 2018 | W9: 2019 | AA9: 2020 | AE9: 2021 | AI9: 2022 | AM9: 2023 | AQ9: 2024 | AU9: 2025 | AY9: 2026 | BC9: 2027 | BG9: 2028 | BK9: 2029 | BO9: 2030 | BS9: 2031 | BW9: 2032 | CA9: 2033 | CE9: 2034 | CI9: 2035
B10: =Tekstnøgler!$C$476 -> Hovedkategori | C10: =Tekstnøgler!$C$491 -> Kategori | D10: =Tekstnøgler!$C$477 -> Parameter | E10: =Tekstnøgler!$C$478 -> Parameter 2 | F10: =Tekstnøgler!$C$479 -> Enhed | G10: =Tekstnøgler!$C$494 -> Scope 1 - faktor | H10: =Tekstnøgler!$C$495 -> Scope 2 - faktor | I10: =Tekstnøgler!$C$496 -> Scope 3 - faktor | J10: =Tekstnøgler!$C$497 -> Udenfor scope - faktor | K10: =Tekstnøgler!$C$494 -> Scope 1 - faktor | L10: =Tekstnøgler!$C$495 -> Scope 2 - faktor | M10: =Tekstnøgler!$C$496 -> Scope 3 - faktor | N10: =Tekstnøgler!$C$497 -> Udenfor scope - faktor | O10: =Tekstnøgler!$C$494 -> Scope 1 - faktor | P10: =Tekstnøgler!$C$495 -> Scope 2 - faktor | Q10: =Tekstnøgler!$C$496 -> Scope 3 - faktor | R10: =Tekstnøgler!$C$497 -> Udenfor scope - faktor | S10: =Tekstnøgler!$C$494 -> Scope 1 - faktor | T10: =Tekstnøgler!$C$495 -> Scope 2 - faktor | U10: =Tekstnøgler!$C$496 -> Scope 3 - faktor | V10: =Tekstnøgler!$C$497 -> Udenfor scope - faktor | W10: =Tekstnøgler!$C$494 -> Scope 1 - faktor | X10: =Tekstnøgler!$C$495 -> Scope 2 - faktor | Y10: =Tekstnøgler!$C$496 -> Scope 3 - faktor | Z10: =Tekstnøgler!$C$497 -> Udenfor scope - faktor | AA10: =Tekstnøgler!$C$494 -> Scope 1 - faktor | AB10: =Tekstnøgler!$C$495 -> Scope 2 - faktor | AC10: =Tekstnøgler!$C$496 -> Scope 3 - faktor | AD10: =Tekstnøgler!$C$497 -> Udenfor scope - faktor | AE10: =Tekstnøgler!$C$494 -> Scope 1 - faktor | AF10: =Tekstnøgler!$C$495 -> Scope 2 - faktor | AG10: =Tekstnøgler!$C$496 -> Scope 3 - faktor | AH10: =Tekstnøgler!$C$497 -> Udenfor scope - faktor | AI10: =Tekstnøgler!$C$494 -> Scope 1 - faktor | AJ10: =Tekstnøgler!$C$495 -> Scope 2 - faktor | AK10: =Tekstnøgler!$C$496 -> Scope 3 - faktor | AL10: =Tekstnøgler!$C$497 -> Udenfor scope - faktor | AM10: =Tekstnøgler!$C$494 -> Scope 1 - faktor | AN10: =Tekstnøgler!$C$495 -> Scope 2 - faktor | AO10: =Tekstnøgler!$C$496 -> Scope 3 - faktor | AP10: =Tekstnøgler!$C$497 -> Udenfor scope - faktor | AQ10: =Tekstnøgler!$C$494 -> Scope 1 - faktor | AR10: =Tekstnøgler!$C$495 -> Scope 2 - faktor | AS10: =Tekstnøgler!$C$496 -> Scope 3 - faktor | AT10: =Tekstnøgler!$C$497 -> Udenfor scope - faktor | AU10: =Tekstnøgler!$C$494 -> Scope 1 - faktor | AV10: =Tekstnøgler!$C$495 -> Scope 2 - faktor | AW10: =Tekstnøgler!$C$496 -> Scope 3 - faktor | AX10: =Tekstnøgler!$C$497 -> Udenfor scope - faktor | AY10: =Tekstnøgler!$C$494 -> Scope 1 - faktor | AZ10: =Tekstnøgler!$C$495 -> Scope 2 - faktor | BA10: =Tekstnøgler!$C$496 -> Scope 3 - faktor | BB10: =Tekstnøgler!$C$497 -> Udenfor scope - faktor | BC10: =Tekstnøgler!$C$494 -> Scope 1 - faktor | BD10: =Tekstnøgler!$C$495 -> Scope 2 - faktor | BE10: =Tekstnøgler!$C$496 -> Scope 3 - faktor | BF10: =Tekstnøgler!$C$497 -> Udenfor scope - faktor | BG10: =Tekstnøgler!$C$494 -> Scope 1 - faktor | BH10: =Tekstnøgler!$C$495 -> Scope 2 - faktor | BI10: =Tekstnøgler!$C$496 -> Scope 3 - faktor | BJ10: =Tekstnøgler!$C$497 -> Udenfor scope - faktor | BK10: =Tekstnøgler!$C$494 -> Scope 1 - faktor | BL10: =Tekstnøgler!$C$495 -> Scope 2 - faktor | BM10: =Tekstnøgler!$C$496 -> Scope 3 - faktor | BN10: =Tekstnøgler!$C$497 -> Udenfor scope - faktor | BO10: =Tekstnøgler!$C$494 -> Scope 1 - faktor | BP10: =Tekstnøgler!$C$495 -> Scope 2 - faktor | BQ10: =Tekstnøgler!$C$496 -> Scope 3 - faktor | BR10: =Tekstnøgler!$C$497 -> Udenfor scope - faktor | BS10: =Tekstnøgler!$C$494 -> Scope 1 - faktor | BT10: =Tekstnøgler!$C$495 -> Scope 2 - faktor | BU10: =Tekstnøgler!$C$496 -> Scope 3 - faktor | BV10: =Tekstnøgler!$C$497 -> Udenfor scope - faktor | BW10: =Tekstnøgler!$C$494 -> Scope 1 - faktor | BX10: =Tekstnøgler!$C$495 -> Scope 2 - faktor | BY10: =Tekstnøgler!$C$496 -> Scope 3 - faktor | BZ10: =Tekstnøgler!$C$497 -> Udenfor scope - faktor | CA10: =Tekstnøgler!$C$494 -> Scope 1 - faktor | CB10: =Tekstnøgler!$C$495 -> Scope 2 - faktor | CC10: =Tekstnøgler!$C$496 -> Scope 3 - faktor | CD10: =Tekstnøgler!$C$497 -> Udenfor scope - faktor | CE10: =Tekstnøgler!$C$494 -> Scope 1 - faktor | CF10: =Tekstnøgler!$C$495 -> Scope 2 - faktor | CG10: =Tekstnøgler!$C$496 -> Scope 3 - faktor | CH10: =Tekstnøgler!$C$497 -> Udenfor scope - faktor | CI10: =Tekstnøgler!$C$494 -> Scope 1 - faktor | CJ10: =Tekstnøgler!$C$495 -> Scope 2 - faktor | CK10: =Tekstnøgler!$C$496 -> Scope 3 - faktor | CL10: =Tekstnøgler!$C$497 -> Udenfor scope - faktor

Sheet Data (alle poster)
B2: =Tekstnøgler!C28 -> Data (alle poster) | E2: =Tekstnøgler!$C$2 -> <-- Gå til forsiden
A4: =Tekstnøgler!C506 -> Hovedkategori | B4: =Tekstnøgler!C507 -> Kategori | C4: =Tekstnøgler!C508 -> Underkategori | D4: =Tekstnøgler!C509 -> Beskrivelse | E4: =Tekstnøgler!C510 -> Parameter 1 - titel | F4: =Tekstnøgler!C511 -> Parameter | G4: =Tekstnøgler!C512 -> Parameter 2 - titel | H4: =Tekstnøgler!C513 -> Parameter 2 | I4: =Tekstnøgler!C514 -> Parameter 3 - titel | J4: =Tekstnøgler!C515 -> Parameter 3 | K4: =Tekstnøgler!C516 -> Mængde | L4: =Tekstnøgler!C517 -> Beløb (ekskl. Moms, DKK) | M4: =Tekstnøgler!C518 -> Enhed | N4: =Tekstnøgler!C519 -> Scope 1 - faktor | O4: =Tekstnøgler!C520 -> Scope 2 - faktor | P4: =Tekstnøgler!C521 -> Scope 3 - faktor | Q4: =Tekstnøgler!C522 -> Udledning i alt | R4: =Tekstnøgler!C523 -> Udenfor scope - faktor | S4: =Tekstnøgler!C524 -> Bemærkninger (fra inputfelt) | T4: =Tekstnøgler!C525 -> År for emissions-faktorer | U4: =Tekstnøgler!C526 -> Land for emissionsfaktorer | V4: =Tekstnøgler!C527 -> Metodevalg
A5: =Tekstnøgler!C376 -> Affald og genbrug | B5: =Tekstnøgler!C568 -> Affald | C5: =Tekstnøgler!C182 -> Affald | D5: Glas | E5: =Tekstnøgler!C832 -> Affaldstype | F5: Glas | G5: =Tekstnøgler!C723 -> Affaldshåndtering | H5: =Tekstnøgler!C1000 -> Forbrænding | K5: 100 | M5: =Tekstnøgler!C280 -> Ton | N5: 0 | O5: 0 | P5: 0 | Q5: 0 | R5: 59.109109 | T5: 2021 | U5: DK
A6: =Tekstnøgler!C376 -> Affald og genbrug | B6: =Tekstnøgler!C568 -> Affald | C6: =Tekstnøgler!C182 -> Affald | D6: Stål | E6: =Tekstnøgler!C832 -> Affaldstype | F6: Stål og jern | G6: =Tekstnøgler!C723 -> Affaldshåndtering | H6: =Tekstnøgler!C933 -> Genanvendelse | K6: 60 | M6: =Tekstnøgler!C280 -> Ton | N6: 0 | O6: 0 | P6: 0 | Q6: 0 | R6: -159.24682 | T6: 2021 | U6: DK
A7: =Tekstnøgler!C376 -> Affald og genbrug | B7: =Tekstnøgler!C568 -> Affald | C7: =Tekstnøgler!C182 -> Affald | D7: Træ | E7: =Tekstnøgler!C832 -> Affaldstype | F7: =Tekstnøgler!C979 -> Træ | G7: =Tekstnøgler!C723 -> Affaldshåndtering | H7: =Tekstnøgler!C933 -> Genanvendelse | K7: 200 | M7: =Tekstnøgler!C280 -> Ton | N7: 0 | O7: 0 | P7: 0 | Q7: 0 | R7: -28.08011 | T7: 2021 | U7: DK
A8: =Tekstnøgler!C373 -> Energi og processer | B8: =Tekstnøgler!C553 -> Elektricitet | C8: =Tekstnøgler!C122 -> Forbrug af elektricitet | D8: Elektricitet | E8: =Tekstnøgler!C833 -> Forbrug af vedvarende el fra egen produktion | F8: 0 | K8: 4500 | M8: =Tekstnøgler!C837 -> MWh | N8: 0 | O8: 1851.795 | P8: 331.10115 | Q8: 2182.8961 | R8: 129.88681 | T8: 2021 | U8: DK | V8: =Tekstnøgler!C79 -> Eldeklaration
A9: =Tekstnøgler!C373 -> Energi og processer | B9: =Tekstnøgler!C554 -> Varme og procesenergi | C9: =Tekstnøgler!C126 -> Brændsler | D9: Benzin | E9: =Tekstnøgler!C803 -> Brændselstype | F9: =Tekstnøgler!C768 -> Benzin | K9: 50000 | M9: =Tekstnøgler!C981 -> L | N9: 108.58751 | O9: 0 | P9: 29.206461 | Q9: 137.79397 | R9: 7.6007239 | T9: 2021 | U9: DK
A10: =Tekstnøgler!C373 -> Energi og processer | B10: =Tekstnøgler!C554 -> Varme og procesenergi | C10: =Tekstnøgler!C126 -> Brændsler | D10: Varme | E10: =Tekstnøgler!C803 -> Brændselstype | F10: =Tekstnøgler!C890 -> Naturgas (X% biogas) | K10: 152265 | M10: =Tekstnøgler!C710 -> m3 | N10: 326.8582 | O10: 0 | P10: 52.287801 | Q10: 379.146 | R10: 0 | T10: 2021 | U10: DK
A11: =Tekstnøgler!C374 -> Indkøb | B11: =Tekstnøgler!C557 -> Materialer | C11: =Tekstnøgler!C135 -> Indkøb af materialer i fysiske enheder | D11: Stål | E11: =Tekstnøgler!C900 -> Materialeproduktgruppe | F11: =Tekstnøgler!C743 -> Metaller | G11: =Tekstnøgler!C752 -> Materialegruppe | H11: =Tekstnøgler!C765 -> Stål og jern (nyt) | K11: 400 | M11: =Tekstnøgler!C280 -> Ton | N11: =Tekstnøgler!C544 -> Ikke relevant | O11: =Tekstnøgler!C544 -> Ikke relevant | P11: 948.94802 | Q11: 948.94802 | R11: =Tekstnøgler!C544 -> Ikke relevant | T11: 2021 | U11: DK
A12: =Tekstnøgler!C374 -> Indkøb | B12: =Tekstnøgler!C557 -> Materialer | C12: =Tekstnøgler!C135 -> Indkøb af materialer i fysiske enheder | D12: Nyt glas | E12: =Tekstnøgler!C900 -> Materialeproduktgruppe | F12: =Tekstnøgler!C836 -> Øvrige | G12: =Tekstnøgler!C752 -> Materialegruppe | H12: =Tekstnøgler!C957 -> Glas (nyt) | K12: 2500 | M12: =Tekstnøgler!C280 -> Ton | N12: =Tekstnøgler!C544 -> Ikke relevant | O12: =Tekstnøgler!C544 -> Ikke relevant | P12: 2500.133 | Q12: 2500.133 | R12: =Tekstnøgler!C544 -> Ikke relevant | T12: 2021 | U12: DK
A13: =Tekstnøgler!C374 -> Indkøb | B13: =Tekstnøgler!C557 -> Materialer | C13: =Tekstnøgler!C135 -> Indkøb af materialer i fysiske enheder | D13: Træ | E13: =Tekstnøgler!C900 -> Materialeproduktgruppe | F13: =Tekstnøgler!C836 -> Øvrige | G13: =Tekstnøgler!C752 -> Materialegruppe | H13: =Tekstnøgler!C983 -> Træ (nyt) | K13: 3500 | M13: =Tekstnøgler!C280 -> Ton | N13: =Tekstnøgler!C544 -> Ikke relevant | O13: =Tekstnøgler!C544 -> Ikke relevant | P13: 3311.8492 | Q13: 3311.8492 | R13: =Tekstnøgler!C544 -> Ikke relevant | T13: 2021 | U13: DK
A14: =Tekstnøgler!C374 -> Indkøb | B14: =Tekstnøgler!C558 -> Produkter og services | C14: =Tekstnøgler!C140 -> Indkøb af produkter i fysiske enheder | D14: Vand | E14: =Tekstnøgler!C974 -> Produktgruppe | F14: =Tekstnøgler!C836 -> Øvrige | G14: =Tekstnøgler!C843 -> Specifikke produkter | H14: =Tekstnøgler!C876 -> Vandforbrug | K14: 2000000 | M14: =Tekstnøgler!C981 -> L | N14: =Tekstnøgler!C544 -> Ikke relevant | O14: =Tekstnøgler!C544 -> Ikke relevant | P14: 4.6554366 | Q14: 4.6554366 | R14: =Tekstnøgler!C544 -> Ikke relevant | T14: 2021 | U14: DK
A15: =Tekstnøgler!C377 -> Solgte produkter | B15: =Tekstnøgler!C573 -> End-of-life behandling | C15: =Tekstnøgler!C191 -> Håndtering af affaldsprodukt | D15: Glas | E15: =Tekstnøgler!C832 -> Affaldstype | F15: Glas | G15: =Tekstnøgler!C723 -> Affaldshåndtering | H15: =Tekstnøgler!C933 -> Genanvendelse | K15: 50 | M15: =Tekstnøgler!C280 -> Ton | N15: =Tekstnøgler!C544 -> Ikke relevant | O15: =Tekstnøgler!C544 -> Ikke relevant | P15: 0 | Q15: 0 | R15: -15.605416 | T15: 2021 | U15: DK
A16: =Tekstnøgler!C377 -> Solgte produkter | B16: =Tekstnøgler!C573 -> End-of-life behandling | C16: =Tekstnøgler!C191 -> Håndtering af affaldsprodukt | D16: Stål | E16: =Tekstnøgler!C832 -> Affaldstype | F16: Stål og jern | G16: =Tekstnøgler!C723 -> Affaldshåndtering | H16: =Tekstnøgler!C933 -> Genanvendelse | K16: 8 | M16: =Tekstnøgler!C280 -> Ton | N16: =Tekstnøgler!C544 -> Ikke relevant | O16: =Tekstnøgler!C544 -> Ikke relevant | P16: 0 | Q16: 0 | R16: -21.232909 | T16: 2021 | U16: DK
A17: =Tekstnøgler!C377 -> Solgte produkter | B17: =Tekstnøgler!C573 -> End-of-life behandling | C17: =Tekstnøgler!C191 -> Håndtering af affaldsprodukt | D17: Træ | E17: =Tekstnøgler!C832 -> Affaldstype | F17: =Tekstnøgler!C979 -> Træ | G17: =Tekstnøgler!C723 -> Affaldshåndtering | H17: =Tekstnøgler!C744 -> Genbrug | K17: 50 | M17: =Tekstnøgler!C280 -> Ton | N17: =Tekstnøgler!C544 -> Ikke relevant | O17: =Tekstnøgler!C544 -> Ikke relevant | P17: 0 | Q17: 0 | R17: -75.059 | T17: 2021 | U17: DK
A18: =Tekstnøgler!C375 -> Transport | B18: =Tekstnøgler!C563 -> Egne og leasede transportmidler | C18: =Tekstnøgler!C163 -> Egne og leasede transportmidler | D18: Kundemøder | E18: =Tekstnøgler!C545 -> Transportmiddel | F18: =Tekstnøgler!C928 -> Personbiler | G18: =Tekstnøgler!C546 -> Drivmiddel | H18: =Tekstnøgler!C768 -> Benzin | I18: =Tekstnøgler!C867 -> Biobrændstofsandel (%) | J18: - | K18: 50000 | M18: =Tekstnøgler!C1005 -> Km | N18: 7.9191354 | O18: 0 | P18: 2.1299865 | Q18: 10.049122 | R18: 0.5543102 | T18: 2021 | U18: DK
A19: =Tekstnøgler!C375 -> Transport | B19: =Tekstnøgler!C564 -> Medarbejdertransport | C19: =Tekstnøgler!C167 -> Pendling | D19: Pendling | E19: =Tekstnøgler!C545 -> Transportmiddel | F19: =Tekstnøgler!C928 -> Personbiler | G19: =Tekstnøgler!C546 -> Drivmiddel | H19: =Tekstnøgler!C768 -> Benzin | K19: 18000 | M19: =Tekstnøgler!C888 -> Person.km | N19: 0 | O19: 0 | P19: 3.6176839 | Q19: 3.6176839 | R19: 0.19955167 | T19: 2021 | U19: DK
A20: =Tekstnøgler!C375 -> Transport | B20: =Tekstnøgler!C566 -> Varetransport til kunde | C20: =Tekstnøgler!C176 -> Varetransport i fysiske enheder | D20: Varetransport til ku | E20: =Tekstnøgler!C545 -> Transportmiddel | F20: =Tekstnøgler!C934 -> Lastbiler | G20: =Tekstnøgler!C546 -> Drivmiddel | H20: =Tekstnøgler!C893 -> Diesel | K20: 4000000 | M20: =Tekstnøgler!C906 -> Ton.km | N20: 0 | O20: 0 | P20: 546.56 | Q20: 546.56 | R20: 29.962533 | T20: 2021 | U20: DK
A21: =Tekstnøgler!C375 -> Transport | B21: =Tekstnøgler!C565 -> Varetransport til virksomhed | C21: =Tekstnøgler!C172 -> Varetransport i fysiske enheder | D21: Transport til virk | E21: =Tekstnøgler!C545 -> Transportmiddel | F21: =Tekstnøgler!C934 -> Lastbiler | G21: =Tekstnøgler!C546 -> Drivmiddel | H21: =Tekstnøgler!C893 -> Diesel | K21: 1500000 | M21: =Tekstnøgler!C906 -> Ton.km | N21: 0 | O21: 0 | P21: 204.96 | Q21: 204.96 | R21: 11.23595 | T21: 2021 | U21: DK

Sheet Data (E-nøgletal)
B2: =Tekstnøgler!C29 -> Data (E-nøgletal) | E2: =Tekstnøgler!$C$2 -> <-- Gå til forsiden
A4: =Tekstnøgler!C506 -> Hovedkategori | B4: =Tekstnøgler!C507 -> Kategori | C4: =Tekstnøgler!C509 -> Beskrivelse | D4: =Tekstnøgler!C530 -> Titel | E4: =Tekstnøgler!C516 -> Mængde | F4: =Tekstnøgler!C518 -> Enhed
A5: =Tekstnøgler!C576 -> ESG | B5: =Tekstnøgler!C577 -> E-Nøgletal | D5: =Tekstnøgler!C247 -> CO₂e-udledning inden for scope 1 | E5: 443.36484 | F5: =Tekstnøgler!$C$263 -> Ton CO₂e
A6: =Tekstnøgler!C576 -> ESG | B6: =Tekstnøgler!C577 -> E-Nøgletal | D6: =Tekstnøgler!C248 -> CO₂e-udledning inden for scope 2 | E6: 1851.795 | F6: =Tekstnøgler!$C$263 -> Ton CO₂e
A7: =Tekstnøgler!C576 -> ESG | B7: =Tekstnøgler!C577 -> E-Nøgletal | D7: =Tekstnøgler!C250 -> Samlet CO₂e-udledning (Scope 1 og 2) | E7: 2295.1598 | F7: =Tekstnøgler!$C$263 -> Ton CO₂e
A8: =Tekstnøgler!C576 -> ESG | B8: =Tekstnøgler!C577 -> E-Nøgletal | D8: =Tekstnøgler!C253 -> CO₂ intensitet (CO₂e-udledning for scope 1 og 2 ift. nettoomsætning) | E8: 99.789558 | F8: =Tekstnøgler!C264 -> Ton CO₂e / mio. DKK
A9: =Tekstnøgler!C576 -> ESG | B9: =Tekstnøgler!C577 -> E-Nøgletal | D9: =Tekstnøgler!C249 -> CO₂e-udledning inden for scope 3 | E9: 7935.4487 | F9: =Tekstnøgler!$C$263 -> Ton CO₂e
A10: =Tekstnøgler!C576 -> ESG | B10: =Tekstnøgler!C577 -> E-Nøgletal | D10: =Tekstnøgler!C251 -> Samlet CO₂e-udledning (Scope 1, 2 og 3) | E10: 10230.609 | F10: =Tekstnøgler!$C$263 -> Ton CO₂e
A11: =Tekstnøgler!C576 -> ESG | B11: =Tekstnøgler!C577 -> E-Nøgletal | D11: =Tekstnøgler!C252 -> CO₂ intensitet (Samlet CO₂e-udledning ift. nettoomsætning) | E11: 444.80907 | F11: =Tekstnøgler!C264 -> Ton CO₂e / mio. DKK
A12: =Tekstnøgler!C576 -> ESG | B12: =Tekstnøgler!C577 -> E-Nøgletal | D12: =Tekstnøgler!C254 -> Energiforbrug: Fossile kilder | E12: 4621.2243 | F12: =Tekstnøgler!$C$289 -> MWh
A13: =Tekstnøgler!C576 -> ESG | B13: =Tekstnøgler!C577 -> E-Nøgletal | D13: =Tekstnøgler!C255 -> Energiforbrug: Nukleare kilder | E13: 1389.2904 | F13: =Tekstnøgler!$C$289 -> MWh
A14: =Tekstnøgler!C576 -> ESG | B14: =Tekstnøgler!C577 -> E-Nøgletal | D14: =Tekstnøgler!C256 -> Energiforbrug: Vedvarende kilder | E14: 479.31625 | F14: =Tekstnøgler!$C$289 -> MWh
A15: =Tekstnøgler!C576 -> ESG | B15: =Tekstnøgler!C577 -> E-Nøgletal | D15: =Tekstnøgler!C257 -> Samlet energiforbrug | E15: 6489.831 | F15: =Tekstnøgler!$C$289 -> MWh
A16: =Tekstnøgler!C576 -> ESG | B16: =Tekstnøgler!C577 -> E-Nøgletal | D16: =Tekstnøgler!C260 -> Samlet vandforbrug | E16: 2000 | F16: =Tekstnøgler!C290 -> m3
A17: =Tekstnøgler!$C$576 -> ESG | B17: =Tekstnøgler!$C$577 -> E-Nøgletal | D17: =Tekstnøgler!C292 -> Samlet mængde affald | E17: 360 | F17: =Tekstnøgler!$C$280 -> Ton
A18: =Tekstnøgler!$C$576 -> ESG | B18: =Tekstnøgler!$C$577 -> E-Nøgletal | D18: =Tekstnøgler!C261 -> Andel af farligt affald (Mængde af farligt affald ift. total mængde affald) | E18: =Tekstnøgler!C269 -> (ikke angivet) | F18: =Tekstnøgler!C267 -> Pct. (%)
A19: =Tekstnøgler!$C$576 -> ESG | B19: =Tekstnøgler!$C$577 -> E-Nøgletal | D19: =Tekstnøgler!C262 -> Andel affald sendt til genanvendelse og genbrug (Mængde af genanvendt affald ift. total mængde affald) | E19: 72.222222 | F19: =Tekstnøgler!C267 -> Pct. (%)
A20: =Tekstnøgler!$C$576 -> ESG | B20: =Tekstnøgler!$C$577 -> E-Nøgletal | D20: =_xlfn.CONCAT(Tekstnøgler!C285," ",Tekstnøgler!C293) -> Vedvarende Elektricitet | E20: 1819.6129 | F20: =Tekstnøgler!$C$289 -> MWh
A21: =Tekstnøgler!$C$576 -> ESG | B21: =Tekstnøgler!$C$577 -> E-Nøgletal | D21: =_xlfn.CONCAT(Tekstnøgler!C286," ",Tekstnøgler!C293) -> Ikke vedvarende Elektricitet | E21: 2680.3871 | F21: =Tekstnøgler!$C$289 -> MWh
A22: =Tekstnøgler!$C$576 -> ESG | B22: =Tekstnøgler!$C$577 -> E-Nøgletal | D22: =_xlfn.CONCAT(Tekstnøgler!C285," ",Tekstnøgler!C294) -> Vedvarende Brændsler | E22: 48.993722 | F22: =Tekstnøgler!$C$289 -> MWh
A23: =Tekstnøgler!$C$576 -> ESG | B23: =Tekstnøgler!$C$577 -> E-Nøgletal | D23: =_xlfn.CONCAT(Tekstnøgler!C286," ",Tekstnøgler!C294) -> Ikke vedvarende Brændsler | E23: 1940.8372 | F23: =Tekstnøgler!$C$289 -> MWh
A24: =Tekstnøgler!$C$576 -> ESG | B24: =Tekstnøgler!$C$577 -> E-Nøgletal | D24: =_xlfn.CONCAT(Tekstnøgler!C285," ",Tekstnøgler!C295) -> Vedvarende Fjernvarme | E24: =Tekstnøgler!C269 -> (ikke angivet) | F24: =Tekstnøgler!$C$289 -> MWh
A25: =Tekstnøgler!$C$576 -> ESG | B25: =Tekstnøgler!$C$577 -> E-Nøgletal | D25: =_xlfn.CONCAT(Tekstnøgler!C286," ",Tekstnøgler!C295) -> Ikke vedvarende Fjernvarme | E25: =Tekstnøgler!C269 -> (ikke angivet) | F25: =Tekstnøgler!$C$289 -> MWh
A26: =Tekstnøgler!C576 -> ESG | B26: =Tekstnøgler!C578 -> Parameter | C26: =Tekstnøgler!C579 -> Brugt til beregning af E-nøgletal | D26: =Tekstnøgler!C273 -> Nettoomsætning | E26: 23 | F26: =Tekstnøgler!C278 -> mio. DKK
A27: =Tekstnøgler!C576 -> ESG | B27: =Tekstnøgler!C578 -> Parameter | C27: =Tekstnøgler!C579 -> Brugt til beregning af E-nøgletal | D27: =Tekstnøgler!C274 -> Vedvarende energiforbrug | E27: 479.31625 | F27: =Tekstnøgler!$C$289 -> MWh
A28: =Tekstnøgler!C576 -> ESG | B28: =Tekstnøgler!C578 -> Parameter | C28: =Tekstnøgler!C579 -> Brugt til beregning af E-nøgletal | D28: =Tekstnøgler!C275 -> Total mængde af affald | E28: 360 | F28: =Tekstnøgler!$C$280 -> Ton
A29: =Tekstnøgler!C576 -> ESG | B29: =Tekstnøgler!C578 -> Parameter | C29: =Tekstnøgler!C579 -> Brugt til beregning af E-nøgletal | D29: =Tekstnøgler!C276 -> Mængde af farligt affald | E29: =Tekstnøgler!C269 -> (ikke angivet) | F29: =Tekstnøgler!$C$280 -> Ton
A30: =Tekstnøgler!C576 -> ESG | B30: =Tekstnøgler!C578 -> Parameter | C30: =Tekstnøgler!C579 -> Brugt til beregning af E-nøgletal | D30: =Tekstnøgler!C277 -> Mængde af genanvendt affald | E30: 260 | F30: =Tekstnøgler!$C$280 -> Ton

Sheet Til udviklerne
B2: Til udviklerne | N2: ß Gå til forside
C5: = | D5: Cellen skal udfyldes med data og have en HVID baggrund.
C7: = | D7: Cellen skal ydfyldes og have en LYSEGRÅ baggrund.
B9: Ny | C9: = | D9: Denne række er ny ift. den gamle excel-ark fra før 15. november.
B11: Skjult række | C11: = | D11: Denne række skal skjules i den skabelon der downloades.
C13: = | D13: Kontrol er godkendt (Typisk "0,00" betyder at to sum er skulle værelige ER lige).
C15: = | D15: Fejldetekstion har fundet en fejl i en input-celle som giver forekerte resultater eller gør en beregning umuligt (fx dividere med "0").
B18: Sprog | E18: FEJL SKAL SKRIVES I BEGGE SPROG OG HAVE EN TEXT_NØGLE
B20: Dansk
B21: English
B24: Kontrol
B26: Følgerne resultater skal give "0,00". Hvis ikke tyder det på at der er en fejl i en ark (typisk) en sum der ikke matcher en anden sum.
B28: Stamdata
B29: Slutår og startår skal være ens | F29: =YEAR(Stamdata!B14)-YEAR(Stamdata!B17) -> 0
B32: Kontrol af at hoved- og delresultater er ens
B34: Scope 1+2+3 | F34: =Hovedresultater!D29-Delresultater!D98 -> 0
B35: Scope 1+2+3 (GHG) | F35: ='Hovedresultater (GHG)'!D25-'Delresultater (GHG)'!G98 -> 0
B36: Scope 1+2+3 (hovedresultater vs GHG) | F36: =Hovedresultater!D29-'Delresultater (GHG)'!G98 -> 0
B39: Kontrol af alle andel
B41: ANDEL | F41: REGEL | I41: Kontrol
B42: Andel af Scopes 1+2+3 - Hovedresultater | F42: Skal være 100% | I42: =Hovedresultater!E29-1 -> 0
B43: Andel af Scopes 1+2+3 - Delresultater | F43: Skal være 100% | I43: =Delresultater!E98-1 -> 0
B44: Andel af scopes - Hovedresultater (GHG)) | F44: Skal være 100% | I44: ='Hovedresultater (GHG)'!E25-1 -> 0
B46: Vedvarende energiandel | F46: Skal være <=100% | I46: ='E-nøgletal (ESG)'!#REF! -> #REF!
B47: Andel af farligt affald | F47: Skal være <=100% | I47: ='E-nøgletal (ESG)'!#REF! -> #REF!
B48: Andel af genanvendt affald | F48: Skal være <=100% | I48: ='E-nøgletal (ESG)'!#REF! -> #REF!
B51: Fremskrivning - Hovedresultater
B53: Det tal der er slået op for alle scopes for start/slut år er ens med summen af de tal der er slået op for start/slutår:
B55: Scope 1+2+3 for Basisår: | E55: ='Fremskrivning - Hovedresultater'!D28-LOOKUP('Fremskrivning - Hovedresultater'!C11,'Fremskrivning - Delresultater'!D15:X15,'Fremskrivning - Delresultater'!D19:X19) -> 0 | G55: Scope 1+2+3 for Slutår: | J55: ='Fremskrivning - Hovedresultater'!E28-LOOKUP('Fremskrivning - Hovedresultater'!D11,'Fremskrivning - Delresultater'!D15:X15,'Fremskrivning - Delresultater'!D19:X19) -> 0
B57: Resultater for sum af delresultater er ens med resultater for sum af scopes (for hvert år)
B58: År | C58: 2015 | D58: 2016 | E58: 2017 | F58: 2018 | G58: 2019 | H58: 2020 | I58: 2021 | J58: 2022 | K58: 2023 | L58: 2024 | M58: 2025 | N58: 2026 | O58: 2027 | P58: 2028 | Q58: 2029 | R58: 2030 | S58: 2031 | T58: 2032 | U58: 2033 | V58: 2034 | W58: 2035
B59: Kontrol | C59: ='Fremskrivning - Delresultater'!D19-'Fremskrivning - Delresultater'!G109 -> 0 | D59: ='Fremskrivning - Delresultater'!E19-'Fremskrivning - Delresultater'!K109 -> 0 | E59: ='Fremskrivning - Delresultater'!F19-'Fremskrivning - Delresultater'!O109 -> 0 | F59: ='Fremskrivning - Delresultater'!G19-'Fremskrivning - Delresultater'!S109 -> 0 | G59: ='Fremskrivning - Delresultater'!H19-'Fremskrivning - Delresultater'!W109 -> 0 | H59: ='Fremskrivning - Delresultater'!I19-'Fremskrivning - Delresultater'!AA109 -> 0 | I59: ='Fremskrivning - Delresultater'!J19-'Fremskrivning - Delresultater'!AE109 -> 0 | J59: ='Fremskrivning - Delresultater'!K19-'Fremskrivning - Delresultater'!AI109 -> 0 | K59: ='Fremskrivning - Delresultater'!L19-'Fremskrivning - Delresultater'!AM109 -> 0 | L59: ='Fremskrivning - Delresultater'!M19-'Fremskrivning - Delresultater'!AQ109 -> 0 | M59: ='Fremskrivning - Delresultater'!N19-'Fremskrivning - Delresultater'!AU109 -> 0 | N59: ='Fremskrivning - Delresultater'!O19-'Fremskrivning - Delresultater'!AY109 -> 0 | O59: ='Fremskrivning - Delresultater'!P19-'Fremskrivning - Delresultater'!BC109 -> 0 | P59: ='Fremskrivning - Delresultater'!Q19-'Fremskrivning - Delresultater'!BG109 -> 0 | Q59: ='Fremskrivning - Delresultater'!R19-'Fremskrivning - Delresultater'!BK109 -> 0 | R59: ='Fremskrivning - Delresultater'!S19-'Fremskrivning - Delresultater'!BO109 -> 0 | S59: ='Fremskrivning - Delresultater'!T19-'Fremskrivning - Delresultater'!BS109 -> 0 | T59: ='Fremskrivning - Delresultater'!U19-'Fremskrivning - Delresultater'!BW109 -> 0 | U59: ='Fremskrivning - Delresultater'!V19-'Fremskrivning - Delresultater'!CA109 -> 0 | V59: ='Fremskrivning - Delresultater'!W19-'Fremskrivning - Delresultater'!CE109 -> 0 | W59: ='Fremskrivning - Delresultater'!X19-'Fremskrivning - Delresultater'!CI109 -> 0
B62: Reduktionsmålsætninger
B64: Målår for reduktionsmålsætning (scope 1+2) skal ikke være større end maks(2030,Startår+10) | K64: =MAX(2030,'Fremskrivning - Hovedresultater'!C11+10)-Reduktionsmålsætning!D15 -> 0 | L64: færre år en maks
B65: Målår for reduktionsmålsætning (scope 3) skal ikke være større end maks(2030,Startår+10) | K65: =MAX(2030,'Fremskrivning - Hovedresultater'!C11+10)-Reduktionsmålsætning!D69 -> 0 | L65: færre år en maks
B66: Målår for Langsigtet net zero målsætning skal ikke være større end 2050 | K66: =2050-Reduktionsmålsætning!D124 -> 0 | L66: færre år en maks
B68: Målsætning for scope 1+2 må ikke være over 100% | K68: =1-Reduktionsmålsætning!D16 -> 0.35 | L68: færre % en maks(100%)
B69: Målsætning for scope 3 må ikke være over 100% | K69: =1-Reduktionsmålsætning!D70 -> 0.35 | L69: færre % en maks(100%)
B70: Langsigtet net zero målsætning må ikke være over 100% | K70: =1-Reduktionsmålsætning!D125 -> 0.1 | L70: færre % en maks(100%)
B73: Yderligere test af inputdata:
B75: Den test handler om at tjekke at der ikke opstår fejl i nogle beregninger, hvis én af inputcellerne (blå baggrund) er tom.
B77: SIDER | G77: INPUT TEST (Hvad) | I77: HÅND-TEST/resultat | M77: Automatisk fejldetektion / Kommentar
B78: Generelle oplysninger om beregningen
B79: Forside | G79: (Ikke relevant)
B80: Stamdata | G80: JA (dato, nøgletal) | I80: Start dato mangler = Fremskriv. fejler | M80: =IF(OR(ISBLANK(Stamdata!B14),ISTEXT(Stamdata!B14)),"Se Start dato under stamdata mangler eller bruger ikke format DATO(yyy,mm,dd)","Fejlbeskeden installeret på siderne Stamdata og Fremskrivnings - Hovedresultater. Bør ikke fejle, da dato er obligatorisk, men format skal være korrekt.") -> Fejlbeskeden installeret på siderne Stamdata og Fremskrivnings - Hovedresultater. Bør ikke fejle, da dato er obligatorisk, men format skal være korrekt.
B81: Kontaktoplysninger | G81: (Ikke relevant)
B83: Resultater
B84: Hovedresultater | G84: JA (metodevalg) | I84: Ingen fejl [23.11.2023] | M84: Metodevalg under Hovedresultater bruges til at vise det samme på de andre resultatsider.
B85: Delresultater | G85: (Ikke relevant)
B86: Hovedresultater (GHG) | G86: (Ikke relevant)
B87: Delresultater (GHG) | G87: JA (alle) | I87: Ingen fejl [23.11.2023] | M87: =IF(OR(SUM('Delresultater (GHG)'!D98:E98)=0,'Delresultater (GHG)'!F98=0),"Enten er summen af scopes 1 og 2 eller scope 3 lige med 0 tons.","Både Scopes 1+2 og scope 3 har en værdier over 0 ton.") -> Både Scopes 1+2 og scope 3 har en værdier over 0 ton.
B88: E-nøgletal (ESG) | G88: JA (alle) | I88: Ingen fejl [23.11.2023] | M88: =IF(OR('E-nøgletal (ESG)'!E69>'E-nøgletal (ESG)'!E68,'E-nøgletal (ESG)'!E70>'E-nøgletal (ESG)'!E68),"Mængde af farligt og/eller genanvendt affald er større end den total mængde af affald","Både mængde af farligt og genavnvendt affald er mindre eller lige med den total mængde affald.") -> Mængde af farligt og/eller genanvendt affald er større end den total mængde af affald
B89: Scope 3 kategorier | G89: JA (alle) | I89: Ingen fejl [23.11.2023] | M89: =IF('Scope 3 kategorier'!E37>'Delresultater (GHG)'!F98,"Summen af scope 3 kategorier udledninger er større end summen af alle scope 3 udledninger.","")
B90: Højeste udledningskategorier | G90: JA (alle) | I90: Ingen fejl [23.11.2023] | M90: =IF(OR('Største udledningsposter'!E61>'Delresultater (GHG)'!D98,'Største udledningsposter'!F61>'Delresultater (GHG)'!E98,'Største udledningsposter'!G61>'Delresultater (GHG)'!F98),"En af scopes for de 30 største poster er større end summen af alle poster for den samme scope","")
B92: Fremskrivning & Reduktionsmålsætninger
B93: Fremskrivning - Hovedresultater | G93: JA (alle) | I93: Ingen fejl [23.11.2023] | M93: =IF(OR('Fremskrivning - Hovedresultater'!D11<='Fremskrivning - Hovedresultater'!C11,'Fremskrivning - Hovedresultater'!D11<2016,'Fremskrivning - Hovedresultater'!D11>MAX(2030,'Fremskrivning - Hovedresultater'!C11+10)),"Slutår er enten mindre (eller lige) med startår eller større end MAKS(2030,startår+10), og det må den ikke","Slutår er mellem startår +1 og MAKS(2030,Startår+10).") -> Slutår er mellem startår +1 og MAKS(2030,Startår+10).
B94: Fremskrivning - Delresultater | G94: JA (alle) | I94: Ingen fejl [23.11.2023] | M94: =IF(OR('Fremskrivning - Delresultater'!K109=0,'Fremskrivning - Delresultater'!O109=0,'Fremskrivning - Delresultater'!S109=0,'Fremskrivning - Delresultater'!W109=0,'Fremskrivning - Delresultater'!AA109=0,'Fremskrivning - Delresultater'!AE109=0,'Fremskrivning - Delresultater'!AI109=0,'Fremskrivning - Delresultater'!AI109=0,'Fremskrivning - Delresultater'!AM109=0,'Fremskrivning - Delresultater'!AQ109=0,'Fremskrivning - Delresultater'!AU109=0,'Fremskrivning - Delresultater'!AY109=0,'Fremskrivning - Delresultater'!BC109=0,'Fremskrivning - Delresultater'!BG109=0,'Fremskrivning - Delresultater'!BK109=0,'Fremskrivning - Delresultater'!BO109=0,'Fremskrivning - Delresultater'!BS109=0,'Fremskrivning - Delresultater'!BW109=0,'Fremskrivning - Delresultater'!CA109=0,'Fremskrivning - Delresultater'!CE109=0,'Fremskrivning - Delresultater'!CI109=0),"Scopes er lige med nul i en af de fremskrevne år","Scopes for alle år er IKKE lige med nul for nogle af de fremskrevne år.") -> Scopes for alle år er IKKE lige med nul for nogle af de fremskrevne år.
B95: Reduktionsmålsætninger
B97: Data
B98: Emissionsfaktorer
B99: Egne Emissionsfaktorer
B100: Fremskrevne emissionsfaktorer
B101: Data (alle poster)
B102: Data (E-nøgletal)

Sheet Tekstnøgler
A1: Tekstnøgle | C1: Vist tekst | E1: Dansk | G1: Engelsk | I1: Side | J1: Celle | K1: Cell-content | M1: Reference-kontrol
A2: excel.go-to-front-page | C2: =IF(Forside!$D$12="Dansk",Tekstnøgler!E2,Tekstnøgler!G2) -> <-- Gå til forsiden | E2: <-- Gå til forsiden | G2: <-- Go to the front page | I2: Stamdata | J2: I2 | K2: {=INDIRECT("'"&I2&"'!"&J2)} -> <-- Gå til forsiden | M2: =IF(C2=K2,"OK","Reference fejl") -> OK
A3: excel.frontpage.title.download-results | C3: =IF(Forside!$D$12="Dansk",Tekstnøgler!E3,Tekstnøgler!G3) -> Download af resultater | E3: Download af resultater | G3: Download the results | I3: Forside | J3: B8 | K3: {=INDIRECT("'"&I3&"'!"&J3)} -> Download af resultater | M3: =IF(C3=K3,"OK","Reference fejl") -> OK
A4: excel.frontpage.text | C4: =IF(Forside!$D$12="Dansk",Tekstnøgler!E4,Tekstnøgler!G4) -> I dette Excel regneark, kan du finde alle resultater som du kunne se på Klimakompasset for den beregning du har valgt (se navn på beregning ovenfor). Herunder kan du se en liste af de resultater og data, du har adgang til. Da navne på individuelle ark i bunden af Excel-arket ikke ændres, når du vælger mellem dansk og engelsk sprog, er det skrevet ind, hvilke ark de danske titler referer til. | E4: I dette Excel regneark, kan du finde alle resultater som du kunne se på Klimakompasset for den beregning du har valgt (se navn på beregning ovenfor). Herunder kan du se en liste af de resultater og data, du har adgang til. Da navne på individuelle ark i bunden af Excel-arket ikke ændres, når du vælger mellem dansk og engelsk sprog, er det skrevet ind, hvilke ark de danske titler referer til. | G4: In this Excel spreadsheet, you can find all the results that you could see on the Climate Compass for the calculation you have chosen (see name of calculation above). Below you can see a list of the results and data you have access to. Since the title of individual sheets remain in Danish even though you choose to have the Excel sheet in English, the column on the right show which Danish-titled sheets the links refer to. | I4: Forside | J4: B10 | K4: {=INDIRECT("'"&I4&"'!"&J4)} -> I dette Excel regneark, kan du finde alle resultater som du kunne se på Klimakompasset for den beregning du har valgt (se navn på beregning ovenfor). Herunder kan du se en liste af de resultater og data, du har adgang til. Da navne på individuelle ark i bunden af Excel-arket ikke ændres, når du vælger mellem dansk og engelsk sprog, er det skrevet ind, hvilke ark de danske titler referer til. | M4: =IF(C4=K4,"OK","reference fejl") -> OK
A5: excel.choose-language | C5: =IF(Forside!$D$12="Dansk",Tekstnøgler!E5,Tekstnøgler!G5) -> Vælg af sprog | E5: Vælg af sprog | G5: Choose a language | I5: Forside | J5: B12 | K5: {=INDIRECT("'"&I5&"'!"&J5)} -> Vælg af sprog | M5: =IF(C5=K5,"OK","Reference fejl") -> OK
A6: excel.click-cell | C6: =IF(Forside!$D$12="Dansk",Tekstnøgler!E6,Tekstnøgler!G6) -> <-- klik på cellen | E6: <-- klik på cellen | G6: <-- Click in the cell | I6: Forside | J6: E12 | K6: {=INDIRECT("'"&I6&"'!"&J6)} -> <-- klik på cellen | M6: =IF(C6=K6,"OK","Reference fejl") -> OK
A7: excel.frontpage.toc | C7: =IF(Forside!$D$12="Dansk",Tekstnøgler!E7,Tekstnøgler!G7) -> Indholdsfortegnelse | E7: Indholdsfortegnelse | G7: Table of Contents | I7: Forside | J7: B15 | K7: {=INDIRECT("'"&I7&"'!"&J7)} -> Indholdsfortegnelse | M7: =IF(C7=K7,"OK","Reference fejl") -> OK
A8: excel.frontpage.title.general-information | C8: =IF(Forside!$D$12="Dansk",Tekstnøgler!E8,Tekstnøgler!G8) -> Generelle oplysninger om beregningen | E8: Generelle oplysninger om beregningen | G8: General information about the calculation | I8: Forside | J8: B17 | K8: {=INDIRECT("'"&I8&"'!"&J8)} -> Generelle oplysninger om beregningen | M8: =IF(C8=K8,"OK","Reference fejl") -> OK
A9: excel.sheet-name.front-page | C9: =IF(Forside!$D$12="Dansk",Tekstnøgler!E9,Tekstnøgler!G9) -> Forside | E9: Forside | G9: Front page | I9: Forside | J9: C18 | K9: {=INDIRECT("'"&I9&"'!"&J9)} -> Forside | M9: =IF(C9=K9,"OK","Reference fejl") -> OK
A10: excel.sheet-name.master-data | C10: =IF(Forside!$D$12="Dansk",Tekstnøgler!E10,Tekstnøgler!G10) -> Stamdata | E10: Stamdata | G10: Master data | I10: Forside | J10: C19 | K10: {=INDIRECT("'"&I10&"'!"&J10)} -> Stamdata | M10: =IF(C10=K10,"OK","Reference fejl") -> OK
A11: excel.sheet-name.contact-information | C11: =IF(Forside!$D$12="Dansk",Tekstnøgler!E11,Tekstnøgler!G11) -> Kontaktoplysninger | E11: Kontaktoplysninger | G11: Contact Information | I11: Forside | J11: C20 | K11: {=INDIRECT("'"&I11&"'!"&J11)} -> Kontaktoplysninger | M11: =IF(C11=K11,"OK","Reference fejl") -> OK
A12: excel.frontpage.title.results | C12: =IF(Forside!$D$12="Dansk",Tekstnøgler!E12,Tekstnøgler!G12) -> Resultater | E12: Resultater | G12: Results | I12: Forside | J12: B22 | K12: {=INDIRECT("'"&I12&"'!"&J12)} -> Resultater | M12: =IF(C12=K12,"OK","Reference fejl") -> OK
A13: excel.sheet-name.main-results | C13: =IF(Forside!$D$12="Dansk",Tekstnøgler!E13,Tekstnøgler!G13) -> Hovedresultater | E13: Hovedresultater | G13: Main results | I13: Forside | J13: C23 | K13: {=INDIRECT("'"&I13&"'!"&J13)} -> Hovedresultater | M13: =IF(C13=K13,"OK","Reference fejl") -> OK
A14: excel.sheet-name.partial-results | C14: =IF(Forside!$D$12="Dansk",Tekstnøgler!E14,Tekstnøgler!G14) -> Delresultater | E14: Delresultater | G14: Partial results | I14: Forside | J14: C24 | K14: {=INDIRECT("'"&I14&"'!"&J14)} -> Delresultater | M14: =IF(C14=K14,"OK","Reference fejl") -> OK
A15: excel.sheet-name.main-results-ghg | C15: =IF(Forside!$D$12="Dansk",Tekstnøgler!E15,Tekstnøgler!G15) -> Hovedresultater (GHG) | E15: Hovedresultater (GHG) | G15: Main results (GHG) | I15: Forside | J15: C25 | K15: {=INDIRECT("'"&I15&"'!"&J15)} -> Hovedresultater (GHG) | M15: =IF(C15=K15,"OK","Reference fejl") -> OK
A16: excel.sheet-name.partial-results-ghg | C16: =IF(Forside!$D$12="Dansk",Tekstnøgler!E16,Tekstnøgler!G16) -> Delresultater (GHG) | E16: Delresultater (GHG) | G16: Partial results (GHG) | I16: Forside | J16: C26 | K16: {=INDIRECT("'"&I16&"'!"&J16)} -> Delresultater (GHG) | M16: =IF(C16=K16,"OK","Reference fejl") -> OK
... A34: calculation.text.result-for | C34: =IF(Forside!$D$12="Dansk",Tekstnøgler!E34,Tekstnøgler!G34) -> Resultat for | E34: Resultat for | G34: Result for | I34: Forside | J34: B5 | K34: {=INDIRECT("'"&I34&"'!"&J34)} -> Resultat for 0 (År) - Tiltagscase | M34: =IF(C34=K34,"OK","Reference fejl") -> Reference fejl
C35: =IF(Forside!$D$12="Dansk",Tekstnøgler!E35,Tekstnøgler!G35) -> 0 | I35: Forside | K35: {=INDIRECT("'"&I35&"'!"&J35)} -> #REF! | M35: =IF(C35=K35,"OK","Reference fejl") -> #REF! | N35: Tekstnøglen for beregningens navn??? | O35: NA
C36: =IF(Forside!$D$12="Dansk",Tekstnøgler!E36,Tekstnøgler!G36) -> 0 | I36: Forside | K36: {=INDIRECT("'"&I36&"'!"&J36)} -> #REF! | M36: =IF(C36=K36,"OK","Reference fejl") -> #REF! | N36: Tekstnøglen for summen af scope 1+2+3??? | O36: NA
A37: calculation.masterdata.title | C37: =IF(Forside!$D$12="Dansk",Tekstnøgler!E37,Tekstnøgler!G37) -> Stamdata | E37: Stamdata | G37: Master data | I37: Stamdata | J37: B2 | K37: {=INDIRECT("'"&I37&"'!"&J37)} -> Stamdata | M37: =IF(C37=K37,"OK","Reference fejl") -> OK
A38: calculation.masterdata.text.about-calculation | C38: =IF(Forside!$D$12="Dansk",Tekstnøgler!E38,Tekstnøgler!G38) -> Om beregningen | E38: Om beregningen | G38: About the calculation | I38: Stamdata | J38: B5 | K38: {=INDIRECT("'"&I38&"'!"&J38)} -> Om beregningen | M38: =IF(C38=K38,"OK","Reference fejl") -> OK
A39: calculation.masterdata.text.calculation-name | C39: =IF(Forside!$D$12="Dansk",Tekstnøgler!E39,Tekstnøgler!G39) -> Navn på beregning | E39: Navn på beregning | G39: Name of calculation | I39: Stamdata | J39: B7 | K39: {=INDIRECT("'"&I39&"'!"&J39)} -> Navn på beregning | M39: =IF(C39=K39,"OK","Reference fejl") -> OK
A40: calculation.masterdata.text.calculation-purpose | C40: =IF(Forside!$D$12="Dansk",Tekstnøgler!E40,Tekstnøgler!G40) -> Formål med beregningen | E40: Formål med beregningen | G40: Purpose of the calculation | I40: Stamdata | J40: B10 | K40: {=INDIRECT("'"&I40&"'!"&J40)} -> Formål med beregningen | M40: =IF(C40=K40,"OK","Reference fejl") -> OK
A41: purpose.purposeOption1 | C41: =IF(Forside!$D$12="Dansk",Tekstnøgler!E41,Tekstnøgler!G41) -> 1. Beregn klimaaftrykket for din virksomhed (CVR-nr. tilknyttet) | E41: 1. Beregn klimaaftrykket for din virksomhed (CVR-nr. tilknyttet) | G41: 1. Calculate climate footprint for your company (CVR number associated) | I41: Stamdata | J41: B11 | K41: {=INDIRECT("'"&I41&"'!"&J41)} -> 4. Beregn klimaaftrykket for din virksomhed (ingen krav om CVR nr.). | M41: =IF(C41=K41,"OK","Reference fejl") -> Reference fejl | N41: =IF(OR(M41="OK",M42="OK",M43="OK",M44="OK"),"OK (one is enough)","fejl") -> OK (one is enough)
A42: purpose.purposeOption2 | C42: =IF(Forside!$D$12="Dansk",Tekstnøgler!E42,Tekstnøgler!G42) -> 2. Beregn forskellige klimatiltag for din virksomhed (CVR-nr. tilknyttet) | E42: 2. Beregn forskellige klimatiltag for din virksomhed (CVR-nr. tilknyttet) | G42: 2. Calculate different climate measures for your company (CVR number associated) | I42: Stamdata | J42: B11 | K42: {=INDIRECT("'"&I42&"'!"&J42)} -> 4. Beregn klimaaftrykket for din virksomhed (ingen krav om CVR nr.). | M42: =IF(C42=K42,"OK","Reference fejl") -> Reference fejl | N42: =IF(OR(M41="OK",M42="OK",M43="OK",M44="OK"),"OK (one is enough)","fejl") -> OK (one is enough)
A43: purpose.purposeOption3 | C43: =IF(Forside!$D$12="Dansk",Tekstnøgler!E43,Tekstnøgler!G43) -> 3. Beregn en virksomheds klimaaftryk (fx hvis den er placeret i udlandet) | E43: 3. Beregn en virksomheds klimaaftryk (fx hvis den er placeret i udlandet) | G43: 3. Calculate a company’s climate footprint (no CVR number associated) | I43: Stamdata | J43: B11 | K43: {=INDIRECT("'"&I43&"'!"&J43)} -> 4. Beregn klimaaftrykket for din virksomhed (ingen krav om CVR nr.). | M43: =IF(C43=K43,"OK","Reference fejl") -> Reference fejl | N43: =IF(OR(M41="OK",M42="OK",M43="OK",M44="OK"),"OK (one is enough)","fejl") -> OK (one is enough)
A44: purpose.purposeOption4 | C44: =IF(Forside!$D$12="Dansk",Tekstnøgler!E44,Tekstnøgler!G44) -> 4. Beregn klimaaftrykket for din virksomhed (ingen krav om CVR nr.). | E44: 4. Beregn klimaaftrykket for din virksomhed (ingen krav om CVR nr.). | G44: 4. Calculate climate footprint of your company (registration number is optional). | I44: Stamdata | J44: B11 | K44: {=INDIRECT("'"&I44&"'!"&J44)} -> 4. Beregn klimaaftrykket for din virksomhed (ingen krav om CVR nr.). | M44: =IF(C44=K44,"OK","Reference fejl") -> OK | N44: =IF(OR(M41="OK",M42="OK",M43="OK",M44="OK"),"OK (one is enough)","fejl") -> OK (one is enough)
A45: calculation.masterdata.text.start-date | C45: =IF(Forside!$D$12="Dansk",Tekstnøgler!E45,Tekstnøgler!G45) -> Start dato - Klimaopgørelser laves typisk for et kalenderår | E45: Start dato - Klimaopgørelser laves typisk for et kalenderår | G45: Start date (dd, mm, yyyy) – Climate accounts are typically made for a calendar year | I45: Stamdata | J45: B13 | K45: {=INDIRECT("'"&I45&"'!"&J45)} -> Start dato - Klimaopgørelser laves typisk for et kalenderår | M45: =IF(C45=K45,"OK","Reference fejl") -> OK
A46: calculation.masterdata.text.end-date | C46: =IF(Forside!$D$12="Dansk",Tekstnøgler!E46,Tekstnøgler!G46) -> Slut dato | E46: Slut dato | G46: End date (dd, mm, yyyy) | I46: Stamdata | J46: B16 | K46: {=INDIRECT("'"&I46&"'!"&J46)} -> Slut dato | M46: =IF(C46=K46,"OK","Reference fejl") -> OK
A47: calculation.masterdata.text.calculation-note | C47: =IF(Forside!$D$12="Dansk",Tekstnøgler!E47,Tekstnøgler!G47) -> Kommentarer til beregningen | E47: Kommentarer til beregningen | G47: Comments on the calculation | I47: Stamdata | J47: B19 | K47: {=INDIRECT("'"&I47&"'!"&J47)} -> Kommentarer til beregningen | M47: =IF(C47=K47,"OK","Reference fejl") -> OK
A48: calculation.masterdata.text.your-company | C48: =IF(Forside!$D$12="Dansk",Tekstnøgler!E48,Tekstnøgler!G48) -> Din virksomhed | E48: Din virksomhed | G48: Your company | I48: Stamdata | J48: B24 | K48: {=INDIRECT("'"&I48&"'!"&J48)} -> Din virksomhed | M48: =IF(C48=K48,"OK","Reference fejl") -> OK
A49: calculation.masterdata.text.vat-no | C49: =IF(Forside!$D$12="Dansk",Tekstnøgler!E49,Tekstnøgler!G49) -> CVR | E49: CVR | G49: CVR | I49: Stamdata | J49: B26 | K49: {=INDIRECT("'"&I49&"'!"&J49)} -> CVR | M49: =IF(C49=K49,"OK","Reference fejl") -> OK
A50: calculation.masterdata.text.company-name | C50: =IF(Forside!$D$12="Dansk",Tekstnøgler!E50,Tekstnøgler!G50) -> Virksomhedens navn | E50: Virksomhedens navn | G50: Company name | I50: Stamdata | J50: B29 | K50: {=INDIRECT("'"&I50&"'!"&J50)} -> Virksomhedens navn | M50: =IF(C50=K50,"OK","Reference fejl") -> OK
A51: calculation.masterdata.text.company-calculation-relates | C51: =IF(Forside!$D$12="Dansk",Tekstnøgler!E51,Tekstnøgler!G51) -> Virksomhed som beregningen vedrører | E51: Virksomhed som beregningen vedrører | G51: Company to which the calculation relates | I51: Stamdata | J51: B34 | K51: {=INDIRECT("'"&I51&"'!"&J51)} -> Virksomhed som beregningen vedrører | M51: =IF(C51=K51,"OK","Reference fejl") -> OK
A52: calculation.masterdata.text.country | C52: =IF(Forside!$D$12="Dansk",Tekstnøgler!E52,Tekstnøgler!G52) -> Land | E52: Land | G52: Country | I52: Stamdata | J52: B36 | K52: {=INDIRECT("'"&I52&"'!"&J52)} -> Land | M52: =IF(C52=K52,"OK","Reference fejl") -> OK
A53: calculation.masterdata.text.p-number | C53: =IF(Forside!$D$12="Dansk",Tekstnøgler!E53,Tekstnøgler!G53) -> P-nummer | E53: P-nummer | G53: P number | I53: Stamdata | J53: B45 | K53: {=INDIRECT("'"&I53&"'!"&J53)} -> P-nummer | M53: =IF(C53=K53,"OK","Reference fejl") -> OK
A54: excel.or | C54: =IF(Forside!$D$12="Dansk",Tekstnøgler!E54,Tekstnøgler!G54) -> eller | E54: eller | G54: or | I54: Stamdata | J54: D34 | K54: {=INDIRECT("'"&I54&"'!"&J54)} -> 0 | M54: =IF(C54=K54,"OK","Reference fejl") -> Reference fejl
A55: calculation.masterdata.text.company-calculation-relates-foreign | C55: =IF(Forside!$D$12="Dansk",Tekstnøgler!E55,Tekstnøgler!G55) -> Udenlandske virksomhed som beregningen vedrører | E55: Udenlandske virksomhed som beregningen vedrører | G55: Foreign company to which the calculation relates | I55: Stamdata | J55: G34 | K55: {=INDIRECT("'"&I55&"'!"&J55)} -> 0 | M55: =IF(C55=K55,"OK","Reference fejl") -> Reference fejl
A56: calculation.masterdata.text.country | C56: =IF(Forside!$D$12="Dansk",Tekstnøgler!E56,Tekstnøgler!G56) -> Land | E56: Land | G56: Country | I56: Stamdata | J56: G36 | K56: {=INDIRECT("'"&I56&"'!"&J56)} -> 0 | M56: =IF(C56=K56,"OK","Reference fejl") -> Reference fejl
... A71: calculation.methodselection.text.method | C71: =IF(Forside!$D$12="Dansk",Tekstnøgler!E71,Tekstnøgler!G71) -> Metodevalg | E71: Metodevalg | G71: Method selection | I71: Hovedresultater | J71: C8 | K71: {=INDIRECT("'"&I71&"'!"&J71)} -> Metodevalg | M71: =IF(C71=K71,"OK","Reference fejl") -> OK
A72: calculation.methodselection.text.method.description | C72: =IF(Forside!$D$12="Dansk",Tekstnøgler!E72,Tekstnøgler!G72) -> Resultaterne baserer sig på en række metodiske valg, der er foretaget i forbindelse med beregningerne. I nedenstående tabel kan du se, hvorvidt Radiative Forcing Index (RFI) er medregnet i forbindelse med udledninger fra flytransport. At medregne (eller korrigere for) RFI betyder, at der er taget højde for, at CO₂e udledt højere oppe i atmosfæren har en større drivhuseffekt end CO₂e udledt ved landjorden. Tabellen viser også, om emissionsfaktoren for el baserer sig på det årlige gennemsnit for sammensætningen af produktionen af el (miljødeklaration), eller om der i emissionsfaktoren korrigeres for virksomheders køb af grønne certifikater, såkaldte oprindelsesgarantier (eldeklaration). | E72: Resultaterne baserer sig på en række metodiske valg, der er foretaget i forbindelse med beregningerne. I nedenstående tabel kan du se, hvorvidt Radiative Forcing Index (RFI) er medregnet i forbindelse med udledninger fra flytransport. At medregne (eller korrigere for) RFI betyder, at der er taget højde for, at CO₂e udledt højere oppe i atmosfæren har en større drivhuseffekt end CO₂e udledt ved landjorden. Tabellen viser også, om emissionsfaktoren for el baserer sig på det årlige gennemsnit for sammensætningen af produktionen af el (miljødeklaration), eller om der i emissionsfaktoren korrigeres for virksomheders køb af grønne certifikater, såkaldte oprindelsesgarantier (eldeklaration). | G72: The results are based on a number of methodological choices which are made in connection with the calculations. In the table below, you can see whether or not the Radiative Forcing Index (RFI) has been included in connection with emissions from air transport. Including (or correcting for) RFI means taking into account the fact that CO₂e emitted higher up in the atmosphere has a greater greenhouse effect than CO₂e emitted on the ground. The table also shows whether the emission factor for electricity is based on the annual average for the composition of electricity production (location-based approach ) or whether the emission factor corrects for the company’s purchase of green certificates, so-called guarantees of origin (market-based approach). | I72: Hovedresultater | J72: C10 | K72: {=INDIRECT("'"&I72&"'!"&J72)} -> Resultaterne baserer sig på en række metodiske valg, der er foretaget i forbindelse med beregningerne. I nedenstående tabel kan du se, hvorvidt Radiative Forcing Index (RFI) er medregnet i forbindelse med udledninger fra flytransport. At medregne (eller korrigere for) RFI betyder, at der er taget højde for, at CO₂e udledt højere oppe i atmosfæren har en større drivhuseffekt end CO₂e udledt ved landjorden. Tabellen viser også, om emissionsfaktoren for el baserer sig på det årlige gennemsnit for sammensætningen af produktionen af el (miljødeklaration), eller om der i emissionsfaktoren korrigeres for virksomheders køb af grønne certifikater, såkaldte oprindelsesgarantier (eldeklaration). | M72: =IF(C72=K72,"OK","Reference fejl") -> OK | O72: =ROW(A77) -> 77
A73: calculation.methodselection.text.method.table.emission-factor | C73: =IF(Forside!$D$12="Dansk",Tekstnøgler!E73,Tekstnøgler!G73) -> Emissionsfaktor | E73: Emissionsfaktor | G73: Emission factor | I73: Hovedresultater | J73: C12 | K73: {=INDIRECT("'"&I73&"'!"&J73)} -> Emissionsfaktor | M73: =IF(C73=K73,"OK","Reference fejl") -> OK
A74: calculation.methodselection.text.method | C74: =IF(Forside!$D$12="Dansk",Tekstnøgler!E74,Tekstnøgler!G74) -> Metodevalg | E74: Metodevalg | G74: Method selection | I74: Hovedresultater | J74: E12 | K74: {=INDIRECT("'"&I74&"'!"&J74)} -> Metodevalg | M74: =IF(C74=K74,"OK","Reference fejl") -> OK | O74: {=INDIRECT("C"&MATCH("coefficient-group.name.environmental-declaration",A:A))} -> Kg
A75: calculation.methodselection.text.method.choice-emission-factor-electricity | C75: =IF(Forside!$D$12="Dansk",Tekstnøgler!E75,Tekstnøgler!G75) -> Valg af emissionsfaktor for elektricitet | E75: Valg af emissionsfaktor for elektricitet | G75: Method for emission factors for electricity | I75: Hovedresultater | J75: C13 | K75: {=INDIRECT("'"&I75&"'!"&J75)} -> Valg af emissionsfaktor for elektricitet | M75: =IF(C75=K75,"OK","Reference fejl") -> OK
A76: calculation.methodselection.text.method.emission-factor-fly | C76: =IF(Forside!$D$12="Dansk",Tekstnøgler!E76,Tekstnøgler!G76) -> Emissionsfaktor for flytransport | E76: Emissionsfaktor for flytransport | G76: Declaration of emission factors for air transport | I76: Hovedresultater | J76: C14 | K76: {=INDIRECT("'"&I76&"'!"&J76)} -> Emissionsfaktor for flytransport | M76: =IF(C76=K76,"OK","Reference fejl") -> OK | O76: =LOOKUP("coefficient-group.name.environmental-declaration",A77:A80,C77:C80) -> Inkluder ikke RFI
A77: coefficient-group.name.environmental-declaration | C77: =IF(Forside!$D$12="Dansk",Tekstnøgler!E77,Tekstnøgler!G77) -> Miljødeklaration | E77: Miljødeklaration | G77: Location-based | O77: =LOOKUP("coefficient-group.name.environmental-declaration",Tekstnøgler!A:A,Tekstnøgler!C:C) -> Kg
A78: calculation.methodselection.text.method.include-rfi | C78: =IF(Forside!$D$12="Dansk",Tekstnøgler!E78,Tekstnøgler!G78) -> Inkluder RFI | E78: Inkluder RFI | G78: Includes RFI | O78: {=LOOKUP(2,1/SEARCH(A:A,"coefficient-group.name.environmental-declaration"),C:C)} -> 0 | Q78: https://www.youtube.com/watch?v=4l97D0A2wIw
A79: coefficient-group.name.electricity-declaration | C79: =IF(Forside!$D$12="Dansk",Tekstnøgler!E79,Tekstnøgler!G79) -> Eldeklaration | E79: Eldeklaration | G79: Market-based
A80: calculation.methodselection.text.method.exclude-rfi | C80: =IF(Forside!$D$12="Dansk",Tekstnøgler!E80,Tekstnøgler!G80) -> Inkluder ikke RFI | E80: Inkluder ikke RFI | G80: Excludes RFI
A81: calculation.mainresult.text.mainresult | C81: =IF(Forside!$D$12="Dansk",Tekstnøgler!E81,Tekstnøgler!G81) -> Hovedresultater | E81: Hovedresultater | G81: Main results | I81: Hovedresultater | J81: C17 | K81: {=INDIRECT("'"&I81&"'!"&J81)} -> Hovedresultater | M81: =IF(C81=K81,"OK","Reference fejl") -> OK
A82: calculation.mainresult.text.mainresult.description | C82: =IF(Forside!$D$12="Dansk",Tekstnøgler!E82,Tekstnøgler!G82) -> Virksomhedens samlede CO₂e-udledning er angivet i tabel 1. CO₂e-udledningen er angivet i ton CO₂-ækvivalenter, og tabellen viser udledningen fordelt på de forskellige hovedkategorier. Bemærk, at udenfor scopes ikke medregnes i klimaaftrykket ifølge GHG-protokollen, men kan oplyses særskilt. | E82: Virksomhedens samlede CO₂e-udledning er angivet i tabel 1. CO₂e-udledningen er angivet i ton CO₂-ækvivalenter, og tabellen viser udledningen fordelt på de forskellige hovedkategorier. Bemærk, at udenfor scopes ikke medregnes i klimaaftrykket ifølge GHG-protokollen, men kan oplyses særskilt. | G82: The company’s total CO₂e emissions are given in Table 1. CO₂e emissions are expressed in tonnes of CO₂ equivalents and the table shows the emissions divided across the various main categories. Note that emissions which are outside the scopes are not included in the climate footprint under the GHG Protocol but can be stated separately. | I82: Hovedresultater | J82: C19 | K82: {=INDIRECT("'"&I82&"'!"&J82)} -> Virksomhedens samlede CO₂e-udledning er angivet i tabel 1. CO₂e-udledningen er angivet i ton CO₂-ækvivalenter, og tabellen viser udledningen fordelt på de forskellige hovedkategorier. Bemærk, at udenfor scopes ikke medregnes i klimaaftrykket ifølge GHG-protokollen, men kan oplyses særskilt. | M82: =IF(C82=K82,"OK","Reference fejl") -> OK
A83: calculation.mainresult.text.mainresult.table1.title | C83: =IF(Forside!$D$12="Dansk",Tekstnøgler!E83,Tekstnøgler!G83) -> Tabel 1: Oversigt over virksomhedens CO₂e-udledninger | E83: Tabel 1: Oversigt over virksomhedens CO₂e-udledninger | G83: Table 1: Overview of the company's CO₂e emissions | I83: Hovedresultater | J83: C21 | K83: {=INDIRECT("'"&I83&"'!"&J83)} -> Tabel 1: Oversigt over virksomhedens CO₂e-udledninger | M83: =IF(C83=K83,"OK","Reference fejl") -> OK
A84: calculation.mainresult.text.mainresult.table1.maincategory | C84: =IF(Forside!$D$12="Dansk",Tekstnøgler!E84,Tekstnøgler!G84) -> Hovedkategori | E84: Hovedkategori | G84: Main category | I84: Hovedresultater | J84: C22 | K84: {=INDIRECT("'"&I84&"'!"&J84)} -> Hovedkategori | M84: =IF(C84=K84,"OK","Reference fejl") -> OK
A85: calculation.mainresult.text.mainresult.table1.emission-scope1-3 | C85: =IF(Forside!$D$12="Dansk",Tekstnøgler!E85,Tekstnøgler!G85) -> Udledning i ton CO₂e (scope 1+2+3) | E85: Udledning i ton CO₂e (scope 1+2+3) | G85: Emissions in tonnes of CO₂e (scope 1+2+3) | I85: Hovedresultater | J85: D22 | K85: {=INDIRECT("'"&I85&"'!"&J85)} -> Udledning i ton CO₂e (scope 1+2+3) | M85: =IF(C85=K85,"OK","Reference fejl") -> OK
A86: calculation.mainresult.text.mainresult.table1.share-emission-scope1-3 | C86: =IF(Forside!$D$12="Dansk",Tekstnøgler!E86,Tekstnøgler!G86) -> Andel af udledning (scope 1+2+3) | E86: Andel af udledning (scope 1+2+3) | G86: Share of emissions (Scopes 1+2+3) | I86: Hovedresultater | J86: E22 | K86: {=INDIRECT("'"&I86&"'!"&J86)} -> Andel af udledning (scope 1+2+3) | M86: =IF(C86=K86,"OK","Reference fejl") -> OK
A87: calculation.mainresult.text.mainresult.table1.emission-outsidescope | C87: =IF(Forside!$D$12="Dansk",Tekstnøgler!E87,Tekstnøgler!G87) -> Udledning i ton CO₂e (udenfor scopes) | E87: Udledning i ton CO₂e (udenfor scopes) | G87: Emissions in tonnes of CO₂e (outside of scopes) | I87: Hovedresultater | J87: F22 | K87: {=INDIRECT("'"&I87&"'!"&J87)} -> Udledning i ton CO₂e (udenfor scopes) | M87: =IF(C87=K87,"OK","Reference fejl") -> Reference fejl
A88: calculation.mainresult.text.mainresult.table1.emission-scope1-3-outside | C88: =IF(Forside!$D$12="Dansk",Tekstnøgler!E88,Tekstnøgler!G88) -> Udledning i ton CO₂e <br /> (scope 1+2+3 + udenfor scopes) | E88: Udledning i ton CO₂e <br /> (scope 1+2+3 + udenfor scopes) | G88: Emissions in tonnes of CO₂e <br /> (scope 1+2+3 + outside of scopes) | I88: Hovedresultater | K88: {=INDIRECT("'"&I88&"'!"&J88)} -> #REF! | M88: =IF(C88=K88,"OK","Reference fejl") -> #REF!
A89: calculation.mainresult.text.mainresult.table1.share-emission-scope1-3-outside | C89: =IF(Forside!$D$12="Dansk",Tekstnøgler!E89,Tekstnøgler!G89) -> Andel af udledning (scope 1+2+3 + udenfor scopes) | E89: Andel af udledning (scope 1+2+3 + udenfor scopes) | G89: Share of emissions (scope 1+2+3 + outside of scopes) | I89: Hovedresultater | K89: {=INDIRECT("'"&I89&"'!"&J89)} -> #REF! | M89: =IF(C89=K89,"OK","Reference fejl") -> #REF!
